Workbook
Name Accelera_Clear_SATIN_additional_topcoat: Epoxy!$T$170
Name Accelera_ClearEXT: Epoxy!$T$168
Name Accelera_PgmntEXT: Epoxy!$T$169
Name AT_Clear_Satin_w_Grit: Epoxy!$T$158
Name AT_ClearGloss_wGrit: Epoxy!$T$159
Name AT_ClearSatin_wGrit: Epoxy!$O$24
Name AT_Pgmt_Gloss_w_Grit: Epoxy!$T$161
Name AT_Pgmt_Satin_w_Grit: Epoxy!$T$160
Name ColorFast: Epoxy!$T$164
Name CoveRez: Epoxy!$T$152
Name Elast_O_Coat_Clear: Epoxy!$T$147
Name Fiberglass_Mat: Epoxy!$W$151
Name Gard_No_Sag: Epoxy!$T$150
Name GardReg: Epoxy!$T$149
Name Glaze4: Epoxy!$T$153
Name HP_Block_Filler_Primer: Epoxy!$T$174
Name HP_Eggshell_Topcoat: Epoxy!$T$175
Name HP_Gripper_Primer: Epoxy!$T$173
Name HP_Satin_Topcoat: Epoxy!$T$176
Name MACROFlake: Epoxy!$W$146
Name MD: Epoxy!$T$163
Name microFlake: Epoxy!$W$147
Name MVP: Epoxy!$T$146
Name NovolacGard: Epoxy!$T$155
Name OPF: Epoxy!$T$151
Name Q11_25a: Epoxy!$W$149
Name Q28_40s: Epoxy!$W$148
Name ShopFloor: Epoxy!$T$154
Name Silica: Epoxy!$W$145
Name SL: Epoxy!$T$162
Name TF_Reg: Epoxy!$T$165
Name WB: Epoxy!$T$145
Name WR: Epoxy!$T$167
Name ZincCoveCap: Epoxy!$W$150

Sheet Epoxy
A1: Project | G1: Bidding Contacts: | L1: MVP $ / SF Ranges: (08/2023)
A2: Bid Date | L2: 3 | M2: Standard
A3: Address | L3: 3.25 | M3: < 1,500 sf * | N3: * use your
A4: Local? | B4: Yes | C4: < 70 miles? | L4: 2.75 | M4: > 10,000 sf * | N4: discretion | AK4: 1000 | AN4: =AK4 | AQ4: =AK4+AN4 | AT4: =AQ4 | AU4: =IF(AK4<=#REF!,#REF!,IF(AK4<=#REF!,#REF!,IF(AK4<=#REF!,#REF!,IF(AK4<=#REF!,#REF!,IF(AK4<=#REF!,#REF!,IF(AK4<=#REF!,#REF!,IF(AK4<=#REF!,#REF!,0.05))))))) | AV4: =AU4*AK4 | AX4: =IF(AN4<=#REF!,#REF!,IF(AN4<=#REF!,#REF!,IF(AN4<=#REF!,#REF!,IF(AN4<=#REF!,#REF!,IF(AN4<=#REF!,#REF!,IF(AN4<=#REF!,#REF!,IF(AN4<=#REF!,#REF!,0.05))))))) | AY4: =AX4*AN4 | BA4: =IF(AQ4<=#REF!,#REF!,IF(AQ4<=#REF!,#REF!,IF(AQ4<=#REF!,#REF!,IF(AQ4<=#REF!,#REF!,IF(AQ4<=#REF!,#REF!,IF(AQ4<=#REF!,#REF!,IF(AQ4<=#REF!,#REF!,0.05))))))) | BB4: =BA4*SUM(AY4,AV4,AQ4) | BD4: =IF(AT4<=#REF!,#REF!,IF(AT4<=#REF!,#REF!,IF(AT4<=#REF!,#REF!,IF(AT4<=#REF!,#REF!,IF(AT4<=#REF!,#REF!,IF(AT4<=#REF!,#REF!,IF(AT4<=#REF!,#REF!,0.05))))))) | BE4: =BD4*AT4 | BG4: =0.07*SUM(AQ4,AV4,AY4,BB4,BE4) | BI4: =SUM(BG4,BE4,BB4,AY4,AV4,AQ4) | BJ4: =SUM(BE4,BB4,AY4,AV4) | BK4: =BJ4/BI4 | BN4: 0.1 | BO4: 5000 | BQ4: 0.35 | BR4: 2000 | BT4: 0.28 | BU4: 9000 | BW4: 0 | BX4: 9000 | CA4: 1000 | CD4: =CA4 | CG4: =CA4+CD4 | CJ4: =CG4 | CK4: =IF(CA4<=BO$4,BN$4,IF(CA4<=BO$5,BN$5,IF(CA4<=BO$6,BN$6,IF(CA4<=BO$7,BN$7,IF(CA4<=BO$12,BN$12,IF(CA4<=BO$13,BN$13,IF(CA4<=BO$14,BN$14,0.05))))))) | CL4: =CK4*CA4 | CN4: =IF(CD4<=BR$4,BQ$4,IF(CD4<=BR$5,BQ$5,IF(CD4<=BR$6,BQ$6,IF(CD4<=BR$7,BQ$7,IF(CD4<=BR$12,BQ$12,IF(CD4<=BR$13,BQ$13,IF(CD4<=BR$14,BQ$14,0.05))))))) | CO4: =CN4*CD4 | CQ4: =IF(CG4<=BU$4,BT$4,IF(CG4<=BU$5,BT$5,IF(CG4<=BU$6,BT$6,IF(CG4<=BU$7,BT$7,IF(CG4<=BU$12,BT$12,IF(CG4<=BU$13,BT$13,IF(CG4<=BU$14,BT$14,0.05))))))) | CR4: =CQ4*SUM(CO4,CL4,CG4) | CT4: =IF(CJ4<=BX$4,BW$4,IF(CJ4<=BX$5,BW$5,IF(CJ4<=BX$6,BW$6,IF(CJ4<=BX$7,BW$7,IF(CJ4<=BX$12,BW$12,IF(CJ4<=BX$13,BW$13,IF(CJ4<=BX$14,BW$14,0.05))))))) | CU4: =CT4*CJ4 | CW4: =0.07*SUM(CG4,CL4,CO4,CR4,CU4) | CY4: =SUM(CW4,CU4,CR4,CO4,CL4,CG4) | CZ4: =SUM(CU4,CR4,CO4,CL4) | DA4: =CZ4/CY4
A5: Hard Bid? | B5: No | C5: PrevailingWage? | D5: No | AK5: 2000 | AN5: =AK5 | AQ5: =AK5+AN5 | AT5: =AQ5 | AU5: =IF(AK5<=#REF!,#REF!,IF(AK5<=#REF!,#REF!,IF(AK5<=#REF!,#REF!,IF(AK5<=#REF!,#REF!,IF(AK5<=#REF!,#REF!,IF(AK5<=#REF!,#REF!,IF(AK5<=#REF!,#REF!,0.05))))))) | AV5: =AU5*AK5 | AX5: =IF(AN5<=#REF!,#REF!,IF(AN5<=#REF!,#REF!,IF(AN5<=#REF!,#REF!,IF(AN5<=#REF!,#REF!,IF(AN5<=#REF!,#REF!,IF(AN5<=#REF!,#REF!,IF(AN5<=#REF!,#REF!,0.05))))))) | AY5: =AX5*AN5 | BA5: =IF(AQ5<=#REF!,#REF!,IF(AQ5<=#REF!,#REF!,IF(AQ5<=#REF!,#REF!,IF(AQ5<=#REF!,#REF!,IF(AQ5<=#REF!,#REF!,IF(AQ5<=#REF!,#REF!,IF(AQ5<=#REF!,#REF!,0.05))))))) | BB5: =BA5*SUM(AY5,AV5,AQ5) | BD5: =IF(AT5<=#REF!,#REF!,IF(AT5<=#REF!,#REF!,IF(AT5<=#REF!,#REF!,IF(AT5<=#REF!,#REF!,IF(AT5<=#REF!,#REF!,IF(AT5<=#REF!,#REF!,IF(AT5<=#REF!,#REF!,0.05))))))) | BE5: =BD5*AT5 | BG5: =0.07*SUM(AQ5,AV5,AY5,BB5,BE5) | BI5: =SUM(BG5,BE5,BB5,AY5,AV5,AQ5) | BJ5: =SUM(BE5,BB5,AY5,AV5) | BK5: =BJ5/BI5 | BN5: 0.05 | BO5: 1000000000 | BQ5: 0.3 | BR5: 3000 | BT5: 0.24 | BU5: 14000 | BW5: -0.04 | BX5: 14000 | CA5: 2000 | CD5: =CA5 | CG5: =CA5+CD5 | CJ5: =CG5 | CK5: =IF(CA5<=BO$4,BN$4,IF(CA5<=BO$5,BN$5,IF(CA5<=BO$6,BN$6,IF(CA5<=BO$7,BN$7,IF(CA5<=BO$12,BN$12,IF(CA5<=BO$13,BN$13,IF(CA5<=BO$14,BN$14,0.05))))))) | CL5: =CK5*CA5 | CN5: =IF(CD5<=BR$4,BQ$4,IF(CD5<=BR$5,BQ$5,IF(CD5<=BR$6,BQ$6,IF(CD5<=BR$7,BQ$7,IF(CD5<=BR$12,BQ$12,IF(CD5<=BR$13,BQ$13,IF(CD5<=BR$14,BQ$14,0.05))))))) | CO5: =CN5*CD5 | CQ5: =IF(CG5<=BU$4,BT$4,IF(CG5<=BU$5,BT$5,IF(CG5<=BU$6,BT$6,IF(CG5<=BU$7,BT$7,IF(CG5<=BU$12,BT$12,IF(CG5<=BU$13,BT$13,IF(CG5<=BU$14,BT$14,0.05))))))) | CR5: =CQ5*SUM(CO5,CL5,CG5) | CT5: =IF(CJ5<=BX$4,BW$4,IF(CJ5<=BX$5,BW$5,IF(CJ5<=BX$6,BW$6,IF(CJ5<=BX$7,BW$7,IF(CJ5<=BX$12,BW$12,IF(CJ5<=BX$13,BW$13,IF(CJ5<=BX$14,BW$14,0.05))))))) | CU5: =CT5*CJ5 | CW5: =0.07*SUM(CG5,CL5,CO5,CR5,CU5) | CY5: =SUM(CW5,CU5,CR5,CO5,CL5,CG5) | CZ5: =SUM(CU5,CR5,CO5,CL5) | DA5: =CZ5/CY5
A6: Taxable? | B6: Yes | C6: Remodel Tax? | D6: No | AK6: 3000 | AN6: =AK6 | AQ6: =AK6+AN6 | AT6: =AQ6 | AU6: =IF(AK6<=#REF!,#REF!,IF(AK6<=#REF!,#REF!,IF(AK6<=#REF!,#REF!,IF(AK6<=#REF!,#REF!,IF(AK6<=#REF!,#REF!,IF(AK6<=#REF!,#REF!,IF(AK6<=#REF!,#REF!,0.05))))))) | AV6: =AU6*AK6 | AX6: =IF(AN6<=#REF!,#REF!,IF(AN6<=#REF!,#REF!,IF(AN6<=#REF!,#REF!,IF(AN6<=#REF!,#REF!,IF(AN6<=#REF!,#REF!,IF(AN6<=#REF!,#REF!,IF(AN6<=#REF!,#REF!,0.05))))))) | AY6: =AX6*AN6 | BA6: =IF(AQ6<=#REF!,#REF!,IF(AQ6<=#REF!,#REF!,IF(AQ6<=#REF!,#REF!,IF(AQ6<=#REF!,#REF!,IF(AQ6<=#REF!,#REF!,IF(AQ6<=#REF!,#REF!,IF(AQ6<=#REF!,#REF!,0.05))))))) | BB6: =BA6*SUM(AY6,AV6,AQ6) | BD6: =IF(AT6<=#REF!,#REF!,IF(AT6<=#REF!,#REF!,IF(AT6<=#REF!,#REF!,IF(AT6<=#REF!,#REF!,IF(AT6<=#REF!,#REF!,IF(AT6<=#REF!,#REF!,IF(AT6<=#REF!,#REF!,0.05))))))) | BE6: =BD6*AT6 | BG6: =0.07*SUM(AQ6,AV6,AY6,BB6,BE6) | BI6: =SUM(BG6,BE6,BB6,AY6,AV6,AQ6) | BJ6: =SUM(BE6,BB6,AY6,AV6) | BK6: =BJ6/BI6 | BN6: 0.05 | BO6: 1000000000 | BQ6: 0.2 | BR6: 4000 | BT6: 0.22 | BU6: 19000 | BW6: -0.05 | BX6: 19000 | CA6: 3000 | CD6: =CA6 | CG6: =CA6+CD6 | CJ6: =CG6 | CK6: =IF(CA6<=BO$4,BN$4,IF(CA6<=BO$5,BN$5,IF(CA6<=BO$6,BN$6,IF(CA6<=BO$7,BN$7,IF(CA6<=BO$12,BN$12,IF(CA6<=BO$13,BN$13,IF(CA6<=BO$14,BN$14,0.05))))))) | CL6: =CK6*CA6 | CN6: =IF(CD6<=BR$4,BQ$4,IF(CD6<=BR$5,BQ$5,IF(CD6<=BR$6,BQ$6,IF(CD6<=BR$7,BQ$7,IF(CD6<=BR$12,BQ$12,IF(CD6<=BR$13,BQ$13,IF(CD6<=BR$14,BQ$14,0.05))))))) | CO6: =CN6*CD6 | CQ6: =IF(CG6<=BU$4,BT$4,IF(CG6<=BU$5,BT$5,IF(CG6<=BU$6,BT$6,IF(CG6<=BU$7,BT$7,IF(CG6<=BU$12,BT$12,IF(CG6<=BU$13,BT$13,IF(CG6<=BU$14,BT$14,0.05))))))) | CR6: =CQ6*SUM(CO6,CL6,CG6) | CT6: =IF(CJ6<=BX$4,BW$4,IF(CJ6<=BX$5,BW$5,IF(CJ6<=BX$6,BW$6,IF(CJ6<=BX$7,BW$7,IF(CJ6<=BX$12,BW$12,IF(CJ6<=BX$13,BW$13,IF(CJ6<=BX$14,BW$14,0.05))))))) | CU6: =CT6*CJ6 | CW6: =0.07*SUM(CG6,CL6,CO6,CR6,CU6) | CY6: =SUM(CW6,CU6,CR6,CO6,CL6,CG6) | CZ6: =SUM(CU6,CR6,CO6,CL6) | DA6: =CZ6/CY6
A7: Approx Start Date | AK7: 4000 | AN7: =AK7 | AQ7: =AK7+AN7 | AT7: =AQ7 | AU7: =IF(AK7<=#REF!,#REF!,IF(AK7<=#REF!,#REF!,IF(AK7<=#REF!,#REF!,IF(AK7<=#REF!,#REF!,IF(AK7<=#REF!,#REF!,IF(AK7<=#REF!,#REF!,IF(AK7<=#REF!,#REF!,0.05))))))) | AV7: =AU7*AK7 | AX7: =IF(AN7<=#REF!,#REF!,IF(AN7<=#REF!,#REF!,IF(AN7<=#REF!,#REF!,IF(AN7<=#REF!,#REF!,IF(AN7<=#REF!,#REF!,IF(AN7<=#REF!,#REF!,IF(AN7<=#REF!,#REF!,0.05))))))) | AY7: =AX7*AN7 | BA7: =IF(AQ7<=#REF!,#REF!,IF(AQ7<=#REF!,#REF!,IF(AQ7<=#REF!,#REF!,IF(AQ7<=#REF!,#REF!,IF(AQ7<=#REF!,#REF!,IF(AQ7<=#REF!,#REF!,IF(AQ7<=#REF!,#REF!,0.05))))))) | BB7: =BA7*SUM(AY7,AV7,AQ7) | BD7: =IF(AT7<=#REF!,#REF!,IF(AT7<=#REF!,#REF!,IF(AT7<=#REF!,#REF!,IF(AT7<=#REF!,#REF!,IF(AT7<=#REF!,#REF!,IF(AT7<=#REF!,#REF!,IF(AT7<=#REF!,#REF!,0.05))))))) | BE7: =BD7*AT7 | BG7: =0.07*SUM(AQ7,AV7,AY7,BB7,BE7) | BI7: =SUM(BG7,BE7,BB7,AY7,AV7,AQ7) | BJ7: =SUM(BE7,BB7,AY7,AV7) | BK7: =BJ7/BI7 | BN7: 0.05 | BO7: 1000000000 | BQ7: 0.1 | BR7: 7000 | BT7: 0.2 | BU7: 24000 | BW7: -0.05 | BX7: 34000 | CA7: 4000 | CD7: =CA7 | CG7: =CA7+CD7 | CJ7: =CG7 | CK7: =IF(CA7<=BO$4,BN$4,IF(CA7<=BO$5,BN$5,IF(CA7<=BO$6,BN$6,IF(CA7<=BO$7,BN$7,IF(CA7<=BO$12,BN$12,IF(CA7<=BO$13,BN$13,IF(CA7<=BO$14,BN$14,0.05))))))) | CL7: =CK7*CA7 | CN7: =IF(CD7<=BR$4,BQ$4,IF(CD7<=BR$5,BQ$5,IF(CD7<=BR$6,BQ$6,IF(CD7<=BR$7,BQ$7,IF(CD7<=BR$12,BQ$12,IF(CD7<=BR$13,BQ$13,IF(CD7<=BR$14,BQ$14,0.05))))))) | CO7: =CN7*CD7 | CQ7: =IF(CG7<=BU$4,BT$4,IF(CG7<=BU$5,BT$5,IF(CG7<=BU$6,BT$6,IF(CG7<=BU$7,BT$7,IF(CG7<=BU$12,BT$12,IF(CG7<=BU$13,BT$13,IF(CG7<=BU$14,BT$14,0.05))))))) | CR7: =CQ7*SUM(CO7,CL7,CG7) | CT7: =IF(CJ7<=BX$4,BW$4,IF(CJ7<=BX$5,BW$5,IF(CJ7<=BX$6,BW$6,IF(CJ7<=BX$7,BW$7,IF(CJ7<=BX$12,BW$12,IF(CJ7<=BX$13,BW$13,IF(CJ7<=BX$14,BW$14,0.05))))))) | CU7: =CT7*CJ7 | CW7: =0.07*SUM(CG7,CL7,CO7,CR7,CU7) | CY7: =SUM(CW7,CU7,CR7,CO7,CL7,CG7) | CZ7: =SUM(CU7,CR7,CO7,CL7) | DA7: =CZ7/CY7
A8: Architect
A9: Drawings Dated
A10: New / Reno:
A12: Floor System- Epoxy: | AK12: 5000 | AN12: =AK12 | AQ12: =AK12+AN12 | AT12: =AQ12 | AU12: =IF(AK12<=#REF!,#REF!,IF(AK12<=#REF!,#REF!,IF(AK12<=#REF!,#REF!,IF(AK12<=#REF!,#REF!,IF(AK12<=#REF!,#REF!,IF(AK12<=#REF!,#REF!,IF(AK12<=#REF!,#REF!,0.05))))))) | AV12: =AU12*AK12 | AX12: =IF(AN12<=#REF!,#REF!,IF(AN12<=#REF!,#REF!,IF(AN12<=#REF!,#REF!,IF(AN12<=#REF!,#REF!,IF(AN12<=#REF!,#REF!,IF(AN12<=#REF!,#REF!,IF(AN12<=#REF!,#REF!,0.05))))))) | AY12: =AX12*AN12 | BA12: =IF(AQ12<=#REF!,#REF!,IF(AQ12<=#REF!,#REF!,IF(AQ12<=#REF!,#REF!,IF(AQ12<=#REF!,#REF!,IF(AQ12<=#REF!,#REF!,IF(AQ12<=#REF!,#REF!,IF(AQ12<=#REF!,#REF!,0.05))))))) | BB12: =BA12*SUM(AY12,AV12,AQ12) | BD12: =IF(AT12<=#REF!,#REF!,IF(AT12<=#REF!,#REF!,IF(AT12<=#REF!,#REF!,IF(AT12<=#REF!,#REF!,IF(AT12<=#REF!,#REF!,IF(AT12<=#REF!,#REF!,IF(AT12<=#REF!,#REF!,0.05))))))) | BE12: =BD12*AT12 | BG12: =0.07*SUM(AQ12,AV12,AY12,BB12,BE12) | BI12: =SUM(BG12,BE12,BB12,AY12,AV12,AQ12) | BJ12: =SUM(BE12,BB12,AY12,AV12) | BK12: =BJ12/BI12 | BN12: 0.05 | BO12: 1000000000 | BQ12: 0.05 | BR12: 10000 | BT12: 0.18 | BU12: 1000000000 | BW12: -0.055 | BX12: 44000 | CA12: 5000 | CD12: =CA12 | CG12: =CA12+CD12 | CJ12: =CG12 | CK12: =IF(CA12<=BO$4,BN$4,IF(CA12<=BO$5,BN$5,IF(CA12<=BO$6,BN$6,IF(CA12<=BO$7,BN$7,IF(CA12<=BO$12,BN$12,IF(CA12<=BO$13,BN$13,IF(CA12<=BO$14,BN$14,0.05))))))) | CL12: =CK12*CA12 | CN12: =IF(CD12<=BR$4,BQ$4,IF(CD12<=BR$5,BQ$5,IF(CD12<=BR$6,BQ$6,IF(CD12<=BR$7,BQ$7,IF(CD12<=BR$12,BQ$12,IF(CD12<=BR$13,BQ$13,IF(CD12<=BR$14,BQ$14,0.05))))))) | CO12: =CN12*CD12 | CQ12: =IF(CG12<=BU$4,BT$4,IF(CG12<=BU$5,BT$5,IF(CG12<=BU$6,BT$6,IF(CG12<=BU$7,BT$7,IF(CG12<=BU$12,BT$12,IF(CG12<=BU$13,BT$13,IF(CG12<=BU$14,BT$14,0.05))))))) | CR12: =CQ12*SUM(CO12,CL12,CG12) | CT12: =IF(CJ12<=BX$4,BW$4,IF(CJ12<=BX$5,BW$5,IF(CJ12<=BX$6,BW$6,IF(CJ12<=BX$7,BW$7,IF(CJ12<=BX$12,BW$12,IF(CJ12<=BX$13,BW$13,IF(CJ12<=BX$14,BW$14,0.05))))))) | CU12: =CT12*CJ12 | CW12: =0.07*SUM(CG12,CL12,CO12,CR12,CU12) | CY12: =SUM(CW12,CU12,CR12,CO12,CL12,CG12) | CZ12: =SUM(CU12,CR12,CO12,CL12) | DA12: =CZ12/CY12
A13: Cove: | AK13: 6000 | AN13: =AK13 | AQ13: =AK13+AN13 | AT13: =AQ13 | AU13: =IF(AK13<=#REF!,#REF!,IF(AK13<=#REF!,#REF!,IF(AK13<=#REF!,#REF!,IF(AK13<=#REF!,#REF!,IF(AK13<=#REF!,#REF!,IF(AK13<=#REF!,#REF!,IF(AK13<=#REF!,#REF!,0.05))))))) | AV13: =AU13*AK13 | AX13: =IF(AN13<=#REF!,#REF!,IF(AN13<=#REF!,#REF!,IF(AN13<=#REF!,#REF!,IF(AN13<=#REF!,#REF!,IF(AN13<=#REF!,#REF!,IF(AN13<=#REF!,#REF!,IF(AN13<=#REF!,#REF!,0.05))))))) | AY13: =AX13*AN13 | BA13: =IF(AQ13<=#REF!,#REF!,IF(AQ13<=#REF!,#REF!,IF(AQ13<=#REF!,#REF!,IF(AQ13<=#REF!,#REF!,IF(AQ13<=#REF!,#REF!,IF(AQ13<=#REF!,#REF!,IF(AQ13<=#REF!,#REF!,0.05))))))) | BB13: =BA13*SUM(AY13,AV13,AQ13) | BD13: =IF(AT13<=#REF!,#REF!,IF(AT13<=#REF!,#REF!,IF(AT13<=#REF!,#REF!,IF(AT13<=#REF!,#REF!,IF(AT13<=#REF!,#REF!,IF(AT13<=#REF!,#REF!,IF(AT13<=#REF!,#REF!,0.05))))))) | BE13: =BD13*AT13 | BG13: =0.07*SUM(AQ13,AV13,AY13,BB13,BE13) | BI13: =SUM(BG13,BE13,BB13,AY13,AV13,AQ13) | BJ13: =SUM(BE13,BB13,AY13,AV13) | BK13: =BJ13/BI13 | BN13: 0.05 | BO13: 1000000000 | BQ13: 0.03 | BR13: 1000000000 | BT13: 0.18 | BU13: 1000000000 | BW13: -0.06 | BX13: 1000000000 | CA13: 6000 | CD13: =CA13 | CG13: =CA13+CD13 | CJ13: =CG13 | CK13: =IF(CA13<=BO$4,BN$4,IF(CA13<=BO$5,BN$5,IF(CA13<=BO$6,BN$6,IF(CA13<=BO$7,BN$7,IF(CA13<=BO$12,BN$12,IF(CA13<=BO$13,BN$13,IF(CA13<=BO$14,BN$14,0.05))))))) | CL13: =CK13*CA13 | CN13: =IF(CD13<=BR$4,BQ$4,IF(CD13<=BR$5,BQ$5,IF(CD13<=BR$6,BQ$6,IF(CD13<=BR$7,BQ$7,IF(CD13<=BR$12,BQ$12,IF(CD13<=BR$13,BQ$13,IF(CD13<=BR$14,BQ$14,0.05))))))) | CO13: =CN13*CD13 | CQ13: =IF(CG13<=BU$4,BT$4,IF(CG13<=BU$5,BT$5,IF(CG13<=BU$6,BT$6,IF(CG13<=BU$7,BT$7,IF(CG13<=BU$12,BT$12,IF(CG13<=BU$13,BT$13,IF(CG13<=BU$14,BT$14,0.05))))))) | CR13: =CQ13*SUM(CO13,CL13,CG13) | CT13: =IF(CJ13<=BX$4,BW$4,IF(CJ13<=BX$5,BW$5,IF(CJ13<=BX$6,BW$6,IF(CJ13<=BX$7,BW$7,IF(CJ13<=BX$12,BW$12,IF(CJ13<=BX$13,BW$13,IF(CJ13<=BX$14,BW$14,0.05))))))) | CU13: =CT13*CJ13 | CW13: =0.07*SUM(CG13,CL13,CO13,CR13,CU13) | CY13: =SUM(CW13,CU13,CR13,CO13,CL13,CG13) | CZ13: =SUM(CU13,CR13,CO13,CL13) | DA13: =CZ13/CY13
A14: ? - Walls: | AK14: 7000 | AN14: =AK14 | AQ14: =AK14+AN14 | AT14: =AQ14 | AU14: =IF(AK14<=#REF!,#REF!,IF(AK14<=#REF!,#REF!,IF(AK14<=#REF!,#REF!,IF(AK14<=#REF!,#REF!,IF(AK14<=#REF!,#REF!,IF(AK14<=#REF!,#REF!,IF(AK14<=#REF!,#REF!,0.05))))))) | AV14: =AU14*AK14 | AX14: =IF(AN14<=#REF!,#REF!,IF(AN14<=#REF!,#REF!,IF(AN14<=#REF!,#REF!,IF(AN14<=#REF!,#REF!,IF(AN14<=#REF!,#REF!,IF(AN14<=#REF!,#REF!,IF(AN14<=#REF!,#REF!,0.05))))))) | AY14: =AX14*AN14 | BA14: =IF(AQ14<=#REF!,#REF!,IF(AQ14<=#REF!,#REF!,IF(AQ14<=#REF!,#REF!,IF(AQ14<=#REF!,#REF!,IF(AQ14<=#REF!,#REF!,IF(AQ14<=#REF!,#REF!,IF(AQ14<=#REF!,#REF!,0.05))))))) | BB14: =BA14*SUM(AY14,AV14,AQ14) | BD14: =IF(AT14<=#REF!,#REF!,IF(AT14<=#REF!,#REF!,IF(AT14<=#REF!,#REF!,IF(AT14<=#REF!,#REF!,IF(AT14<=#REF!,#REF!,IF(AT14<=#REF!,#REF!,IF(AT14<=#REF!,#REF!,0.05))))))) | BE14: =BD14*AT14 | BG14: =0.07*SUM(AQ14,AV14,AY14,BB14,BE14) | BI14: =SUM(BG14,BE14,BB14,AY14,AV14,AQ14) | BJ14: =SUM(BE14,BB14,AY14,AV14) | BK14: =BJ14/BI14 | BN14: 0.05 | BO14: 1000000000 | BQ14: 0.03 | BR14: 1000000000 | BT14: 0.18 | BU14: 1000000000 | BW14: 0 | BX14: 1000000000 | CA14: 7000 | CD14: =CA14 | CG14: =CA14+CD14 | CJ14: =CG14 | CK14: =IF(CA14<=BO$4,BN$4,IF(CA14<=BO$5,BN$5,IF(CA14<=BO$6,BN$6,IF(CA14<=BO$7,BN$7,IF(CA14<=BO$12,BN$12,IF(CA14<=BO$13,BN$13,IF(CA14<=BO$14,BN$14,0.05))))))) | CL14: =CK14*CA14 | CN14: =IF(CD14<=BR$4,BQ$4,IF(CD14<=BR$5,BQ$5,IF(CD14<=BR$6,BQ$6,IF(CD14<=BR$7,BQ$7,IF(CD14<=BR$12,BQ$12,IF(CD14<=BR$13,BQ$13,IF(CD14<=BR$14,BQ$14,0.05))))))) | CO14: =CN14*CD14 | CQ14: =IF(CG14<=BU$4,BT$4,IF(CG14<=BU$5,BT$5,IF(CG14<=BU$6,BT$6,IF(CG14<=BU$7,BT$7,IF(CG14<=BU$12,BT$12,IF(CG14<=BU$13,BT$13,IF(CG14<=BU$14,BT$14,0.05))))))) | CR14: =CQ14*SUM(CO14,CL14,CG14) | CT14: =IF(CJ14<=BX$4,BW$4,IF(CJ14<=BX$5,BW$5,IF(CJ14<=BX$6,BW$6,IF(CJ14<=BX$7,BW$7,IF(CJ14<=BX$12,BW$12,IF(CJ14<=BX$13,BW$13,IF(CJ14<=BX$14,BW$14,0.05))))))) | CU14: =CT14*CJ14 | CW14: =0.07*SUM(CG14,CL14,CO14,CR14,CU14) | CY14: =SUM(CW14,CU14,CR14,CO14,CL14,CG14) | CZ14: =SUM(CU14,CR14,CO14,CL14) | DA14: =CZ14/CY14
AK15: 8000 | AN15: =AK15 | AQ15: =AK15+AN15 | AT15: =AQ15 | AU15: =IF(AK15<=#REF!,#REF!,IF(AK15<=#REF!,#REF!,IF(AK15<=#REF!,#REF!,IF(AK15<=#REF!,#REF!,IF(AK15<=#REF!,#REF!,IF(AK15<=#REF!,#REF!,IF(AK15<=#REF!,#REF!,0.05))))))) | AV15: =AU15*AK15 | AX15: =IF(AN15<=#REF!,#REF!,IF(AN15<=#REF!,#REF!,IF(AN15<=#REF!,#REF!,IF(AN15<=#REF!,#REF!,IF(AN15<=#REF!,#REF!,IF(AN15<=#REF!,#REF!,IF(AN15<=#REF!,#REF!,0.05))))))) | AY15: =AX15*AN15 | BA15: =IF(AQ15<=#REF!,#REF!,IF(AQ15<=#REF!,#REF!,IF(AQ15<=#REF!,#REF!,IF(AQ15<=#REF!,#REF!,IF(AQ15<=#REF!,#REF!,IF(AQ15<=#REF!,#REF!,IF(AQ15<=#REF!,#REF!,0.05))))))) | BB15: =BA15*SUM(AY15,AV15,AQ15) | BD15: =IF(AT15<=#REF!,#REF!,IF(AT15<=#REF!,#REF!,IF(AT15<=#REF!,#REF!,IF(AT15<=#REF!,#REF!,IF(AT15<=#REF!,#REF!,IF(AT15<=#REF!,#REF!,IF(AT15<=#REF!,#REF!,0.05))))))) | BE15: =BD15*AT15 | BG15: =0.07*SUM(AQ15,AV15,AY15,BB15,BE15) | BI15: =SUM(BG15,BE15,BB15,AY15,AV15,AQ15) | BJ15: =SUM(BE15,BB15,AY15,AV15) | BK15: =BJ15/BI15 | CA15: 8000 | CD15: =CA15 | CG15: =CA15+CD15 | CJ15: =CG15 | CK15: =IF(CA15<=BO$4,BN$4,IF(CA15<=BO$5,BN$5,IF(CA15<=BO$6,BN$6,IF(CA15<=BO$7,BN$7,IF(CA15<=BO$12,BN$12,IF(CA15<=BO$13,BN$13,IF(CA15<=BO$14,BN$14,0.05))))))) | CL15: =CK15*CA15 | CN15: =IF(CD15<=BR$4,BQ$4,IF(CD15<=BR$5,BQ$5,IF(CD15<=BR$6,BQ$6,IF(CD15<=BR$7,BQ$7,IF(CD15<=BR$12,BQ$12,IF(CD15<=BR$13,BQ$13,IF(CD15<=BR$14,BQ$14,0.05))))))) | CO15: =CN15*CD15 | CQ15: =IF(CG15<=BU$4,BT$4,IF(CG15<=BU$5,BT$5,IF(CG15<=BU$6,BT$6,IF(CG15<=BU$7,BT$7,IF(CG15<=BU$12,BT$12,IF(CG15<=BU$13,BT$13,IF(CG15<=BU$14,BT$14,0.05))))))) | CR15: =CQ15*SUM(CO15,CL15,CG15) | CT15: =IF(CJ15<=BX$4,BW$4,IF(CJ15<=BX$5,BW$5,IF(CJ15<=BX$6,BW$6,IF(CJ15<=BX$7,BW$7,IF(CJ15<=BX$12,BW$12,IF(CJ15<=BX$13,BW$13,IF(CJ15<=BX$14,BW$14,0.05))))))) | CU15: =CT15*CJ15 | CW15: =0.07*SUM(CG15,CL15,CO15,CR15,CU15) | CY15: =SUM(CW15,CU15,CR15,CO15,CL15,CG15) | CZ15: =SUM(CU15,CR15,CO15,CL15) | DA15: =CZ15/CY15
A16: Total Base Bid: | B16: =D88 | C16: $ / SF: | D16: =C88 | AK16: 9000 | AN16: =AK16 | AQ16: =AK16+AN16 | AT16: =AQ16 | AU16: =IF(AK16<=#REF!,#REF!,IF(AK16<=#REF!,#REF!,IF(AK16<=#REF!,#REF!,IF(AK16<=#REF!,#REF!,IF(AK16<=#REF!,#REF!,IF(AK16<=#REF!,#REF!,IF(AK16<=#REF!,#REF!,0.05))))))) | AV16: =AU16*AK16 | AX16: =IF(AN16<=#REF!,#REF!,IF(AN16<=#REF!,#REF!,IF(AN16<=#REF!,#REF!,IF(AN16<=#REF!,#REF!,IF(AN16<=#REF!,#REF!,IF(AN16<=#REF!,#REF!,IF(AN16<=#REF!,#REF!,0.05))))))) | AY16: =AX16*AN16 | BA16: =IF(AQ16<=#REF!,#REF!,IF(AQ16<=#REF!,#REF!,IF(AQ16<=#REF!,#REF!,IF(AQ16<=#REF!,#REF!,IF(AQ16<=#REF!,#REF!,IF(AQ16<=#REF!,#REF!,IF(AQ16<=#REF!,#REF!,0.05))))))) | BB16: =BA16*SUM(AY16,AV16,AQ16) | BD16: =IF(AT16<=#REF!,#REF!,IF(AT16<=#REF!,#REF!,IF(AT16<=#REF!,#REF!,IF(AT16<=#REF!,#REF!,IF(AT16<=#REF!,#REF!,IF(AT16<=#REF!,#REF!,IF(AT16<=#REF!,#REF!,0.05))))))) | BE16: =BD16*AT16 | BG16: =0.07*SUM(AQ16,AV16,AY16,BB16,BE16) | BI16: =SUM(BG16,BE16,BB16,AY16,AV16,AQ16) | BJ16: =SUM(BE16,BB16,AY16,AV16) | BK16: =BJ16/BI16 | CA16: 9000 | CD16: =CA16 | CG16: =CA16+CD16 | CJ16: =CG16 | CK16: =IF(CA16<=BO$4,BN$4,IF(CA16<=BO$5,BN$5,IF(CA16<=BO$6,BN$6,IF(CA16<=BO$7,BN$7,IF(CA16<=BO$12,BN$12,IF(CA16<=BO$13,BN$13,IF(CA16<=BO$14,BN$14,0.05))))))) | CL16: =CK16*CA16 | CN16: =IF(CD16<=BR$4,BQ$4,IF(CD16<=BR$5,BQ$5,IF(CD16<=BR$6,BQ$6,IF(CD16<=BR$7,BQ$7,IF(CD16<=BR$12,BQ$12,IF(CD16<=BR$13,BQ$13,IF(CD16<=BR$14,BQ$14,0.05))))))) | CO16: =CN16*CD16 | CQ16: =IF(CG16<=BU$4,BT$4,IF(CG16<=BU$5,BT$5,IF(CG16<=BU$6,BT$6,IF(CG16<=BU$7,BT$7,IF(CG16<=BU$12,BT$12,IF(CG16<=BU$13,BT$13,IF(CG16<=BU$14,BT$14,0.05))))))) | CR16: =CQ16*SUM(CO16,CL16,CG16) | CT16: =IF(CJ16<=BX$4,BW$4,IF(CJ16<=BX$5,BW$5,IF(CJ16<=BX$6,BW$6,IF(CJ16<=BX$7,BW$7,IF(CJ16<=BX$12,BW$12,IF(CJ16<=BX$13,BW$13,IF(CJ16<=BX$14,BW$14,0.05))))))) | CU16: =CT16*CJ16 | CW16: =0.07*SUM(CG16,CL16,CO16,CR16,CU16) | CY16: =SUM(CW16,CU16,CR16,CO16,CL16,CG16) | CZ16: =SUM(CU16,CR16,CO16,CL16) | DA16: =CZ16/CY16
A17: MATERIAL - Patch | B17: Quantity | C17: Cost | D17: Total | H17: Standard Add's | I17: Cost / Unit | J17: SF -or- LF | K17: Total | AK17: 10000 | AN17: =AK17 | AQ17: =AK17+AN17 | AT17: =AQ17 | AU17: =IF(AK17<=#REF!,#REF!,IF(AK17<=#REF!,#REF!,IF(AK17<=#REF!,#REF!,IF(AK17<=#REF!,#REF!,IF(AK17<=#REF!,#REF!,IF(AK17<=#REF!,#REF!,IF(AK17<=#REF!,#REF!,0.05))))))) | AV17: =AU17*AK17 | AX17: =IF(AN17<=#REF!,#REF!,IF(AN17<=#REF!,#REF!,IF(AN17<=#REF!,#REF!,IF(AN17<=#REF!,#REF!,IF(AN17<=#REF!,#REF!,IF(AN17<=#REF!,#REF!,IF(AN17<=#REF!,#REF!,0.05))))))) | AY17: =AX17*AN17 | BA17: =IF(AQ17<=#REF!,#REF!,IF(AQ17<=#REF!,#REF!,IF(AQ17<=#REF!,#REF!,IF(AQ17<=#REF!,#REF!,IF(AQ17<=#REF!,#REF!,IF(AQ17<=#REF!,#REF!,IF(AQ17<=#REF!,#REF!,0.05))))))) | BB17: =BA17*SUM(AY17,AV17,AQ17) | BD17: =IF(AT17<=#REF!,#REF!,IF(AT17<=#REF!,#REF!,IF(AT17<=#REF!,#REF!,IF(AT17<=#REF!,#REF!,IF(AT17<=#REF!,#REF!,IF(AT17<=#REF!,#REF!,IF(AT17<=#REF!,#REF!,0.05))))))) | BE17: =BD17*AT17 | BG17: =0.07*SUM(AQ17,AV17,AY17,BB17,BE17) | BI17: =SUM(BG17,BE17,BB17,AY17,AV17,AQ17) | BJ17: =SUM(BE17,BB17,AY17,AV17) | BK17: =BJ17/BI17 | CA17: 10000 | CD17: =CA17 | CG17: =CA17+CD17 | CJ17: =CG17 | CK17: =IF(CA17<=BO$4,BN$4,IF(CA17<=BO$5,BN$5,IF(CA17<=BO$6,BN$6,IF(CA17<=BO$7,BN$7,IF(CA17<=BO$12,BN$12,IF(CA17<=BO$13,BN$13,IF(CA17<=BO$14,BN$14,0.05))))))) | CL17: =CK17*CA17 | CN17: =IF(CD17<=BR$4,BQ$4,IF(CD17<=BR$5,BQ$5,IF(CD17<=BR$6,BQ$6,IF(CD17<=BR$7,BQ$7,IF(CD17<=BR$12,BQ$12,IF(CD17<=BR$13,BQ$13,IF(CD17<=BR$14,BQ$14,0.05))))))) | CO17: =CN17*CD17 | CQ17: =IF(CG17<=BU$4,BT$4,IF(CG17<=BU$5,BT$5,IF(CG17<=BU$6,BT$6,IF(CG17<=BU$7,BT$7,IF(CG17<=BU$12,BT$12,IF(CG17<=BU$13,BT$13,IF(CG17<=BU$14,BT$14,0.05))))))) | CR17: =CQ17*SUM(CO17,CL17,CG17) | CT17: =IF(CJ17<=BX$4,BW$4,IF(CJ17<=BX$5,BW$5,IF(CJ17<=BX$6,BW$6,IF(CJ17<=BX$7,BW$7,IF(CJ17<=BX$12,BW$12,IF(CJ17<=BX$13,BW$13,IF(CJ17<=BX$14,BW$14,0.05))))))) | CU17: =CT17*CJ17 | CW17: =0.07*SUM(CG17,CL17,CO17,CR17,CU17) | CY17: =SUM(CW17,CU17,CR17,CO17,CL17,CG17) | CZ17: =SUM(CU17,CR17,CO17,CL17) | DA17: =CZ17/CY17
A18: system 1 | B18: =E20 | C18: 0.1 | D18: =B18*C18 | H18: Ram Board | I18: =IF(J18<=1000,validation!$R$4,IF(J18<1500,validation!$R$6,IF(J18<2000,validation!$R$8,IF(J18<2500,validation!$R$10,IF(J18<=3000,validation!$R$12,IF(J18<3500,validation!$R$14,IF(J18<4000,validation!$R$16,IF(J18<5000,validation!$R$18,validation!$R$20)))))))) | J18: =B45 | K18: =ROUNDUP((I18*J18),0) | L18: LF | M18: $ / LF | AK18: 11000 | AN18: =AK18 | AQ18: =AK18+AN18 | AT18: =AQ18 | AU18: =IF(AK18<=#REF!,#REF!,IF(AK18<=#REF!,#REF!,IF(AK18<=#REF!,#REF!,IF(AK18<=#REF!,#REF!,IF(AK18<=#REF!,#REF!,IF(AK18<=#REF!,#REF!,IF(AK18<=#REF!,#REF!,0.05))))))) | AV18: =AU18*AK18 | AX18: =IF(AN18<=#REF!,#REF!,IF(AN18<=#REF!,#REF!,IF(AN18<=#REF!,#REF!,IF(AN18<=#REF!,#REF!,IF(AN18<=#REF!,#REF!,IF(AN18<=#REF!,#REF!,IF(AN18<=#REF!,#REF!,0.05))))))) | AY18: =AX18*AN18 | BA18: =IF(AQ18<=#REF!,#REF!,IF(AQ18<=#REF!,#REF!,IF(AQ18<=#REF!,#REF!,IF(AQ18<=#REF!,#REF!,IF(AQ18<=#REF!,#REF!,IF(AQ18<=#REF!,#REF!,IF(AQ18<=#REF!,#REF!,0.05))))))) | BB18: =BA18*SUM(AY18,AV18,AQ18) | BD18: =IF(AT18<=#REF!,#REF!,IF(AT18<=#REF!,#REF!,IF(AT18<=#REF!,#REF!,IF(AT18<=#REF!,#REF!,IF(AT18<=#REF!,#REF!,IF(AT18<=#REF!,#REF!,IF(AT18<=#REF!,#REF!,0.05))))))) | BE18: =BD18*AT18 | BG18: =0.07*SUM(AQ18,AV18,AY18,BB18,BE18) | BI18: =SUM(BG18,BE18,BB18,AY18,AV18,AQ18) | BJ18: =SUM(BE18,BB18,AY18,AV18) | BK18: =BJ18/BI18 | CA18: 11000 | CD18: =CA18 | CG18: =CA18+CD18 | CJ18: =CG18 | CK18: =IF(CA18<=BO$4,BN$4,IF(CA18<=BO$5,BN$5,IF(CA18<=BO$6,BN$6,IF(CA18<=BO$7,BN$7,IF(CA18<=BO$12,BN$12,IF(CA18<=BO$13,BN$13,IF(CA18<=BO$14,BN$14,0.05))))))) | CL18: =CK18*CA18 | CN18: =IF(CD18<=BR$4,BQ$4,IF(CD18<=BR$5,BQ$5,IF(CD18<=BR$6,BQ$6,IF(CD18<=BR$7,BQ$7,IF(CD18<=BR$12,BQ$12,IF(CD18<=BR$13,BQ$13,IF(CD18<=BR$14,BQ$14,0.05))))))) | CO18: =CN18*CD18 | CQ18: =IF(CG18<=BU$4,BT$4,IF(CG18<=BU$5,BT$5,IF(CG18<=BU$6,BT$6,IF(CG18<=BU$7,BT$7,IF(CG18<=BU$12,BT$12,IF(CG18<=BU$13,BT$13,IF(CG18<=BU$14,BT$14,0.05))))))) | CR18: =CQ18*SUM(CO18,CL18,CG18) | CT18: =IF(CJ18<=BX$4,BW$4,IF(CJ18<=BX$5,BW$5,IF(CJ18<=BX$6,BW$6,IF(CJ18<=BX$7,BW$7,IF(CJ18<=BX$12,BW$12,IF(CJ18<=BX$13,BW$13,IF(CJ18<=BX$14,BW$14,0.05))))))) | CU18: =CT18*CJ18 | CW18: =0.07*SUM(CG18,CL18,CO18,CR18,CU18) | CY18: =SUM(CW18,CU18,CR18,CO18,CL18,CG18) | CZ18: =SUM(CU18,CR18,CO18,CL18) | DA18: =CZ18/CY18
A19: system 2 | B19: =E24 | C19: =C18 | D19: =B19*C19 | H19: Joint Filler | I19: =IF(J19<=1000,validation!$U$4,IF(J19<1500,validation!$U$6,IF(J19<2000,validation!$U$8,IF(J19<2500,validation!$U$10,IF(J19<=3000,validation!$U$12,IF(J19<3500,validation!$U$14,IF(J19<4000,validation!$U$16,IF(J19<5000,validation!$U$18,validation!$U$20)))))))) | J19: =B45 | K19: =ROUNDUP((I19*J19),0) | L19: =0.2*J19 | M19: =K19/L19 | N19: *Double for removal of existing soft joints | AK19: 12000 | AN19: =AK19 | AQ19: =AK19+AN19 | AT19: =AQ19 | AU19: =IF(AK19<=#REF!,#REF!,IF(AK19<=#REF!,#REF!,IF(AK19<=#REF!,#REF!,IF(AK19<=#REF!,#REF!,IF(AK19<=#REF!,#REF!,IF(AK19<=#REF!,#REF!,IF(AK19<=#REF!,#REF!,0.05))))))) | AV19: =AU19*AK19 | AX19: =IF(AN19<=#REF!,#REF!,IF(AN19<=#REF!,#REF!,IF(AN19<=#REF!,#REF!,IF(AN19<=#REF!,#REF!,IF(AN19<=#REF!,#REF!,IF(AN19<=#REF!,#REF!,IF(AN19<=#REF!,#REF!,0.05))))))) | AY19: =AX19*AN19 | BA19: =IF(AQ19<=#REF!,#REF!,IF(AQ19<=#REF!,#REF!,IF(AQ19<=#REF!,#REF!,IF(AQ19<=#REF!,#REF!,IF(AQ19<=#REF!,#REF!,IF(AQ19<=#REF!,#REF!,IF(AQ19<=#REF!,#REF!,0.05))))))) | BB19: =BA19*SUM(AY19,AV19,AQ19) | BD19: =IF(AT19<=#REF!,#REF!,IF(AT19<=#REF!,#REF!,IF(AT19<=#REF!,#REF!,IF(AT19<=#REF!,#REF!,IF(AT19<=#REF!,#REF!,IF(AT19<=#REF!,#REF!,IF(AT19<=#REF!,#REF!,0.05))))))) | BE19: =BD19*AT19 | BG19: =0.07*SUM(AQ19,AV19,AY19,BB19,BE19) | BI19: =SUM(BG19,BE19,BB19,AY19,AV19,AQ19) | BJ19: =SUM(BE19,BB19,AY19,AV19) | BK19: =BJ19/BI19 | CA19: 12000 | CD19: =CA19 | CG19: =CA19+CD19 | CJ19: =CG19 | CK19: =IF(CA19<=BO$4,BN$4,IF(CA19<=BO$5,BN$5,IF(CA19<=BO$6,BN$6,IF(CA19<=BO$7,BN$7,IF(CA19<=BO$12,BN$12,IF(CA19<=BO$13,BN$13,IF(CA19<=BO$14,BN$14,0.05))))))) | CL19: =CK19*CA19 | CN19: =IF(CD19<=BR$4,BQ$4,IF(CD19<=BR$5,BQ$5,IF(CD19<=BR$6,BQ$6,IF(CD19<=BR$7,BQ$7,IF(CD19<=BR$12,BQ$12,IF(CD19<=BR$13,BQ$13,IF(CD19<=BR$14,BQ$14,0.05))))))) | CO19: =CN19*CD19 | CQ19: =IF(CG19<=BU$4,BT$4,IF(CG19<=BU$5,BT$5,IF(CG19<=BU$6,BT$6,IF(CG19<=BU$7,BT$7,IF(CG19<=BU$12,BT$12,IF(CG19<=BU$13,BT$13,IF(CG19<=BU$14,BT$14,0.05))))))) | CR19: =CQ19*SUM(CO19,CL19,CG19) | CT19: =IF(CJ19<=BX$4,BW$4,IF(CJ19<=BX$5,BW$5,IF(CJ19<=BX$6,BW$6,IF(CJ19<=BX$7,BW$7,IF(CJ19<=BX$12,BW$12,IF(CJ19<=BX$13,BW$13,IF(CJ19<=BX$14,BW$14,0.05))))))) | CU19: =CT19*CJ19 | CW19: =0.07*SUM(CG19,CL19,CO19,CR19,CU19) | CY19: =SUM(CW19,CU19,CR19,CO19,CL19,CG19) | CZ19: =SUM(CU19,CR19,CO19,CL19) | DA19: =CZ19/CY19
A20: MATERIAL - Epoxy Liquids | E20: 0 | F20: SF -- System 1 | H20: 4" Rubber Cove (/LF) | I20: =IF(J20<=100,validation!$R$24,IF(J20<150,validation!$R$26,IF(J20<200,validation!$R$28,IF(J20<250,validation!$R$30,IF(J20<=300,validation!$R$32,IF(J20<350,validation!$R$34,IF(J20<400,validation!$R$36,IF(J20<500,validation!$R$38,validation!$R$40)))))))) | J20: =E34+E37 | K20: =ROUNDUP((I20*J20),0) | AK20: 13000 | AN20: =AK20 | AQ20: =AK20+AN20 | AT20: =AQ20 | AU20: =IF(AK20<=#REF!,#REF!,IF(AK20<=#REF!,#REF!,IF(AK20<=#REF!,#REF!,IF(AK20<=#REF!,#REF!,IF(AK20<=#REF!,#REF!,IF(AK20<=#REF!,#REF!,IF(AK20<=#REF!,#REF!,0.05))))))) | AV20: =AU20*AK20 | AX20: =IF(AN20<=#REF!,#REF!,IF(AN20<=#REF!,#REF!,IF(AN20<=#REF!,#REF!,IF(AN20<=#REF!,#REF!,IF(AN20<=#REF!,#REF!,IF(AN20<=#REF!,#REF!,IF(AN20<=#REF!,#REF!,0.05))))))) | AY20: =AX20*AN20 | BA20: =IF(AQ20<=#REF!,#REF!,IF(AQ20<=#REF!,#REF!,IF(AQ20<=#REF!,#REF!,IF(AQ20<=#REF!,#REF!,IF(AQ20<=#REF!,#REF!,IF(AQ20<=#REF!,#REF!,IF(AQ20<=#REF!,#REF!,0.05))))))) | BB20: =BA20*SUM(AY20,AV20,AQ20) | BD20: =IF(AT20<=#REF!,#REF!,IF(AT20<=#REF!,#REF!,IF(AT20<=#REF!,#REF!,IF(AT20<=#REF!,#REF!,IF(AT20<=#REF!,#REF!,IF(AT20<=#REF!,#REF!,IF(AT20<=#REF!,#REF!,0.05))))))) | BE20: =BD20*AT20 | BG20: =0.07*SUM(AQ20,AV20,AY20,BB20,BE20) | BI20: =SUM(BG20,BE20,BB20,AY20,AV20,AQ20) | BJ20: =SUM(BE20,BB20,AY20,AV20) | BK20: =BJ20/BI20 | CA20: 13000 | CD20: =CA20 | CG20: =CA20+CD20 | CJ20: =CG20 | CK20: =IF(CA20<=BO$4,BN$4,IF(CA20<=BO$5,BN$5,IF(CA20<=BO$6,BN$6,IF(CA20<=BO$7,BN$7,IF(CA20<=BO$12,BN$12,IF(CA20<=BO$13,BN$13,IF(CA20<=BO$14,BN$14,0.05))))))) | CL20: =CK20*CA20 | CN20: =IF(CD20<=BR$4,BQ$4,IF(CD20<=BR$5,BQ$5,IF(CD20<=BR$6,BQ$6,IF(CD20<=BR$7,BQ$7,IF(CD20<=BR$12,BQ$12,IF(CD20<=BR$13,BQ$13,IF(CD20<=BR$14,BQ$14,0.05))))))) | CO20: =CN20*CD20 | CQ20: =IF(CG20<=BU$4,BT$4,IF(CG20<=BU$5,BT$5,IF(CG20<=BU$6,BT$6,IF(CG20<=BU$7,BT$7,IF(CG20<=BU$12,BT$12,IF(CG20<=BU$13,BT$13,IF(CG20<=BU$14,BT$14,0.05))))))) | CR20: =CQ20*SUM(CO20,CL20,CG20) | CT20: =IF(CJ20<=BX$4,BW$4,IF(CJ20<=BX$5,BW$5,IF(CJ20<=BX$6,BW$6,IF(CJ20<=BX$7,BW$7,IF(CJ20<=BX$12,BW$12,IF(CJ20<=BX$13,BW$13,IF(CJ20<=BX$14,BW$14,0.05))))))) | CU20: =CT20*CJ20 | CW20: =0.07*SUM(CG20,CL20,CO20,CR20,CU20) | CY20: =SUM(CW20,CU20,CR20,CO20,CL20,CG20) | CZ20: =SUM(CU20,CR20,CO20,CL20) | DA20: =CZ20/CY20
A21: Primer Options | C21: Liquids | D21: =IF(A21=B162,F162,IF(A21=B163,F163,IF(A21=B164,F164,IF(A21=B165,F165,0)))) | H21: 6" Rubber Cove (/LF) | I21: =IF(J20<=100,validation!$U$24,IF(J20<150,validation!$U$26,IF(J20<200,validation!$U$28,IF(J20<250,validation!$U$30,IF(J20<=300,validation!$U$32,IF(J20<350,validation!$U$34,IF(J20<400,validation!$U$36,IF(J20<500,validation!$U$38,validation!$U$40)))))))) | J21: =E34+E37 | K21: =ROUNDUP((I21*J21),0) | M21: Epoxy: | N21: ='Stnd Alts'!E243 | O21: Mock-Up* | AK21: 14000 | AN21: =AK21 | AQ21: =AK21+AN21 | AT21: =AQ21 | AU21: =IF(AK21<=#REF!,#REF!,IF(AK21<=#REF!,#REF!,IF(AK21<=#REF!,#REF!,IF(AK21<=#REF!,#REF!,IF(AK21<=#REF!,#REF!,IF(AK21<=#REF!,#REF!,IF(AK21<=#REF!,#REF!,0.05))))))) | AV21: =AU21*AK21 | AX21: =IF(AN21<=#REF!,#REF!,IF(AN21<=#REF!,#REF!,IF(AN21<=#REF!,#REF!,IF(AN21<=#REF!,#REF!,IF(AN21<=#REF!,#REF!,IF(AN21<=#REF!,#REF!,IF(AN21<=#REF!,#REF!,0.05))))))) | AY21: =AX21*AN21 | BA21: =IF(AQ21<=#REF!,#REF!,IF(AQ21<=#REF!,#REF!,IF(AQ21<=#REF!,#REF!,IF(AQ21<=#REF!,#REF!,IF(AQ21<=#REF!,#REF!,IF(AQ21<=#REF!,#REF!,IF(AQ21<=#REF!,#REF!,0.05))))))) | BB21: =BA21*SUM(AY21,AV21,AQ21) | BD21: =IF(AT21<=#REF!,#REF!,IF(AT21<=#REF!,#REF!,IF(AT21<=#REF!,#REF!,IF(AT21<=#REF!,#REF!,IF(AT21<=#REF!,#REF!,IF(AT21<=#REF!,#REF!,IF(AT21<=#REF!,#REF!,0.05))))))) | BE21: =BD21*AT21 | BG21: =0.07*SUM(AQ21,AV21,AY21,BB21,BE21) | BI21: =SUM(BG21,BE21,BB21,AY21,AV21,AQ21) | BJ21: =SUM(BE21,BB21,AY21,AV21) | BK21: =BJ21/BI21 | CA21: 14000 | CD21: =CA21 | CG21: =CA21+CD21 | CJ21: =CG21 | CK21: =IF(CA21<=BO$4,BN$4,IF(CA21<=BO$5,BN$5,IF(CA21<=BO$6,BN$6,IF(CA21<=BO$7,BN$7,IF(CA21<=BO$12,BN$12,IF(CA21<=BO$13,BN$13,IF(CA21<=BO$14,BN$14,0.05))))))) | CL21: =CK21*CA21 | CN21: =IF(CD21<=BR$4,BQ$4,IF(CD21<=BR$5,BQ$5,IF(CD21<=BR$6,BQ$6,IF(CD21<=BR$7,BQ$7,IF(CD21<=BR$12,BQ$12,IF(CD21<=BR$13,BQ$13,IF(CD21<=BR$14,BQ$14,0.05))))))) | CO21: =CN21*CD21 | CQ21: =IF(CG21<=BU$4,BT$4,IF(CG21<=BU$5,BT$5,IF(CG21<=BU$6,BT$6,IF(CG21<=BU$7,BT$7,IF(CG21<=BU$12,BT$12,IF(CG21<=BU$13,BT$13,IF(CG21<=BU$14,BT$14,0.05))))))) | CR21: =CQ21*SUM(CO21,CL21,CG21) | CT21: =IF(CJ21<=BX$4,BW$4,IF(CJ21<=BX$5,BW$5,IF(CJ21<=BX$6,BW$6,IF(CJ21<=BX$7,BW$7,IF(CJ21<=BX$12,BW$12,IF(CJ21<=BX$13,BW$13,IF(CJ21<=BX$14,BW$14,0.05))))))) | CU21: =CT21*CJ21 | CW21: =0.07*SUM(CG21,CL21,CO21,CR21,CU21) | CY21: =SUM(CW21,CU21,CR21,CO21,CL21,CG21) | CZ21: =SUM(CU21,CR21,CO21,CL21) | DA21: =CZ21/CY21
A22: System 1 Options | C22: Liquids | D22: =IF(A22=R181,F175,IF(A22=R182,F182,IF(A22=R183,F188,IF(A22=R184,F197,IF(A22=R185,F205,IF(A22=R186,F213,IF(A22=R187,F221,IF(A22=R188,F227,IF(A22=R189,F237,IF(A22=R190,F245,IF(A22=R191,F254,IF(A22=R192,F264,IF(A22=R193,F271,IF(A22=R194,F279,IF(A22=R195,F286,0))))))))))))))) | H22: 4" Line Striping (/LF) | I22: =IF(J22<=100,validation!$R$44,IF(J22<150,validation!$R$46,IF(J22<200,validation!$R$48,IF(J22<250,validation!$R$50,IF(J22<=300,validation!$R$52,IF(J22<350,validation!$R$54,IF(J22<400,validation!$R$56,IF(J22<500,validation!$R$58,validation!$R$60)))))))) | J22: 0 | K22: =ROUNDUP((I22*J22),0) | M22: **In Town** | N22: ='Stnd Alts'!E145 | O22: Mob Fee* | P22: *see "Stnd Alts" tab | AK22: 15000 | AN22: =AK22 | AQ22: =AK22+AN22 | AT22: =AQ22 | AU22: =IF(AK22<=#REF!,#REF!,IF(AK22<=#REF!,#REF!,IF(AK22<=#REF!,#REF!,IF(AK22<=#REF!,#REF!,IF(AK22<=#REF!,#REF!,IF(AK22<=#REF!,#REF!,IF(AK22<=#REF!,#REF!,0.05))))))) | AV22: =AU22*AK22 | AX22: =IF(AN22<=#REF!,#REF!,IF(AN22<=#REF!,#REF!,IF(AN22<=#REF!,#REF!,IF(AN22<=#REF!,#REF!,IF(AN22<=#REF!,#REF!,IF(AN22<=#REF!,#REF!,IF(AN22<=#REF!,#REF!,0.05))))))) | AY22: =AX22*AN22 | BA22: =IF(AQ22<=#REF!,#REF!,IF(AQ22<=#REF!,#REF!,IF(AQ22<=#REF!,#REF!,IF(AQ22<=#REF!,#REF!,IF(AQ22<=#REF!,#REF!,IF(AQ22<=#REF!,#REF!,IF(AQ22<=#REF!,#REF!,0.05))))))) | BB22: =BA22*SUM(AY22,AV22,AQ22) | BD22: =IF(AT22<=#REF!,#REF!,IF(AT22<=#REF!,#REF!,IF(AT22<=#REF!,#REF!,IF(AT22<=#REF!,#REF!,IF(AT22<=#REF!,#REF!,IF(AT22<=#REF!,#REF!,IF(AT22<=#REF!,#REF!,0.05))))))) | BE22: =BD22*AT22 | BG22: =0.07*SUM(AQ22,AV22,AY22,BB22,BE22) | BI22: =SUM(BG22,BE22,BB22,AY22,AV22,AQ22) | BJ22: =SUM(BE22,BB22,AY22,AV22) | BK22: =BJ22/BI22 | CA22: 15000 | CD22: =CA22 | CG22: =CA22+CD22 | CJ22: =CG22 | CK22: =IF(CA22<=BO$4,BN$4,IF(CA22<=BO$5,BN$5,IF(CA22<=BO$6,BN$6,IF(CA22<=BO$7,BN$7,IF(CA22<=BO$12,BN$12,IF(CA22<=BO$13,BN$13,IF(CA22<=BO$14,BN$14,0.05))))))) | CL22: =CK22*CA22 | CN22: =IF(CD22<=BR$4,BQ$4,IF(CD22<=BR$5,BQ$5,IF(CD22<=BR$6,BQ$6,IF(CD22<=BR$7,BQ$7,IF(CD22<=BR$12,BQ$12,IF(CD22<=BR$13,BQ$13,IF(CD22<=BR$14,BQ$14,0.05))))))) | CO22: =CN22*CD22 | CQ22: =IF(CG22<=BU$4,BT$4,IF(CG22<=BU$5,BT$5,IF(CG22<=BU$6,BT$6,IF(CG22<=BU$7,BT$7,IF(CG22<=BU$12,BT$12,IF(CG22<=BU$13,BT$13,IF(CG22<=BU$14,BT$14,0.05))))))) | CR22: =CQ22*SUM(CO22,CL22,CG22) | CT22: =IF(CJ22<=BX$4,BW$4,IF(CJ22<=BX$5,BW$5,IF(CJ22<=BX$6,BW$6,IF(CJ22<=BX$7,BW$7,IF(CJ22<=BX$12,BW$12,IF(CJ22<=BX$13,BW$13,IF(CJ22<=BX$14,BW$14,0.05))))))) | CU22: =CT22*CJ22 | CW22: =0.07*SUM(CG22,CL22,CO22,CR22,CU22) | CY22: =SUM(CW22,CU22,CR22,CO22,CL22,CG22) | CZ22: =SUM(CU22,CR22,CO22,CL22) | DA22: =CZ22/CY22
D23: =B23*C23 | H23: 6" Line Striping (/LF) | I23: =IF(J22<=100,validation!$U$44,IF(J22<150,validation!$U$46,IF(J22<200,validation!$U$48,IF(J22<250,validation!$U$50,IF(J22<=300,validation!$U$52,IF(J22<350,validation!$U$54,IF(J22<400,validation!$U$56,IF(J22<500,validation!$U$58,validation!$U$60)))))))) | J23: 0 | K23: =ROUNDUP((I23*J23),0) | AK23: 16000 | AN23: =AK23 | AQ23: =AK23+AN23 | AT23: =AQ23 | AU23: =IF(AK23<=#REF!,#REF!,IF(AK23<=#REF!,#REF!,IF(AK23<=#REF!,#REF!,IF(AK23<=#REF!,#REF!,IF(AK23<=#REF!,#REF!,IF(AK23<=#REF!,#REF!,IF(AK23<=#REF!,#REF!,0.05))))))) | AV23: =AU23*AK23 | AX23: =IF(AN23<=#REF!,#REF!,IF(AN23<=#REF!,#REF!,IF(AN23<=#REF!,#REF!,IF(AN23<=#REF!,#REF!,IF(AN23<=#REF!,#REF!,IF(AN23<=#REF!,#REF!,IF(AN23<=#REF!,#REF!,0.05))))))) | AY23: =AX23*AN23 | BA23: =IF(AQ23<=#REF!,#REF!,IF(AQ23<=#REF!,#REF!,IF(AQ23<=#REF!,#REF!,IF(AQ23<=#REF!,#REF!,IF(AQ23<=#REF!,#REF!,IF(AQ23<=#REF!,#REF!,IF(AQ23<=#REF!,#REF!,0.05))))))) | BB23: =BA23*SUM(AY23,AV23,AQ23) | BD23: =IF(AT23<=#REF!,#REF!,IF(AT23<=#REF!,#REF!,IF(AT23<=#REF!,#REF!,IF(AT23<=#REF!,#REF!,IF(AT23<=#REF!,#REF!,IF(AT23<=#REF!,#REF!,IF(AT23<=#REF!,#REF!,0.05))))))) | BE23: =BD23*AT23 | BG23: =0.07*SUM(AQ23,AV23,AY23,BB23,BE23) | BI23: =SUM(BG23,BE23,BB23,AY23,AV23,AQ23) | BJ23: =SUM(BE23,BB23,AY23,AV23) | BK23: =BJ23/BI23 | CA23: 16000 | CD23: =CA23 | CG23: =CA23+CD23 | CJ23: =CG23 | CK23: =IF(CA23<=BO$4,BN$4,IF(CA23<=BO$5,BN$5,IF(CA23<=BO$6,BN$6,IF(CA23<=BO$7,BN$7,IF(CA23<=BO$12,BN$12,IF(CA23<=BO$13,BN$13,IF(CA23<=BO$14,BN$14,0.05))))))) | CL23: =CK23*CA23 | CN23: =IF(CD23<=BR$4,BQ$4,IF(CD23<=BR$5,BQ$5,IF(CD23<=BR$6,BQ$6,IF(CD23<=BR$7,BQ$7,IF(CD23<=BR$12,BQ$12,IF(CD23<=BR$13,BQ$13,IF(CD23<=BR$14,BQ$14,0.05))))))) | CO23: =CN23*CD23 | CQ23: =IF(CG23<=BU$4,BT$4,IF(CG23<=BU$5,BT$5,IF(CG23<=BU$6,BT$6,IF(CG23<=BU$7,BT$7,IF(CG23<=BU$12,BT$12,IF(CG23<=BU$13,BT$13,IF(CG23<=BU$14,BT$14,0.05))))))) | CR23: =CQ23*SUM(CO23,CL23,CG23) | CT23: =IF(CJ23<=BX$4,BW$4,IF(CJ23<=BX$5,BW$5,IF(CJ23<=BX$6,BW$6,IF(CJ23<=BX$7,BW$7,IF(CJ23<=BX$12,BW$12,IF(CJ23<=BX$13,BW$13,IF(CJ23<=BX$14,BW$14,0.05))))))) | CU23: =CT23*CJ23 | CW23: =0.07*SUM(CG23,CL23,CO23,CR23,CU23) | CY23: =SUM(CW23,CU23,CR23,CO23,CL23,CG23) | CZ23: =SUM(CU23,CR23,CO23,CL23) | DA23: =CZ23/CY23
A24: MATERIAL - Epoxy Liquids | E24: 0 | F24: SF -- System 2 | H24: Patch: Gallons CoveRez | I24: 86 | J24: =(SUM(D18:D19)) | K24: =ROUND(J24/I24,0) | L24: # of Gallons (if CoveRez) | N24: AT satin clr + Grit = | O24: =AT_Clear_Satin_w_Grit | P24: <---broken cell, can't change "Defined Name" | AK24: 17000 | AN24: =AK24 | AQ24: =AK24+AN24 | AT24: =AQ24 | AU24: =IF(AK24<=#REF!,#REF!,IF(AK24<=#REF!,#REF!,IF(AK24<=#REF!,#REF!,IF(AK24<=#REF!,#REF!,IF(AK24<=#REF!,#REF!,IF(AK24<=#REF!,#REF!,IF(AK24<=#REF!,#REF!,0.05))))))) | AV24: =AU24*AK24 | AX24: =IF(AN24<=#REF!,#REF!,IF(AN24<=#REF!,#REF!,IF(AN24<=#REF!,#REF!,IF(AN24<=#REF!,#REF!,IF(AN24<=#REF!,#REF!,IF(AN24<=#REF!,#REF!,IF(AN24<=#REF!,#REF!,0.05))))))) | AY24: =AX24*AN24 | BA24: =IF(AQ24<=#REF!,#REF!,IF(AQ24<=#REF!,#REF!,IF(AQ24<=#REF!,#REF!,IF(AQ24<=#REF!,#REF!,IF(AQ24<=#REF!,#REF!,IF(AQ24<=#REF!,#REF!,IF(AQ24<=#REF!,#REF!,0.05))))))) | BB24: =BA24*SUM(AY24,AV24,AQ24) | BD24: =IF(AT24<=#REF!,#REF!,IF(AT24<=#REF!,#REF!,IF(AT24<=#REF!,#REF!,IF(AT24<=#REF!,#REF!,IF(AT24<=#REF!,#REF!,IF(AT24<=#REF!,#REF!,IF(AT24<=#REF!,#REF!,0.05))))))) | BE24: =BD24*AT24 | BG24: =0.07*SUM(AQ24,AV24,AY24,BB24,BE24) | BI24: =SUM(BG24,BE24,BB24,AY24,AV24,AQ24) | BJ24: =SUM(BE24,BB24,AY24,AV24) | BK24: =BJ24/BI24 | CA24: 17000 | CD24: =CA24 | CG24: =CA24+CD24 | CJ24: =CG24 | CK24: =IF(CA24<=BO$4,BN$4,IF(CA24<=BO$5,BN$5,IF(CA24<=BO$6,BN$6,IF(CA24<=BO$7,BN$7,IF(CA24<=BO$12,BN$12,IF(CA24<=BO$13,BN$13,IF(CA24<=BO$14,BN$14,0.05))))))) | CL24: =CK24*CA24 | CN24: =IF(CD24<=BR$4,BQ$4,IF(CD24<=BR$5,BQ$5,IF(CD24<=BR$6,BQ$6,IF(CD24<=BR$7,BQ$7,IF(CD24<=BR$12,BQ$12,IF(CD24<=BR$13,BQ$13,IF(CD24<=BR$14,BQ$14,0.05))))))) | CO24: =CN24*CD24 | CQ24: =IF(CG24<=BU$4,BT$4,IF(CG24<=BU$5,BT$5,IF(CG24<=BU$6,BT$6,IF(CG24<=BU$7,BT$7,IF(CG24<=BU$12,BT$12,IF(CG24<=BU$13,BT$13,IF(CG24<=BU$14,BT$14,0.05))))))) | CR24: =CQ24*SUM(CO24,CL24,CG24) | CT24: =IF(CJ24<=BX$4,BW$4,IF(CJ24<=BX$5,BW$5,IF(CJ24<=BX$6,BW$6,IF(CJ24<=BX$7,BW$7,IF(CJ24<=BX$12,BW$12,IF(CJ24<=BX$13,BW$13,IF(CJ24<=BX$14,BW$14,0.05))))))) | CU24: =CT24*CJ24 | CW24: =0.07*SUM(CG24,CL24,CO24,CR24,CU24) | CY24: =SUM(CW24,CU24,CR24,CO24,CL24,CG24) | CZ24: =SUM(CU24,CR24,CO24,CL24) | DA24: =CZ24/CY24
A25: Primer Options | C25: Liquids | D25: =IF(A25=AB162,AF162,IF(A25=AB163,AF163,IF(A25=AB164,AF164,IF(A25=AB165,AF165,IF(A25=AB166,AF166,IF(A25=AB167,AF167,0)))))) | H25: Patch: Kits of WR | I25: 59 | J25: =(SUM(D18:D19)) | K25: =ROUND(J25/I25,0) | L25: # of Kits (if WR) | O25: Takoff Tab | P25: sf | Q25: lf | R25: extra cell | S25: extra cell | T25: extra cell | AK25: 18000 | AN25: =AK25 | AQ25: =AK25+AN25 | AT25: =AQ25 | AU25: =IF(AK25<=#REF!,#REF!,IF(AK25<=#REF!,#REF!,IF(AK25<=#REF!,#REF!,IF(AK25<=#REF!,#REF!,IF(AK25<=#REF!,#REF!,IF(AK25<=#REF!,#REF!,IF(AK25<=#REF!,#REF!,0.05))))))) | AV25: =AU25*AK25 | AX25: =IF(AN25<=#REF!,#REF!,IF(AN25<=#REF!,#REF!,IF(AN25<=#REF!,#REF!,IF(AN25<=#REF!,#REF!,IF(AN25<=#REF!,#REF!,IF(AN25<=#REF!,#REF!,IF(AN25<=#REF!,#REF!,0.05))))))) | AY25: =AX25*AN25 | BA25: =IF(AQ25<=#REF!,#REF!,IF(AQ25<=#REF!,#REF!,IF(AQ25<=#REF!,#REF!,IF(AQ25<=#REF!,#REF!,IF(AQ25<=#REF!,#REF!,IF(AQ25<=#REF!,#REF!,IF(AQ25<=#REF!,#REF!,0.05))))))) | BB25: =BA25*SUM(AY25,AV25,AQ25) | BD25: =IF(AT25<=#REF!,#REF!,IF(AT25<=#REF!,#REF!,IF(AT25<=#REF!,#REF!,IF(AT25<=#REF!,#REF!,IF(AT25<=#REF!,#REF!,IF(AT25<=#REF!,#REF!,IF(AT25<=#REF!,#REF!,0.05))))))) | BE25: =BD25*AT25 | BG25: =0.07*SUM(AQ25,AV25,AY25,BB25,BE25) | BI25: =SUM(BG25,BE25,BB25,AY25,AV25,AQ25) | BJ25: =SUM(BE25,BB25,AY25,AV25) | BK25: =BJ25/BI25 | CA25: 18000 | CD25: =CA25 | CG25: =CA25+CD25 | CJ25: =CG25 | CK25: =IF(CA25<=BO$4,BN$4,IF(CA25<=BO$5,BN$5,IF(CA25<=BO$6,BN$6,IF(CA25<=BO$7,BN$7,IF(CA25<=BO$12,BN$12,IF(CA25<=BO$13,BN$13,IF(CA25<=BO$14,BN$14,0.05))))))) | CL25: =CK25*CA25 | CN25: =IF(CD25<=BR$4,BQ$4,IF(CD25<=BR$5,BQ$5,IF(CD25<=BR$6,BQ$6,IF(CD25<=BR$7,BQ$7,IF(CD25<=BR$12,BQ$12,IF(CD25<=BR$13,BQ$13,IF(CD25<=BR$14,BQ$14,0.05))))))) | CO25: =CN25*CD25 | CQ25: =IF(CG25<=BU$4,BT$4,IF(CG25<=BU$5,BT$5,IF(CG25<=BU$6,BT$6,IF(CG25<=BU$7,BT$7,IF(CG25<=BU$12,BT$12,IF(CG25<=BU$13,BT$13,IF(CG25<=BU$14,BT$14,0.05))))))) | CR25: =CQ25*SUM(CO25,CL25,CG25) | CT25: =IF(CJ25<=BX$4,BW$4,IF(CJ25<=BX$5,BW$5,IF(CJ25<=BX$6,BW$6,IF(CJ25<=BX$7,BW$7,IF(CJ25<=BX$12,BW$12,IF(CJ25<=BX$13,BW$13,IF(CJ25<=BX$14,BW$14,0.05))))))) | CU25: =CT25*CJ25 | CW25: =0.07*SUM(CG25,CL25,CO25,CR25,CU25) | CY25: =SUM(CW25,CU25,CR25,CO25,CL25,CG25) | CZ25: =SUM(CU25,CR25,CO25,CL25) | DA25: =CZ25/CY25
A26: System 2 Options / Walls (scroll down) | C26: Liquids | D26: =IF(A26=AR181,AF175,IF(A26=AR182,AF182,IF(A26=AR183,AF188,IF(A26=AR184,AF197,IF(A26=AR185,AF205,IF(A26=AR186,AF213,IF(A26=AR187,AF221,IF(A26=AR188,AF227,IF(A26=AR189,AF237,IF(A26=AR190,AF245,IF(A26=AR191,AF254,IF(A26=AR192,AF264,IF(A26=AR193,AF271,IF(A26=AR194,AF279,IF(A26=AR195,AF286,IF(A26=AR198,AF297,IF(A26=AR199,AF308,IF(A26=AR200,AF316,IF(A26=AR201,AF324,IF(A26=AR202,AF331,IF(A26=AR203,AF339,0))))))))))))))))))))) | O26: =Takeoff!B14 | P26: =Takeoff!C14 | Q26: =Takeoff!D14 | R26: =Takeoff!E14 | S26: =Takeoff!F14 | T26: =Takeoff!G14 | AK26: 19000 | AN26: =AK26 | AQ26: =AK26+AN26 | AT26: =AQ26 | AU26: =IF(AK26<=#REF!,#REF!,IF(AK26<=#REF!,#REF!,IF(AK26<=#REF!,#REF!,IF(AK26<=#REF!,#REF!,IF(AK26<=#REF!,#REF!,IF(AK26<=#REF!,#REF!,IF(AK26<=#REF!,#REF!,0.05))))))) | AV26: =AU26*AK26 | AX26: =IF(AN26<=#REF!,#REF!,IF(AN26<=#REF!,#REF!,IF(AN26<=#REF!,#REF!,IF(AN26<=#REF!,#REF!,IF(AN26<=#REF!,#REF!,IF(AN26<=#REF!,#REF!,IF(AN26<=#REF!,#REF!,0.05))))))) | AY26: =AX26*AN26 | BA26: =IF(AQ26<=#REF!,#REF!,IF(AQ26<=#REF!,#REF!,IF(AQ26<=#REF!,#REF!,IF(AQ26<=#REF!,#REF!,IF(AQ26<=#REF!,#REF!,IF(AQ26<=#REF!,#REF!,IF(AQ26<=#REF!,#REF!,0.05))))))) | BB26: =BA26*SUM(AY26,AV26,AQ26) | BD26: =IF(AT26<=#REF!,#REF!,IF(AT26<=#REF!,#REF!,IF(AT26<=#REF!,#REF!,IF(AT26<=#REF!,#REF!,IF(AT26<=#REF!,#REF!,IF(AT26<=#REF!,#REF!,IF(AT26<=#REF!,#REF!,0.05))))))) | BE26: =BD26*AT26 | BG26: =0.07*SUM(AQ26,AV26,AY26,BB26,BE26) | BI26: =SUM(BG26,BE26,BB26,AY26,AV26,AQ26) | BJ26: =SUM(BE26,BB26,AY26,AV26) | BK26: =BJ26/BI26 | CA26: 19000 | CD26: =CA26 | CG26: =CA26+CD26 | CJ26: =CG26 | CK26: =IF(CA26<=BO$4,BN$4,IF(CA26<=BO$5,BN$5,IF(CA26<=BO$6,BN$6,IF(CA26<=BO$7,BN$7,IF(CA26<=BO$12,BN$12,IF(CA26<=BO$13,BN$13,IF(CA26<=BO$14,BN$14,0.05))))))) | CL26: =CK26*CA26 | CN26: =IF(CD26<=BR$4,BQ$4,IF(CD26<=BR$5,BQ$5,IF(CD26<=BR$6,BQ$6,IF(CD26<=BR$7,BQ$7,IF(CD26<=BR$12,BQ$12,IF(CD26<=BR$13,BQ$13,IF(CD26<=BR$14,BQ$14,0.05))))))) | CO26: =CN26*CD26 | CQ26: =IF(CG26<=BU$4,BT$4,IF(CG26<=BU$5,BT$5,IF(CG26<=BU$6,BT$6,IF(CG26<=BU$7,BT$7,IF(CG26<=BU$12,BT$12,IF(CG26<=BU$13,BT$13,IF(CG26<=BU$14,BT$14,0.05))))))) | CR26: =CQ26*SUM(CO26,CL26,CG26) | CT26: =IF(CJ26<=BX$4,BW$4,IF(CJ26<=BX$5,BW$5,IF(CJ26<=BX$6,BW$6,IF(CJ26<=BX$7,BW$7,IF(CJ26<=BX$12,BW$12,IF(CJ26<=BX$13,BW$13,IF(CJ26<=BX$14,BW$14,0.05))))))) | CU26: =CT26*CJ26 | CW26: =0.07*SUM(CG26,CL26,CO26,CR26,CU26) | CY26: =SUM(CW26,CU26,CR26,CO26,CL26,CG26) | CZ26: =SUM(CU26,CR26,CO26,CL26) | DA26: =CZ26/CY26
D27: =B27*C27 | O27: =Takeoff!I14 | P27: =Takeoff!J14 | Q27: =Takeoff!K14 | R27: =Takeoff!L14 | S27: =Takeoff!M14 | T27: =Takeoff!N14 | AW27: 20000 | AZ27: =AW27 | BC27: =AW27+AZ27 | BF27: =BC27 | BG27: =IF(AW27<=#REF!,#REF!,IF(AW27<=#REF!,#REF!,IF(AW27<=#REF!,#REF!,IF(AW27<=#REF!,#REF!,IF(AW27<=#REF!,#REF!,IF(AW27<=#REF!,#REF!,IF(AW27<=#REF!,#REF!,0.05))))))) | BH27: =BG27*AW27 | BJ27: =IF(AZ27<=#REF!,#REF!,IF(AZ27<=#REF!,#REF!,IF(AZ27<=#REF!,#REF!,IF(AZ27<=#REF!,#REF!,IF(AZ27<=#REF!,#REF!,IF(AZ27<=#REF!,#REF!,IF(AZ27<=#REF!,#REF!,0.05))))))) | BK27: =BJ27*AZ27 | BM27: =IF(BC27<=#REF!,#REF!,IF(BC27<=#REF!,#REF!,IF(BC27<=#REF!,#REF!,IF(BC27<=#REF!,#REF!,IF(BC27<=#REF!,#REF!,IF(BC27<=#REF!,#REF!,IF(BC27<=#REF!,#REF!,0.05))))))) | BN27: =BM27*SUM(BK27,BH27,BC27) | BP27: =IF(BF27<=#REF!,#REF!,IF(BF27<=#REF!,#REF!,IF(BF27<=#REF!,#REF!,IF(BF27<=#REF!,#REF!,IF(BF27<=#REF!,#REF!,IF(BF27<=#REF!,#REF!,IF(BF27<=#REF!,#REF!,0.05))))))) | BQ27: =BP27*BF27 | BS27: =0.07*SUM(BC27,BH27,BK27,BN27,BQ27) | BU27: =SUM(BS27,BQ27,BN27,BK27,BH27,BC27) | BV27: =SUM(BQ27,BN27,BK27,BH27) | BW27: =BV27/BU27 | CM27: 20000 | CP27: =CM27 | CS27: =CM27+CP27 | CV27: =CS27 | CW27: =IF(CM27<=BO$4,BN$4,IF(CM27<=BO$5,BN$5,IF(CM27<=BO$6,BN$6,IF(CM27<=BO$7,BN$7,IF(CM27<=BO$12,BN$12,IF(CM27<=BO$13,BN$13,IF(CM27<=BO$14,BN$14,0.05))))))) | CX27: =CW27*CM27 | CZ27: =IF(CP27<=BR$4,BQ$4,IF(CP27<=BR$5,BQ$5,IF(CP27<=BR$6,BQ$6,IF(CP27<=BR$7,BQ$7,IF(CP27<=BR$12,BQ$12,IF(CP27<=BR$13,BQ$13,IF(CP27<=BR$14,BQ$14,0.05))))))) | DA27: =CZ27*CP27 | DC27: =IF(CS27<=BU$4,BT$4,IF(CS27<=BU$5,BT$5,IF(CS27<=BU$6,BT$6,IF(CS27<=BU$7,BT$7,IF(CS27<=BU$12,BT$12,IF(CS27<=BU$13,BT$13,IF(CS27<=BU$14,BT$14,0.05))))))) | DD27: =DC27*SUM(DA27,CX27,CS27) | DF27: =IF(CV27<=BX$4,BW$4,IF(CV27<=BX$5,BW$5,IF(CV27<=BX$6,BW$6,IF(CV27<=BX$7,BW$7,IF(CV27<=BX$12,BW$12,IF(CV27<=BX$13,BW$13,IF(CV27<=BX$14,BW$14,0.05))))))) | DG27: =DF27*CV27 | DI27: =0.07*SUM(CS27,CX27,DA27,DD27,DG27) | DK27: =SUM(DI27,DG27,DD27,DA27,CX27,CS27) | DL27: =SUM(DG27,DD27,DA27,CX27) | DM27: =DL27/DK27
D28: =B28*C28 | O28: =Takeoff!P14 | P28: =Takeoff!Q14 | Q28: =Takeoff!R14 | R28: =Takeoff!S14 | S28: =Takeoff!T14 | T28: =Takeoff!U14 | AW28: 21000 | AZ28: =AW28 | BC28: =AW28+AZ28 | BF28: =BC28 | BG28: =IF(AW28<=#REF!,#REF!,IF(AW28<=#REF!,#REF!,IF(AW28<=#REF!,#REF!,IF(AW28<=#REF!,#REF!,IF(AW28<=#REF!,#REF!,IF(AW28<=#REF!,#REF!,IF(AW28<=#REF!,#REF!,0.05))))))) | BH28: =BG28*AW28 | BJ28: =IF(AZ28<=#REF!,#REF!,IF(AZ28<=#REF!,#REF!,IF(AZ28<=#REF!,#REF!,IF(AZ28<=#REF!,#REF!,IF(AZ28<=#REF!,#REF!,IF(AZ28<=#REF!,#REF!,IF(AZ28<=#REF!,#REF!,0.05))))))) | BK28: =BJ28*AZ28 | BM28: =IF(BC28<=#REF!,#REF!,IF(BC28<=#REF!,#REF!,IF(BC28<=#REF!,#REF!,IF(BC28<=#REF!,#REF!,IF(BC28<=#REF!,#REF!,IF(BC28<=#REF!,#REF!,IF(BC28<=#REF!,#REF!,0.05))))))) | BN28: =BM28*SUM(BK28,BH28,BC28) | BP28: =IF(BF28<=#REF!,#REF!,IF(BF28<=#REF!,#REF!,IF(BF28<=#REF!,#REF!,IF(BF28<=#REF!,#REF!,IF(BF28<=#REF!,#REF!,IF(BF28<=#REF!,#REF!,IF(BF28<=#REF!,#REF!,0.05))))))) | BQ28: =BP28*BF28 | BS28: =0.07*SUM(BC28,BH28,BK28,BN28,BQ28) | BU28: =SUM(BS28,BQ28,BN28,BK28,BH28,BC28) | BV28: =SUM(BQ28,BN28,BK28,BH28) | BW28: =BV28/BU28 | CM28: 21000 | CP28: =CM28 | CS28: =CM28+CP28 | CV28: =CS28 | CW28: =IF(CM28<=BO$4,BN$4,IF(CM28<=BO$5,BN$5,IF(CM28<=BO$6,BN$6,IF(CM28<=BO$7,BN$7,IF(CM28<=BO$12,BN$12,IF(CM28<=BO$13,BN$13,IF(CM28<=BO$14,BN$14,0.05))))))) | CX28: =CW28*CM28 | CZ28: =IF(CP28<=BR$4,BQ$4,IF(CP28<=BR$5,BQ$5,IF(CP28<=BR$6,BQ$6,IF(CP28<=BR$7,BQ$7,IF(CP28<=BR$12,BQ$12,IF(CP28<=BR$13,BQ$13,IF(CP28<=BR$14,BQ$14,0.05))))))) | DA28: =CZ28*CP28 | DC28: =IF(CS28<=BU$4,BT$4,IF(CS28<=BU$5,BT$5,IF(CS28<=BU$6,BT$6,IF(CS28<=BU$7,BT$7,IF(CS28<=BU$12,BT$12,IF(CS28<=BU$13,BT$13,IF(CS28<=BU$14,BT$14,0.05))))))) | DD28: =DC28*SUM(DA28,CX28,CS28) | DF28: =IF(CV28<=BX$4,BW$4,IF(CV28<=BX$5,BW$5,IF(CV28<=BX$6,BW$6,IF(CV28<=BX$7,BW$7,IF(CV28<=BX$12,BW$12,IF(CV28<=BX$13,BW$13,IF(CV28<=BX$14,BW$14,0.05))))))) | DG28: =DF28*CV28 | DI28: =0.07*SUM(CS28,CX28,DA28,DD28,DG28) | DK28: =SUM(DI28,DG28,DD28,DA28,CX28,CS28) | DL28: =SUM(DG28,DD28,DA28,CX28) | DM28: =DL28/DK28
A29: MATERIAL - Extras | O29: =Takeoff!I3 | P29: =Takeoff!J3 | Q29: =Takeoff!K3 | R29: =Takeoff!L3 | S29: =Takeoff!M3 | T29: =Takeoff!N3 | AW29: 22000 | AZ29: =AW29 | BC29: =AW29+AZ29 | BF29: =BC29 | BG29: =IF(AW29<=#REF!,#REF!,IF(AW29<=#REF!,#REF!,IF(AW29<=#REF!,#REF!,IF(AW29<=#REF!,#REF!,IF(AW29<=#REF!,#REF!,IF(AW29<=#REF!,#REF!,IF(AW29<=#REF!,#REF!,0.05))))))) | BH29: =BG29*AW29 | BJ29: =IF(AZ29<=#REF!,#REF!,IF(AZ29<=#REF!,#REF!,IF(AZ29<=#REF!,#REF!,IF(AZ29<=#REF!,#REF!,IF(AZ29<=#REF!,#REF!,IF(AZ29<=#REF!,#REF!,IF(AZ29<=#REF!,#REF!,0.05))))))) | BK29: =BJ29*AZ29 | BM29: =IF(BC29<=#REF!,#REF!,IF(BC29<=#REF!,#REF!,IF(BC29<=#REF!,#REF!,IF(BC29<=#REF!,#REF!,IF(BC29<=#REF!,#REF!,IF(BC29<=#REF!,#REF!,IF(BC29<=#REF!,#REF!,0.05))))))) | BN29: =BM29*SUM(BK29,BH29,BC29) | BP29: =IF(BF29<=#REF!,#REF!,IF(BF29<=#REF!,#REF!,IF(BF29<=#REF!,#REF!,IF(BF29<=#REF!,#REF!,IF(BF29<=#REF!,#REF!,IF(BF29<=#REF!,#REF!,IF(BF29<=#REF!,#REF!,0.05))))))) | BQ29: =BP29*BF29 | BS29: =0.07*SUM(BC29,BH29,BK29,BN29,BQ29) | BU29: =SUM(BS29,BQ29,BN29,BK29,BH29,BC29) | BV29: =SUM(BQ29,BN29,BK29,BH29) | BW29: =BV29/BU29 | CM29: 22000 | CP29: =CM29 | CS29: =CM29+CP29 | CV29: =CS29 | CW29: =IF(CM29<=BO$4,BN$4,IF(CM29<=BO$5,BN$5,IF(CM29<=BO$6,BN$6,IF(CM29<=BO$7,BN$7,IF(CM29<=BO$12,BN$12,IF(CM29<=BO$13,BN$13,IF(CM29<=BO$14,BN$14,0.05))))))) | CX29: =CW29*CM29 | CZ29: =IF(CP29<=BR$4,BQ$4,IF(CP29<=BR$5,BQ$5,IF(CP29<=BR$6,BQ$6,IF(CP29<=BR$7,BQ$7,IF(CP29<=BR$12,BQ$12,IF(CP29<=BR$13,BQ$13,IF(CP29<=BR$14,BQ$14,0.05))))))) | DA29: =CZ29*CP29 | DC29: =IF(CS29<=BU$4,BT$4,IF(CS29<=BU$5,BT$5,IF(CS29<=BU$6,BT$6,IF(CS29<=BU$7,BT$7,IF(CS29<=BU$12,BT$12,IF(CS29<=BU$13,BT$13,IF(CS29<=BU$14,BT$14,0.05))))))) | DD29: =DC29*SUM(DA29,CX29,CS29) | DF29: =IF(CV29<=BX$4,BW$4,IF(CV29<=BX$5,BW$5,IF(CV29<=BX$6,BW$6,IF(CV29<=BX$7,BW$7,IF(CV29<=BX$12,BW$12,IF(CV29<=BX$13,BW$13,IF(CV29<=BX$14,BW$14,0.05))))))) | DG29: =DF29*CV29 | DI29: =0.07*SUM(CS29,CX29,DA29,DD29,DG29) | DK29: =SUM(DI29,DG29,DD29,DA29,CX29,CS29) | DL29: =SUM(DG29,DD29,DA29,CX29) | DM29: =DL29/DK29
A30: =A22 | C30: other | D30: =IF(A30=R181,P174,IF(A30=R182,P180,IF(A30=R183,P187,IF(A30=R184,P195,IF(A30=R185,P203,IF(A30=R186,P211,IF(A30=R187,P219,IF(A30=R188,P226,IF(A30=R189,P235,IF(A30=R190,P243,IF(A30=R191,P251,IF(A30=R192,P262,IF(A30=R193,P269,IF(A30=R194,P278,IF(A30=R195,P286,0))))))))))))))) | E30: silica, flake (MACRO/micro), quartz | AW30: 23000 | AZ30: =AW30 | BC30: =AW30+AZ30 | BF30: =BC30 | BG30: =IF(AW30<=#REF!,#REF!,IF(AW30<=#REF!,#REF!,IF(AW30<=#REF!,#REF!,IF(AW30<=#REF!,#REF!,IF(AW30<=#REF!,#REF!,IF(AW30<=#REF!,#REF!,IF(AW30<=#REF!,#REF!,0.05))))))) | BH30: =BG30*AW30 | BJ30: =IF(AZ30<=#REF!,#REF!,IF(AZ30<=#REF!,#REF!,IF(AZ30<=#REF!,#REF!,IF(AZ30<=#REF!,#REF!,IF(AZ30<=#REF!,#REF!,IF(AZ30<=#REF!,#REF!,IF(AZ30<=#REF!,#REF!,0.05))))))) | BK30: =BJ30*AZ30 | BM30: =IF(BC30<=#REF!,#REF!,IF(BC30<=#REF!,#REF!,IF(BC30<=#REF!,#REF!,IF(BC30<=#REF!,#REF!,IF(BC30<=#REF!,#REF!,IF(BC30<=#REF!,#REF!,IF(BC30<=#REF!,#REF!,0.05))))))) | BN30: =BM30*SUM(BK30,BH30,BC30) | BP30: =IF(BF30<=#REF!,#REF!,IF(BF30<=#REF!,#REF!,IF(BF30<=#REF!,#REF!,IF(BF30<=#REF!,#REF!,IF(BF30<=#REF!,#REF!,IF(BF30<=#REF!,#REF!,IF(BF30<=#REF!,#REF!,0.05))))))) | BQ30: =BP30*BF30 | BS30: =0.07*SUM(BC30,BH30,BK30,BN30,BQ30) | BU30: =SUM(BS30,BQ30,BN30,BK30,BH30,BC30) | BV30: =SUM(BQ30,BN30,BK30,BH30) | BW30: =BV30/BU30 | CM30: 23000 | CP30: =CM30 | CS30: =CM30+CP30 | CV30: =CS30 | CW30: =IF(CM30<=BO$4,BN$4,IF(CM30<=BO$5,BN$5,IF(CM30<=BO$6,BN$6,IF(CM30<=BO$7,BN$7,IF(CM30<=BO$12,BN$12,IF(CM30<=BO$13,BN$13,IF(CM30<=BO$14,BN$14,0.05))))))) | CX30: =CW30*CM30 | CZ30: =IF(CP30<=BR$4,BQ$4,IF(CP30<=BR$5,BQ$5,IF(CP30<=BR$6,BQ$6,IF(CP30<=BR$7,BQ$7,IF(CP30<=BR$12,BQ$12,IF(CP30<=BR$13,BQ$13,IF(CP30<=BR$14,BQ$14,0.05))))))) | DA30: =CZ30*CP30 | DC30: =IF(CS30<=BU$4,BT$4,IF(CS30<=BU$5,BT$5,IF(CS30<=BU$6,BT$6,IF(CS30<=BU$7,BT$7,IF(CS30<=BU$12,BT$12,IF(CS30<=BU$13,BT$13,IF(CS30<=BU$14,BT$14,0.05))))))) | DD30: =DC30*SUM(DA30,CX30,CS30) | DF30: =IF(CV30<=BX$4,BW$4,IF(CV30<=BX$5,BW$5,IF(CV30<=BX$6,BW$6,IF(CV30<=BX$7,BW$7,IF(CV30<=BX$12,BW$12,IF(CV30<=BX$13,BW$13,IF(CV30<=BX$14,BW$14,0.05))))))) | DG30: =DF30*CV30 | DI30: =0.07*SUM(CS30,CX30,DA30,DD30,DG30) | DK30: =SUM(DI30,DG30,DD30,DA30,CX30,CS30) | DL30: =SUM(DG30,DD30,DA30,CX30) | DM30: =DL30/DK30
A31: =A26 | C31: other | D31: =IF(A31=AR181,AP174,IF(A31=AR182,AP180,IF(A31=AR183,AP187,IF(A31=AR184,AP195,IF(A31=AR185,AP203,IF(A31=AR186,AP211,IF(A31=AR187,AP219,IF(A31=AR188,AP226,IF(A31=AR189,AP235,IF(A31=AR190,AP243,IF(A31=AR191,AP251,IF(A31=AR192,AP262,IF(A31=AR193,AP269,IF(A31=AR194,AP278,IF(A31=AR195,AP286,IF(A31=AR198,AP296,IF(A31=AR199,AP306,IF(A31=AR200,AP314,IF(A31=AR201,AQ324,IF(A31=AR202,AQ330,IF(A31=AR203,AP336,0))))))))))))))))))))) | E31: silica, flake (MACRO/micro), quartz | O31: Cant Cove Calculator (must be a 45° Angle):
D32: =B32*C32 | O32: h2/1.5 = Ratio to 6" cove w/ cap (1/8" thick)
D33: =B33*C33 | G33: ? Yes / No ? | H33: Special Transitions ? | I33: "Nat. Guard" = 8' @ ~$130 ea. ($16.25 /lf.) | O33: =(P33*P33)/1.5 | Q33: Height of Cant Cove
A34: MATERIAL - Cove | E34: 0 | F34: LF -- System 1 | O34: =P34*O33 | Q34: Total Resin + Hardner
A35: Cove 1 Options | C35: Liquids | D35: =IF(A35=S125,F125,IF(A35=S126,F130,IF(A35=S127,F135,IF(A35=S128,F141,IF(A35=S129,F147,IF(A35=S130,F152,IF(A35=S131,P125,IF(A35=S132,P130,IF(A35=S133,P135,IF(A35=S134,P141,IF(A35=S135,P147,IF(A35=S136,P152,0)))))))))))) | E35: =B13 | O35: =P35*O33 | Q35: Total Aggregate | AW35: 24000 | AZ35: =AW35 | BC35: =AW35+AZ35 | BF35: =BC35 | BG35: =IF(AW35<=#REF!,#REF!,IF(AW35<=#REF!,#REF!,IF(AW35<=#REF!,#REF!,IF(AW35<=#REF!,#REF!,IF(AW35<=#REF!,#REF!,IF(AW35<=#REF!,#REF!,IF(AW35<=#REF!,#REF!,0.05))))))) | BH35: =BG35*AW35 | BJ35: =IF(AZ35<=#REF!,#REF!,IF(AZ35<=#REF!,#REF!,IF(AZ35<=#REF!,#REF!,IF(AZ35<=#REF!,#REF!,IF(AZ35<=#REF!,#REF!,IF(AZ35<=#REF!,#REF!,IF(AZ35<=#REF!,#REF!,0.05))))))) | BK35: =BJ35*AZ35 | BM35: =IF(BC35<=#REF!,#REF!,IF(BC35<=#REF!,#REF!,IF(BC35<=#REF!,#REF!,IF(BC35<=#REF!,#REF!,IF(BC35<=#REF!,#REF!,IF(BC35<=#REF!,#REF!,IF(BC35<=#REF!,#REF!,0.05))))))) | BN35: =BM35*SUM(BK35,BH35,BC35) | BP35: =IF(BF35<=#REF!,#REF!,IF(BF35<=#REF!,#REF!,IF(BF35<=#REF!,#REF!,IF(BF35<=#REF!,#REF!,IF(BF35<=#REF!,#REF!,IF(BF35<=#REF!,#REF!,IF(BF35<=#REF!,#REF!,0.05))))))) | BQ35: =BP35*BF35 | BS35: =0.07*SUM(BC35,BH35,BK35,BN35,BQ35) | BU35: =SUM(BS35,BQ35,BN35,BK35,BH35,BC35) | BV35: =SUM(BQ35,BN35,BK35,BH35) | BW35: =BV35/BU35 | CM35: 24000 | CP35: =CM35 | CS35: =CM35+CP35 | CV35: =CS35 | CW35: =IF(CM35<=BO$4,BN$4,IF(CM35<=BO$5,BN$5,IF(CM35<=BO$6,BN$6,IF(CM35<=BO$7,BN$7,IF(CM35<=BO$12,BN$12,IF(CM35<=BO$13,BN$13,IF(CM35<=BO$14,BN$14,0.05))))))) | CX35: =CW35*CM35 | CZ35: =IF(CP35<=BR$4,BQ$4,IF(CP35<=BR$5,BQ$5,IF(CP35<=BR$6,BQ$6,IF(CP35<=BR$7,BQ$7,IF(CP35<=BR$12,BQ$12,IF(CP35<=BR$13,BQ$13,IF(CP35<=BR$14,BQ$14,0.05))))))) | DA35: =CZ35*CP35 | DC35: =IF(CS35<=BU$4,BT$4,IF(CS35<=BU$5,BT$5,IF(CS35<=BU$6,BT$6,IF(CS35<=BU$7,BT$7,IF(CS35<=BU$12,BT$12,IF(CS35<=BU$13,BT$13,IF(CS35<=BU$14,BT$14,0.05))))))) | DD35: =DC35*SUM(DA35,CX35,CS35) | DF35: =IF(CV35<=BX$4,BW$4,IF(CV35<=BX$5,BW$5,IF(CV35<=BX$6,BW$6,IF(CV35<=BX$7,BW$7,IF(CV35<=BX$12,BW$12,IF(CV35<=BX$13,BW$13,IF(CV35<=BX$14,BW$14,0.05))))))) | DG35: =DF35*CV35 | DI35: =0.07*SUM(CS35,CX35,DA35,DD35,DG35) | DK35: =SUM(DI35,DG35,DD35,DA35,CX35,CS35) | DL35: =SUM(DG35,DD35,DA35,CX35) | DM35: =DL35/DK35
C36: Sand &/or Cap | D36: =IF(A35=S125,F126,IF(A35=S126,F131,IF(A35=S127,H137,IF(A35=S128,H143,IF(A35=S129,F148,IF(A35=S130,H154,IF(A35=S131,0,IF(A35=S132,0,IF(A35=S133,P136,IF(A35=S134,P142,IF(A35=S135,0,IF(A35=S136,P153,0)))))))))))) | O36: =P36*O33 | Q36: WR | AW36: 25000 | AZ36: =AW36 | BC36: =AW36+AZ36 | BF36: =BC36 | BG36: =IF(AW36<=#REF!,#REF!,IF(AW36<=#REF!,#REF!,IF(AW36<=#REF!,#REF!,IF(AW36<=#REF!,#REF!,IF(AW36<=#REF!,#REF!,IF(AW36<=#REF!,#REF!,IF(AW36<=#REF!,#REF!,0.05))))))) | BH36: =BG36*AW36 | BJ36: =IF(AZ36<=#REF!,#REF!,IF(AZ36<=#REF!,#REF!,IF(AZ36<=#REF!,#REF!,IF(AZ36<=#REF!,#REF!,IF(AZ36<=#REF!,#REF!,IF(AZ36<=#REF!,#REF!,IF(AZ36<=#REF!,#REF!,0.05))))))) | BK36: =BJ36*AZ36 | BM36: =IF(BC36<=#REF!,#REF!,IF(BC36<=#REF!,#REF!,IF(BC36<=#REF!,#REF!,IF(BC36<=#REF!,#REF!,IF(BC36<=#REF!,#REF!,IF(BC36<=#REF!,#REF!,IF(BC36<=#REF!,#REF!,0.05))))))) | BN36: =BM36*SUM(BK36,BH36,BC36) | BP36: =IF(BF36<=#REF!,#REF!,IF(BF36<=#REF!,#REF!,IF(BF36<=#REF!,#REF!,IF(BF36<=#REF!,#REF!,IF(BF36<=#REF!,#REF!,IF(BF36<=#REF!,#REF!,IF(BF36<=#REF!,#REF!,0.05))))))) | BQ36: =BP36*BF36 | BS36: =0.07*SUM(BC36,BH36,BK36,BN36,BQ36) | BU36: =SUM(BS36,BQ36,BN36,BK36,BH36,BC36) | BV36: =SUM(BQ36,BN36,BK36,BH36) | BW36: =BV36/BU36 | CM36: 25000 | CP36: =CM36 | CS36: =CM36+CP36 | CV36: =CS36 | CW36: =IF(CM36<=BO$4,BN$4,IF(CM36<=BO$5,BN$5,IF(CM36<=BO$6,BN$6,IF(CM36<=BO$7,BN$7,IF(CM36<=BO$12,BN$12,IF(CM36<=BO$13,BN$13,IF(CM36<=BO$14,BN$14,0.05))))))) | CX36: =CW36*CM36 | CZ36: =IF(CP36<=BR$4,BQ$4,IF(CP36<=BR$5,BQ$5,IF(CP36<=BR$6,BQ$6,IF(CP36<=BR$7,BQ$7,IF(CP36<=BR$12,BQ$12,IF(CP36<=BR$13,BQ$13,IF(CP36<=BR$14,BQ$14,0.05))))))) | DA36: =CZ36*CP36 | DC36: =IF(CS36<=BU$4,BT$4,IF(CS36<=BU$5,BT$5,IF(CS36<=BU$6,BT$6,IF(CS36<=BU$7,BT$7,IF(CS36<=BU$12,BT$12,IF(CS36<=BU$13,BT$13,IF(CS36<=BU$14,BT$14,0.05))))))) | DD36: =DC36*SUM(DA36,CX36,CS36) | DF36: =IF(CV36<=BX$4,BW$4,IF(CV36<=BX$5,BW$5,IF(CV36<=BX$6,BW$6,IF(CV36<=BX$7,BW$7,IF(CV36<=BX$12,BW$12,IF(CV36<=BX$13,BW$13,IF(CV36<=BX$14,BW$14,0.05))))))) | DG36: =DF36*CV36 | DI36: =0.07*SUM(CS36,CX36,DA36,DD36,DG36) | DK36: =SUM(DI36,DG36,DD36,DA36,CX36,CS36) | DL36: =SUM(DG36,DD36,DA36,CX36) | DM36: =DL36/DK36
A37: Cove 2 Options | C37: Liquids | D37: =IF(A37=AS125,AF125,IF(A37=AS126,AF130,IF(A37=AS127,AF135,IF(A37=AS128,AF141,IF(A37=AS129,AF147,IF(A37=AS130,AF152,IF(A37=AS131,AP125,IF(A37=AS132,AP130,IF(A37=AS133,AP135,IF(A37=AS134,AP141,IF(A37=AS135,AP147,IF(A37=AS136,AP152,0)))))))))))) | E37: 0 | F37: LF -- System 2 | AW37: 26000 | AZ37: =AW37 | BC37: =AW37+AZ37 | BF37: =BC37 | BG37: =IF(AW37<=#REF!,#REF!,IF(AW37<=#REF!,#REF!,IF(AW37<=#REF!,#REF!,IF(AW37<=#REF!,#REF!,IF(AW37<=#REF!,#REF!,IF(AW37<=#REF!,#REF!,IF(AW37<=#REF!,#REF!,0.05))))))) | BH37: =BG37*AW37 | BJ37: =IF(AZ37<=#REF!,#REF!,IF(AZ37<=#REF!,#REF!,IF(AZ37<=#REF!,#REF!,IF(AZ37<=#REF!,#REF!,IF(AZ37<=#REF!,#REF!,IF(AZ37<=#REF!,#REF!,IF(AZ37<=#REF!,#REF!,0.05))))))) | BK37: =BJ37*AZ37 | BM37: =IF(BC37<=#REF!,#REF!,IF(BC37<=#REF!,#REF!,IF(BC37<=#REF!,#REF!,IF(BC37<=#REF!,#REF!,IF(BC37<=#REF!,#REF!,IF(BC37<=#REF!,#REF!,IF(BC37<=#REF!,#REF!,0.05))))))) | BN37: =BM37*SUM(BK37,BH37,BC37) | BP37: =IF(BF37<=#REF!,#REF!,IF(BF37<=#REF!,#REF!,IF(BF37<=#REF!,#REF!,IF(BF37<=#REF!,#REF!,IF(BF37<=#REF!,#REF!,IF(BF37<=#REF!,#REF!,IF(BF37<=#REF!,#REF!,0.05))))))) | BQ37: =BP37*BF37 | BS37: =0.07*SUM(BC37,BH37,BK37,BN37,BQ37) | BU37: =SUM(BS37,BQ37,BN37,BK37,BH37,BC37) | BV37: =SUM(BQ37,BN37,BK37,BH37) | BW37: =BV37/BU37 | CM37: 26000 | CP37: =CM37 | CS37: =CM37+CP37 | CV37: =CS37 | CW37: =IF(CM37<=BO$4,BN$4,IF(CM37<=BO$5,BN$5,IF(CM37<=BO$6,BN$6,IF(CM37<=BO$7,BN$7,IF(CM37<=BO$12,BN$12,IF(CM37<=BO$13,BN$13,IF(CM37<=BO$14,BN$14,0.05))))))) | CX37: =CW37*CM37 | CZ37: =IF(CP37<=BR$4,BQ$4,IF(CP37<=BR$5,BQ$5,IF(CP37<=BR$6,BQ$6,IF(CP37<=BR$7,BQ$7,IF(CP37<=BR$12,BQ$12,IF(CP37<=BR$13,BQ$13,IF(CP37<=BR$14,BQ$14,0.05))))))) | DA37: =CZ37*CP37 | DC37: =IF(CS37<=BU$4,BT$4,IF(CS37<=BU$5,BT$5,IF(CS37<=BU$6,BT$6,IF(CS37<=BU$7,BT$7,IF(CS37<=BU$12,BT$12,IF(CS37<=BU$13,BT$13,IF(CS37<=BU$14,BT$14,0.05))))))) | DD37: =DC37*SUM(DA37,CX37,CS37) | DF37: =IF(CV37<=BX$4,BW$4,IF(CV37<=BX$5,BW$5,IF(CV37<=BX$6,BW$6,IF(CV37<=BX$7,BW$7,IF(CV37<=BX$12,BW$12,IF(CV37<=BX$13,BW$13,IF(CV37<=BX$14,BW$14,0.05))))))) | DG37: =DF37*CV37 | DI37: =0.07*SUM(CS37,CX37,DA37,DD37,DG37) | DK37: =SUM(DI37,DG37,DD37,DA37,CX37,CS37) | DL37: =SUM(DG37,DD37,DA37,CX37) | DM37: =DL37/DK37
C38: Sand &/or Cap | D38: =IF(A37=AS125,AF126,IF(A37=AS126,AF131,IF(A37=AS127,AH137,IF(A37=AS128,AH143,IF(A37=AS129,AF148,IF(A37=AS130,AH154,IF(A37=AS131,0,IF(A37=AS132,0,IF(A37=AS133,AP136,IF(A37=AS134,AP142,IF(A37=AS135,0,IF(A37=AS136,AP153,0)))))))))))) | K38: divided SF | L38: =$B$45/M38 | M38: 6 | N38: # divided by | AW38: 27000 | AZ38: =AW38 | BC38: =AW38+AZ38 | BF38: =BC38 | BG38: =IF(AW38<=#REF!,#REF!,IF(AW38<=#REF!,#REF!,IF(AW38<=#REF!,#REF!,IF(AW38<=#REF!,#REF!,IF(AW38<=#REF!,#REF!,IF(AW38<=#REF!,#REF!,IF(AW38<=#REF!,#REF!,0.05))))))) | BH38: =BG38*AW38 | BJ38: =IF(AZ38<=#REF!,#REF!,IF(AZ38<=#REF!,#REF!,IF(AZ38<=#REF!,#REF!,IF(AZ38<=#REF!,#REF!,IF(AZ38<=#REF!,#REF!,IF(AZ38<=#REF!,#REF!,IF(AZ38<=#REF!,#REF!,0.05))))))) | BK38: =BJ38*AZ38 | BM38: =IF(BC38<=#REF!,#REF!,IF(BC38<=#REF!,#REF!,IF(BC38<=#REF!,#REF!,IF(BC38<=#REF!,#REF!,IF(BC38<=#REF!,#REF!,IF(BC38<=#REF!,#REF!,IF(BC38<=#REF!,#REF!,0.05))))))) | BN38: =BM38*SUM(BK38,BH38,BC38) | BP38: =IF(BF38<=#REF!,#REF!,IF(BF38<=#REF!,#REF!,IF(BF38<=#REF!,#REF!,IF(BF38<=#REF!,#REF!,IF(BF38<=#REF!,#REF!,IF(BF38<=#REF!,#REF!,IF(BF38<=#REF!,#REF!,0.05))))))) | BQ38: =BP38*BF38 | BS38: =0.07*SUM(BC38,BH38,BK38,BN38,BQ38) | BU38: =SUM(BS38,BQ38,BN38,BK38,BH38,BC38) | BV38: =SUM(BQ38,BN38,BK38,BH38) | BW38: =BV38/BU38 | CM38: 27000 | CP38: =CM38 | CS38: =CM38+CP38 | CV38: =CS38 | CW38: =IF(CM38<=BO$4,BN$4,IF(CM38<=BO$5,BN$5,IF(CM38<=BO$6,BN$6,IF(CM38<=BO$7,BN$7,IF(CM38<=BO$12,BN$12,IF(CM38<=BO$13,BN$13,IF(CM38<=BO$14,BN$14,0.05))))))) | CX38: =CW38*CM38 | CZ38: =IF(CP38<=BR$4,BQ$4,IF(CP38<=BR$5,BQ$5,IF(CP38<=BR$6,BQ$6,IF(CP38<=BR$7,BQ$7,IF(CP38<=BR$12,BQ$12,IF(CP38<=BR$13,BQ$13,IF(CP38<=BR$14,BQ$14,0.05))))))) | DA38: =CZ38*CP38 | DC38: =IF(CS38<=BU$4,BT$4,IF(CS38<=BU$5,BT$5,IF(CS38<=BU$6,BT$6,IF(CS38<=BU$7,BT$7,IF(CS38<=BU$12,BT$12,IF(CS38<=BU$13,BT$13,IF(CS38<=BU$14,BT$14,0.05))))))) | DD38: =DC38*SUM(DA38,CX38,CS38) | DF38: =IF(CV38<=BX$4,BW$4,IF(CV38<=BX$5,BW$5,IF(CV38<=BX$6,BW$6,IF(CV38<=BX$7,BW$7,IF(CV38<=BX$12,BW$12,IF(CV38<=BX$13,BW$13,IF(CV38<=BX$14,BW$14,0.05))))))) | DG38: =DF38*CV38 | DI38: =0.07*SUM(CS38,CX38,DA38,DD38,DG38) | DK38: =SUM(DI38,DG38,DD38,DA38,CX38,CS38) | DL38: =SUM(DG38,DD38,DA38,CX38) | DM38: =DL38/DK38
D39: =B39*C39 | K39: divided SF | L39: =$B$45/M39 | M39: 5 | N39: # divided by | AW39: 28000 | AZ39: =AW39 | BC39: =AW39+AZ39 | BF39: =BC39 | BG39: =IF(AW39<=#REF!,#REF!,IF(AW39<=#REF!,#REF!,IF(AW39<=#REF!,#REF!,IF(AW39<=#REF!,#REF!,IF(AW39<=#REF!,#REF!,IF(AW39<=#REF!,#REF!,IF(AW39<=#REF!,#REF!,0.05))))))) | BH39: =BG39*AW39 | BJ39: =IF(AZ39<=#REF!,#REF!,IF(AZ39<=#REF!,#REF!,IF(AZ39<=#REF!,#REF!,IF(AZ39<=#REF!,#REF!,IF(AZ39<=#REF!,#REF!,IF(AZ39<=#REF!,#REF!,IF(AZ39<=#REF!,#REF!,0.05))))))) | BK39: =BJ39*AZ39 | BM39: =IF(BC39<=#REF!,#REF!,IF(BC39<=#REF!,#REF!,IF(BC39<=#REF!,#REF!,IF(BC39<=#REF!,#REF!,IF(BC39<=#REF!,#REF!,IF(BC39<=#REF!,#REF!,IF(BC39<=#REF!,#REF!,0.05))))))) | BN39: =BM39*SUM(BK39,BH39,BC39) | BP39: =IF(BF39<=#REF!,#REF!,IF(BF39<=#REF!,#REF!,IF(BF39<=#REF!,#REF!,IF(BF39<=#REF!,#REF!,IF(BF39<=#REF!,#REF!,IF(BF39<=#REF!,#REF!,IF(BF39<=#REF!,#REF!,0.05))))))) | BQ39: =BP39*BF39 | BS39: =0.07*SUM(BC39,BH39,BK39,BN39,BQ39) | BU39: =SUM(BS39,BQ39,BN39,BK39,BH39,BC39) | BV39: =SUM(BQ39,BN39,BK39,BH39) | BW39: =BV39/BU39 | CM39: 28000 | CP39: =CM39 | CS39: =CM39+CP39 | CV39: =CS39 | CW39: =IF(CM39<=BO$4,BN$4,IF(CM39<=BO$5,BN$5,IF(CM39<=BO$6,BN$6,IF(CM39<=BO$7,BN$7,IF(CM39<=BO$12,BN$12,IF(CM39<=BO$13,BN$13,IF(CM39<=BO$14,BN$14,0.05))))))) | CX39: =CW39*CM39 | CZ39: =IF(CP39<=BR$4,BQ$4,IF(CP39<=BR$5,BQ$5,IF(CP39<=BR$6,BQ$6,IF(CP39<=BR$7,BQ$7,IF(CP39<=BR$12,BQ$12,IF(CP39<=BR$13,BQ$13,IF(CP39<=BR$14,BQ$14,0.05))))))) | DA39: =CZ39*CP39 | DC39: =IF(CS39<=BU$4,BT$4,IF(CS39<=BU$5,BT$5,IF(CS39<=BU$6,BT$6,IF(CS39<=BU$7,BT$7,IF(CS39<=BU$12,BT$12,IF(CS39<=BU$13,BT$13,IF(CS39<=BU$14,BT$14,0.05))))))) | DD39: =DC39*SUM(DA39,CX39,CS39) | DF39: =IF(CV39<=BX$4,BW$4,IF(CV39<=BX$5,BW$5,IF(CV39<=BX$6,BW$6,IF(CV39<=BX$7,BW$7,IF(CV39<=BX$12,BW$12,IF(CV39<=BX$13,BW$13,IF(CV39<=BX$14,BW$14,0.05))))))) | DG39: =DF39*CV39 | DI39: =0.07*SUM(CS39,CX39,DA39,DD39,DG39) | DK39: =SUM(DI39,DG39,DD39,DA39,CX39,CS39) | DL39: =SUM(DG39,DD39,DA39,CX39) | DM39: =DL39/DK39
A40: Material Sub Total | B40: Epoxy Discount | C40: Poly-Crete Discount | D40: =ROUNDUP(SUM(D18:D39),0) | E40: $ per SW 010126 | F40: +6% for 5/1/26 ^ $ | G40: and Torginol Flake: +0.07 & Quartz: +0.05 | K40: divided SF | L40: =$B$45/M40 | M40: 4 | N40: # divided by | AW40: 29000 | AZ40: =AW40 | BC40: =AW40+AZ40 | BF40: =BC40 | BG40: =IF(AW40<=#REF!,#REF!,IF(AW40<=#REF!,#REF!,IF(AW40<=#REF!,#REF!,IF(AW40<=#REF!,#REF!,IF(AW40<=#REF!,#REF!,IF(AW40<=#REF!,#REF!,IF(AW40<=#REF!,#REF!,0.05))))))) | BH40: =BG40*AW40 | BJ40: =IF(AZ40<=#REF!,#REF!,IF(AZ40<=#REF!,#REF!,IF(AZ40<=#REF!,#REF!,IF(AZ40<=#REF!,#REF!,IF(AZ40<=#REF!,#REF!,IF(AZ40<=#REF!,#REF!,IF(AZ40<=#REF!,#REF!,0.05))))))) | BK40: =BJ40*AZ40 | BM40: =IF(BC40<=#REF!,#REF!,IF(BC40<=#REF!,#REF!,IF(BC40<=#REF!,#REF!,IF(BC40<=#REF!,#REF!,IF(BC40<=#REF!,#REF!,IF(BC40<=#REF!,#REF!,IF(BC40<=#REF!,#REF!,0.05))))))) | BN40: =BM40*SUM(BK40,BH40,BC40) | BP40: =IF(BF40<=#REF!,#REF!,IF(BF40<=#REF!,#REF!,IF(BF40<=#REF!,#REF!,IF(BF40<=#REF!,#REF!,IF(BF40<=#REF!,#REF!,IF(BF40<=#REF!,#REF!,IF(BF40<=#REF!,#REF!,0.05))))))) | BQ40: =BP40*BF40 | BS40: =0.07*SUM(BC40,BH40,BK40,BN40,BQ40) | BU40: =SUM(BS40,BQ40,BN40,BK40,BH40,BC40) | BV40: =SUM(BQ40,BN40,BK40,BH40) | BW40: =BV40/BU40 | CM40: 29000 | CP40: =CM40 | CS40: =CM40+CP40 | CV40: =CS40 | CW40: =IF(CM40<=BO$4,BN$4,IF(CM40<=BO$5,BN$5,IF(CM40<=BO$6,BN$6,IF(CM40<=BO$7,BN$7,IF(CM40<=BO$12,BN$12,IF(CM40<=BO$13,BN$13,IF(CM40<=BO$14,BN$14,0.05))))))) | CX40: =CW40*CM40 | CZ40: =IF(CP40<=BR$4,BQ$4,IF(CP40<=BR$5,BQ$5,IF(CP40<=BR$6,BQ$6,IF(CP40<=BR$7,BQ$7,IF(CP40<=BR$12,BQ$12,IF(CP40<=BR$13,BQ$13,IF(CP40<=BR$14,BQ$14,0.05))))))) | DA40: =CZ40*CP40 | DC40: =IF(CS40<=BU$4,BT$4,IF(CS40<=BU$5,BT$5,IF(CS40<=BU$6,BT$6,IF(CS40<=BU$7,BT$7,IF(CS40<=BU$12,BT$12,IF(CS40<=BU$13,BT$13,IF(CS40<=BU$14,BT$14,0.05))))))) | DD40: =DC40*SUM(DA40,CX40,CS40) | DF40: =IF(CV40<=BX$4,BW$4,IF(CV40<=BX$5,BW$5,IF(CV40<=BX$6,BW$6,IF(CV40<=BX$7,BW$7,IF(CV40<=BX$12,BW$12,IF(CV40<=BX$13,BW$13,IF(CV40<=BX$14,BW$14,0.05))))))) | DG40: =DF40*CV40 | DI40: =0.07*SUM(CS40,CX40,DA40,DD40,DG40) | DK40: =SUM(DI40,DG40,DD40,DA40,CX40,CS40) | DL40: =SUM(DG40,DD40,DA40,CX40) | DM40: =DL40/DK40
A41: Discount / Overage | B41: 0 | C41: =B41 | D41: Bulk Discount OFF | E41: ? Extra discount ? | G41: =IF(H41="15%","Request Discount:",IF(H41="20%","Request Discount:",IF(H41="25%","Request Discount:"))) | H41: =IF(D40>=100000,"25%",IF(D40>=30000,"20%",IF(D40>=10000,"15%"))) | K41: divided SF | L41: =$B$45/M41 | M41: 3 | N41: # divided by | O41: =O43/M41 | AW41: 30000 | AZ41: =AW41 | BC41: =AW41+AZ41 | BF41: =BC41 | BG41: =IF(AW41<=#REF!,#REF!,IF(AW41<=#REF!,#REF!,IF(AW41<=#REF!,#REF!,IF(AW41<=#REF!,#REF!,IF(AW41<=#REF!,#REF!,IF(AW41<=#REF!,#REF!,IF(AW41<=#REF!,#REF!,0.05))))))) | BH41: =BG41*AW41 | BJ41: =IF(AZ41<=#REF!,#REF!,IF(AZ41<=#REF!,#REF!,IF(AZ41<=#REF!,#REF!,IF(AZ41<=#REF!,#REF!,IF(AZ41<=#REF!,#REF!,IF(AZ41<=#REF!,#REF!,IF(AZ41<=#REF!,#REF!,0.05))))))) | BK41: =BJ41*AZ41 | BM41: =IF(BC41<=#REF!,#REF!,IF(BC41<=#REF!,#REF!,IF(BC41<=#REF!,#REF!,IF(BC41<=#REF!,#REF!,IF(BC41<=#REF!,#REF!,IF(BC41<=#REF!,#REF!,IF(BC41<=#REF!,#REF!,0.05))))))) | BN41: =BM41*SUM(BK41,BH41,BC41) | BP41: =IF(BF41<=#REF!,#REF!,IF(BF41<=#REF!,#REF!,IF(BF41<=#REF!,#REF!,IF(BF41<=#REF!,#REF!,IF(BF41<=#REF!,#REF!,IF(BF41<=#REF!,#REF!,IF(BF41<=#REF!,#REF!,0.05))))))) | BQ41: =BP41*BF41 | BS41: =0.07*SUM(BC41,BH41,BK41,BN41,BQ41) | BU41: =SUM(BS41,BQ41,BN41,BK41,BH41,BC41) | BV41: =SUM(BQ41,BN41,BK41,BH41) | BW41: =BV41/BU41 | CM41: 30000 | CP41: =CM41 | CS41: =CM41+CP41 | CV41: =CS41 | CW41: =IF(CM41<=BO$4,BN$4,IF(CM41<=BO$5,BN$5,IF(CM41<=BO$6,BN$6,IF(CM41<=BO$7,BN$7,IF(CM41<=BO$12,BN$12,IF(CM41<=BO$13,BN$13,IF(CM41<=BO$14,BN$14,0.05))))))) | CX41: =CW41*CM41 | CZ41: =IF(CP41<=BR$4,BQ$4,IF(CP41<=BR$5,BQ$5,IF(CP41<=BR$6,BQ$6,IF(CP41<=BR$7,BQ$7,IF(CP41<=BR$12,BQ$12,IF(CP41<=BR$13,BQ$13,IF(CP41<=BR$14,BQ$14,0.05))))))) | DA41: =CZ41*CP41 | DC41: =IF(CS41<=BU$4,BT$4,IF(CS41<=BU$5,BT$5,IF(CS41<=BU$6,BT$6,IF(CS41<=BU$7,BT$7,IF(CS41<=BU$12,BT$12,IF(CS41<=BU$13,BT$13,IF(CS41<=BU$14,BT$14,0.05))))))) | DD41: =DC41*SUM(DA41,CX41,CS41) | DF41: =IF(CV41<=BX$4,BW$4,IF(CV41<=BX$5,BW$5,IF(CV41<=BX$6,BW$6,IF(CV41<=BX$7,BW$7,IF(CV41<=BX$12,BW$12,IF(CV41<=BX$13,BW$13,IF(CV41<=BX$14,BW$14,0.05))))))) | DG41: =DF41*CV41 | DI41: =0.07*SUM(CS41,CX41,DA41,DD41,DG41) | DK41: =SUM(DI41,DG41,DD41,DA41,CX41,CS41) | DL41: =SUM(DG41,DD41,DA41,CX41) | DM41: =DL41/DK41
A42: Shipping + Matr'l Escln | B42: =0.05+IF(D40<=5000,0.1,IF(D40<=10000,0.06,0.04)) | D42: =ROUNDUP(D40*B42,0) | H42: Material Budget | K42: divided SF | L42: =$B$45/M42 | M42: 2 | N42: # divided by | O42: =O43/M42 | AB42: MACRO Single Flake | AW42: 31000 | AZ42: =AW42 | BC42: =AW42+AZ42 | BF42: =BC42 | BG42: =IF(AW42<=#REF!,#REF!,IF(AW42<=#REF!,#REF!,IF(AW42<=#REF!,#REF!,IF(AW42<=#REF!,#REF!,IF(AW42<=#REF!,#REF!,IF(AW42<=#REF!,#REF!,IF(AW42<=#REF!,#REF!,0.05))))))) | BH42: =BG42*AW42 | BJ42: =IF(AZ42<=#REF!,#REF!,IF(AZ42<=#REF!,#REF!,IF(AZ42<=#REF!,#REF!,IF(AZ42<=#REF!,#REF!,IF(AZ42<=#REF!,#REF!,IF(AZ42<=#REF!,#REF!,IF(AZ42<=#REF!,#REF!,0.05))))))) | BK42: =BJ42*AZ42 | BM42: =IF(BC42<=#REF!,#REF!,IF(BC42<=#REF!,#REF!,IF(BC42<=#REF!,#REF!,IF(BC42<=#REF!,#REF!,IF(BC42<=#REF!,#REF!,IF(BC42<=#REF!,#REF!,IF(BC42<=#REF!,#REF!,0.05))))))) | BN42: =BM42*SUM(BK42,BH42,BC42) | BP42: =IF(BF42<=#REF!,#REF!,IF(BF42<=#REF!,#REF!,IF(BF42<=#REF!,#REF!,IF(BF42<=#REF!,#REF!,IF(BF42<=#REF!,#REF!,IF(BF42<=#REF!,#REF!,IF(BF42<=#REF!,#REF!,0.05))))))) | BQ42: =BP42*BF42 | BS42: =0.07*SUM(BC42,BH42,BK42,BN42,BQ42) | BU42: =SUM(BS42,BQ42,BN42,BK42,BH42,BC42) | BV42: =SUM(BQ42,BN42,BK42,BH42) | BW42: =BV42/BU42 | CM42: 31000 | CP42: =CM42 | CS42: =CM42+CP42 | CV42: =CS42 | CW42: =IF(CM42<=BO$4,BN$4,IF(CM42<=BO$5,BN$5,IF(CM42<=BO$6,BN$6,IF(CM42<=BO$7,BN$7,IF(CM42<=BO$12,BN$12,IF(CM42<=BO$13,BN$13,IF(CM42<=BO$14,BN$14,0.05))))))) | CX42: =CW42*CM42 | CZ42: =IF(CP42<=BR$4,BQ$4,IF(CP42<=BR$5,BQ$5,IF(CP42<=BR$6,BQ$6,IF(CP42<=BR$7,BQ$7,IF(CP42<=BR$12,BQ$12,IF(CP42<=BR$13,BQ$13,IF(CP42<=BR$14,BQ$14,0.05))))))) | DA42: =CZ42*CP42 | DC42: =IF(CS42<=BU$4,BT$4,IF(CS42<=BU$5,BT$5,IF(CS42<=BU$6,BT$6,IF(CS42<=BU$7,BT$7,IF(CS42<=BU$12,BT$12,IF(CS42<=BU$13,BT$13,IF(CS42<=BU$14,BT$14,0.05))))))) | DD42: =DC42*SUM(DA42,CX42,CS42) | DF42: =IF(CV42<=BX$4,BW$4,IF(CV42<=BX$5,BW$5,IF(CV42<=BX$6,BW$6,IF(CV42<=BX$7,BW$7,IF(CV42<=BX$12,BW$12,IF(CV42<=BX$13,BW$13,IF(CV42<=BX$14,BW$14,0.05))))))) | DG42: =DF42*CV42 | DI42: =0.07*SUM(CS42,CX42,DA42,DD42,DG42) | DK42: =SUM(DI42,DG42,DD42,DA42,CX42,CS42) | DL42: =SUM(DG42,DD42,DA42,CX42) | DM42: =DL42/DK42
A43: Material Total | D43: =SUM(D40:D42) | E43: =D43/B45 | F43: Material $/SF | H43: =D43 | K43: TOTAL SF | L43: =B45 | O43: =I47 | P43: SF for System | Q43: =J47 | R43: LF Cove | S43: =Q43/O43 | T43: cove ratio | AB43: =B45 | AC43: SF for System | AD43: =D45 | AE43: LF Cove | AF43: =AD43/AB43 | AG43: cove ratio | AW43: 32000 | AZ43: =AW43 | BC43: =AW43+AZ43 | BF43: =BC43 | BG43: =IF(AW43<=#REF!,#REF!,IF(AW43<=#REF!,#REF!,IF(AW43<=#REF!,#REF!,IF(AW43<=#REF!,#REF!,IF(AW43<=#REF!,#REF!,IF(AW43<=#REF!,#REF!,IF(AW43<=#REF!,#REF!,0.05))))))) | BH43: =BG43*AW43 | BJ43: =IF(AZ43<=#REF!,#REF!,IF(AZ43<=#REF!,#REF!,IF(AZ43<=#REF!,#REF!,IF(AZ43<=#REF!,#REF!,IF(AZ43<=#REF!,#REF!,IF(AZ43<=#REF!,#REF!,IF(AZ43<=#REF!,#REF!,0.05))))))) | BK43: =BJ43*AZ43 | BM43: =IF(BC43<=#REF!,#REF!,IF(BC43<=#REF!,#REF!,IF(BC43<=#REF!,#REF!,IF(BC43<=#REF!,#REF!,IF(BC43<=#REF!,#REF!,IF(BC43<=#REF!,#REF!,IF(BC43<=#REF!,#REF!,0.05))))))) | BN43: =BM43*SUM(BK43,BH43,BC43) | BP43: =IF(BF43<=#REF!,#REF!,IF(BF43<=#REF!,#REF!,IF(BF43<=#REF!,#REF!,IF(BF43<=#REF!,#REF!,IF(BF43<=#REF!,#REF!,IF(BF43<=#REF!,#REF!,IF(BF43<=#REF!,#REF!,0.05))))))) | BQ43: =BP43*BF43 | BS43: =0.07*SUM(BC43,BH43,BK43,BN43,BQ43) | BU43: =SUM(BS43,BQ43,BN43,BK43,BH43,BC43) | BV43: =SUM(BQ43,BN43,BK43,BH43) | BW43: =BV43/BU43 | CM43: 32000 | CP43: =CM43 | CS43: =CM43+CP43 | CV43: =CS43 | CW43: =IF(CM43<=BO$4,BN$4,IF(CM43<=BO$5,BN$5,IF(CM43<=BO$6,BN$6,IF(CM43<=BO$7,BN$7,IF(CM43<=BO$12,BN$12,IF(CM43<=BO$13,BN$13,IF(CM43<=BO$14,BN$14,0.05))))))) | CX43: =CW43*CM43 | CZ43: =IF(CP43<=BR$4,BQ$4,IF(CP43<=BR$5,BQ$5,IF(CP43<=BR$6,BQ$6,IF(CP43<=BR$7,BQ$7,IF(CP43<=BR$12,BQ$12,IF(CP43<=BR$13,BQ$13,IF(CP43<=BR$14,BQ$14,0.05))))))) | DA43: =CZ43*CP43 | DC43: =IF(CS43<=BU$4,BT$4,IF(CS43<=BU$5,BT$5,IF(CS43<=BU$6,BT$6,IF(CS43<=BU$7,BT$7,IF(CS43<=BU$12,BT$12,IF(CS43<=BU$13,BT$13,IF(CS43<=BU$14,BT$14,0.05))))))) | DD43: =DC43*SUM(DA43,CX43,CS43) | DF43: =IF(CV43<=BX$4,BW$4,IF(CV43<=BX$5,BW$5,IF(CV43<=BX$6,BW$6,IF(CV43<=BX$7,BW$7,IF(CV43<=BX$12,BW$12,IF(CV43<=BX$13,BW$13,IF(CV43<=BX$14,BW$14,0.05))))))) | DG43: =DF43*CV43 | DI43: =0.07*SUM(CS43,CX43,DA43,DD43,DG43) | DK43: =SUM(DI43,DG43,DD43,DA43,CX43,CS43) | DL43: =SUM(DG43,DD43,DA43,CX43) | DM43: =DL43/DK43
A44: Floor ONLY SF: | B44: =E20+E24 | L44: # of Guys (epoxy) | O44: (Avg.) Guys | P44: (Avg.) Days | Q44: Labor Value | R44: Wage Rate | AB44: (Avg.) Guys | AC44: (Avg.) Days | AD44: Labor Value | AE44: Wage Rate | AW44: 33000 | AZ44: =AW44 | BC44: =AW44+AZ44 | BF44: =BC44 | BG44: =IF(AW44<=#REF!,#REF!,IF(AW44<=#REF!,#REF!,IF(AW44<=#REF!,#REF!,IF(AW44<=#REF!,#REF!,IF(AW44<=#REF!,#REF!,IF(AW44<=#REF!,#REF!,IF(AW44<=#REF!,#REF!,0.05))))))) | BH44: =BG44*AW44 | BJ44: =IF(AZ44<=#REF!,#REF!,IF(AZ44<=#REF!,#REF!,IF(AZ44<=#REF!,#REF!,IF(AZ44<=#REF!,#REF!,IF(AZ44<=#REF!,#REF!,IF(AZ44<=#REF!,#REF!,IF(AZ44<=#REF!,#REF!,0.05))))))) | BK44: =BJ44*AZ44 | BM44: =IF(BC44<=#REF!,#REF!,IF(BC44<=#REF!,#REF!,IF(BC44<=#REF!,#REF!,IF(BC44<=#REF!,#REF!,IF(BC44<=#REF!,#REF!,IF(BC44<=#REF!,#REF!,IF(BC44<=#REF!,#REF!,0.05))))))) | BN44: =BM44*SUM(BK44,BH44,BC44) | BP44: =IF(BF44<=#REF!,#REF!,IF(BF44<=#REF!,#REF!,IF(BF44<=#REF!,#REF!,IF(BF44<=#REF!,#REF!,IF(BF44<=#REF!,#REF!,IF(BF44<=#REF!,#REF!,IF(BF44<=#REF!,#REF!,0.05))))))) | BQ44: =BP44*BF44 | BS44: =0.07*SUM(BC44,BH44,BK44,BN44,BQ44) | BU44: =SUM(BS44,BQ44,BN44,BK44,BH44,BC44) | BV44: =SUM(BQ44,BN44,BK44,BH44) | BW44: =BV44/BU44 | CM44: 33000 | CP44: =CM44 | CS44: =CM44+CP44 | CV44: =CS44 | CW44: =IF(CM44<=BO$4,BN$4,IF(CM44<=BO$5,BN$5,IF(CM44<=BO$6,BN$6,IF(CM44<=BO$7,BN$7,IF(CM44<=BO$12,BN$12,IF(CM44<=BO$13,BN$13,IF(CM44<=BO$14,BN$14,0.05))))))) | CX44: =CW44*CM44 | CZ44: =IF(CP44<=BR$4,BQ$4,IF(CP44<=BR$5,BQ$5,IF(CP44<=BR$6,BQ$6,IF(CP44<=BR$7,BQ$7,IF(CP44<=BR$12,BQ$12,IF(CP44<=BR$13,BQ$13,IF(CP44<=BR$14,BQ$14,0.05))))))) | DA44: =CZ44*CP44 | DC44: =IF(CS44<=BU$4,BT$4,IF(CS44<=BU$5,BT$5,IF(CS44<=BU$6,BT$6,IF(CS44<=BU$7,BT$7,IF(CS44<=BU$12,BT$12,IF(CS44<=BU$13,BT$13,IF(CS44<=BU$14,BT$14,0.05))))))) | DD44: =DC44*SUM(DA44,CX44,CS44) | DF44: =IF(CV44<=BX$4,BW$4,IF(CV44<=BX$5,BW$5,IF(CV44<=BX$6,BW$6,IF(CV44<=BX$7,BW$7,IF(CV44<=BX$12,BW$12,IF(CV44<=BX$13,BW$13,IF(CV44<=BX$14,BW$14,0.05))))))) | DG44: =DF44*CV44 | DI44: =0.07*SUM(CS44,CX44,DA44,DD44,DG44) | DK44: =SUM(DI44,DG44,DD44,DA44,CX44,CS44) | DL44: =SUM(DG44,DD44,DA44,CX44) | DM44: =DL44/DK44
A45: Square Footage: | B45: =E20+E24 | C45: Linear Footage: | D45: =E34+E37 | E45: 8 hour days | F45: =D45/B45 | G45: : Ratio of Cove-Floor | H45: 15%-25% = Normal | I45: SF for MH Calc | J45: LF | K45: Cove Ratio % | L45: Flake or lesser | M45: Qrtz/SLB or + | O45: 3 | P45: =P50/O45 | Q45: =O45*P45*R45*8 | R45: =C47 | AB45: 3 | AC45: =AC50/AB45 | AD45: =AB45*AC45*AE45*8 | AE45: =C47 | AW45: 34000 | AZ45: =AW45 | BC45: =AW45+AZ45 | BF45: =BC45 | BG45: =IF(AW45<=#REF!,#REF!,IF(AW45<=#REF!,#REF!,IF(AW45<=#REF!,#REF!,IF(AW45<=#REF!,#REF!,IF(AW45<=#REF!,#REF!,IF(AW45<=#REF!,#REF!,IF(AW45<=#REF!,#REF!,0.05))))))) | BH45: =BG45*AW45 | BJ45: =IF(AZ45<=#REF!,#REF!,IF(AZ45<=#REF!,#REF!,IF(AZ45<=#REF!,#REF!,IF(AZ45<=#REF!,#REF!,IF(AZ45<=#REF!,#REF!,IF(AZ45<=#REF!,#REF!,IF(AZ45<=#REF!,#REF!,0.05))))))) | BK45: =BJ45*AZ45 | BM45: =IF(BC45<=#REF!,#REF!,IF(BC45<=#REF!,#REF!,IF(BC45<=#REF!,#REF!,IF(BC45<=#REF!,#REF!,IF(BC45<=#REF!,#REF!,IF(BC45<=#REF!,#REF!,IF(BC45<=#REF!,#REF!,0.05))))))) | BN45: =BM45*SUM(BK45,BH45,BC45) | BP45: =IF(BF45<=#REF!,#REF!,IF(BF45<=#REF!,#REF!,IF(BF45<=#REF!,#REF!,IF(BF45<=#REF!,#REF!,IF(BF45<=#REF!,#REF!,IF(BF45<=#REF!,#REF!,IF(BF45<=#REF!,#REF!,0.05))))))) | BQ45: =BP45*BF45 | BS45: =0.07*SUM(BC45,BH45,BK45,BN45,BQ45) | BU45: =SUM(BS45,BQ45,BN45,BK45,BH45,BC45) | BV45: =SUM(BQ45,BN45,BK45,BH45) | BW45: =BV45/BU45 | CM45: 34000 | CP45: =CM45 | CS45: =CM45+CP45 | CV45: =CS45 | CW45: =IF(CM45<=BO$4,BN$4,IF(CM45<=BO$5,BN$5,IF(CM45<=BO$6,BN$6,IF(CM45<=BO$7,BN$7,IF(CM45<=BO$12,BN$12,IF(CM45<=BO$13,BN$13,IF(CM45<=BO$14,BN$14,0.05))))))) | CX45: =CW45*CM45 | CZ45: =IF(CP45<=BR$4,BQ$4,IF(CP45<=BR$5,BQ$5,IF(CP45<=BR$6,BQ$6,IF(CP45<=BR$7,BQ$7,IF(CP45<=BR$12,BQ$12,IF(CP45<=BR$13,BQ$13,IF(CP45<=BR$14,BQ$14,0.05))))))) | DA45: =CZ45*CP45 | DC45: =IF(CS45<=BU$4,BT$4,IF(CS45<=BU$5,BT$5,IF(CS45<=BU$6,BT$6,IF(CS45<=BU$7,BT$7,IF(CS45<=BU$12,BT$12,IF(CS45<=BU$13,BT$13,IF(CS45<=BU$14,BT$14,0.05))))))) | DD45: =DC45*SUM(DA45,CX45,CS45) | DF45: =IF(CV45<=BX$4,BW$4,IF(CV45<=BX$5,BW$5,IF(CV45<=BX$6,BW$6,IF(CV45<=BX$7,BW$7,IF(CV45<=BX$12,BW$12,IF(CV45<=BX$13,BW$13,IF(CV45<=BX$14,BW$14,0.05))))))) | DG45: =DF45*CV45 | DI45: =0.07*SUM(CS45,CX45,DA45,DD45,DG45) | DK45: =SUM(DI45,DG45,DD45,DA45,CX45,CS45) | DL45: =SUM(DG45,DD45,DA45,CX45) | DM45: =DL45/DK45
A46: Labor: Guys | B46: Days | C46: Rate (PW?) | D46: Totals | E46: =(IF(D5="Yes","PW","-")) | F46: Estimated SF/MH | G46: SF/MH Benchmark (1K sf - 3K sf) | L46: 2 | M46: 2 | N46: < 500 sf | O46: UNIT | P46: Prep / Patch | Q46: Cove | R46: Prime | S46: Broadcast | T46: (? double BC ?) | U46: Grout | V46: (? double Grout ?) | W46: Topcoat | AB46: UNIT | AC46: Prep / Patch | AD46: Cove | AE46: Prime | AF46: Broadcast | AG46: (? double BC ?) | AH46: Grout | AI46: (? double Grout ?) | AJ46: Topcoat | AW46: 35000 | AZ46: =AW46 | BC46: =AW46+AZ46 | BF46: =BC46 | BG46: =IF(AW46<=#REF!,#REF!,IF(AW46<=#REF!,#REF!,IF(AW46<=#REF!,#REF!,IF(AW46<=#REF!,#REF!,IF(AW46<=#REF!,#REF!,IF(AW46<=#REF!,#REF!,IF(AW46<=#REF!,#REF!,0.05))))))) | BH46: =BG46*AW46 | BJ46: =IF(AZ46<=#REF!,#REF!,IF(AZ46<=#REF!,#REF!,IF(AZ46<=#REF!,#REF!,IF(AZ46<=#REF!,#REF!,IF(AZ46<=#REF!,#REF!,IF(AZ46<=#REF!,#REF!,IF(AZ46<=#REF!,#REF!,0.05))))))) | BK46: =BJ46*AZ46 | BM46: =IF(BC46<=#REF!,#REF!,IF(BC46<=#REF!,#REF!,IF(BC46<=#REF!,#REF!,IF(BC46<=#REF!,#REF!,IF(BC46<=#REF!,#REF!,IF(BC46<=#REF!,#REF!,IF(BC46<=#REF!,#REF!,0.05))))))) | BN46: =BM46*SUM(BK46,BH46,BC46) | BP46: =IF(BF46<=#REF!,#REF!,IF(BF46<=#REF!,#REF!,IF(BF46<=#REF!,#REF!,IF(BF46<=#REF!,#REF!,IF(BF46<=#REF!,#REF!,IF(BF46<=#REF!,#REF!,IF(BF46<=#REF!,#REF!,0.05))))))) | BQ46: =BP46*BF46 | BS46: =0.07*SUM(BC46,BH46,BK46,BN46,BQ46) | BU46: =SUM(BS46,BQ46,BN46,BK46,BH46,BC46) | BV46: =SUM(BQ46,BN46,BK46,BH46) | BW46: =BV46/BU46 | CM46: 35000 | CP46: =CM46 | CS46: =CM46+CP46 | CV46: =CS46 | CW46: =IF(CM46<=BO$4,BN$4,IF(CM46<=BO$5,BN$5,IF(CM46<=BO$6,BN$6,IF(CM46<=BO$7,BN$7,IF(CM46<=BO$12,BN$12,IF(CM46<=BO$13,BN$13,IF(CM46<=BO$14,BN$14,0.05))))))) | CX46: =CW46*CM46 | CZ46: =IF(CP46<=BR$4,BQ$4,IF(CP46<=BR$5,BQ$5,IF(CP46<=BR$6,BQ$6,IF(CP46<=BR$7,BQ$7,IF(CP46<=BR$12,BQ$12,IF(CP46<=BR$13,BQ$13,IF(CP46<=BR$14,BQ$14,0.05))))))) | DA46: =CZ46*CP46 | DC46: =IF(CS46<=BU$4,BT$4,IF(CS46<=BU$5,BT$5,IF(CS46<=BU$6,BT$6,IF(CS46<=BU$7,BT$7,IF(CS46<=BU$12,BT$12,IF(CS46<=BU$13,BT$13,IF(CS46<=BU$14,BT$14,0.05))))))) | DD46: =DC46*SUM(DA46,CX46,CS46) | DF46: =IF(CV46<=BX$4,BW$4,IF(CV46<=BX$5,BW$5,IF(CV46<=BX$6,BW$6,IF(CV46<=BX$7,BW$7,IF(CV46<=BX$12,BW$12,IF(CV46<=BX$13,BW$13,IF(CV46<=BX$14,BW$14,0.05))))))) | DG46: =DF46*CV46 | DI46: =0.07*SUM(CS46,CX46,DA46,DD46,DG46) | DK46: =SUM(DI46,DG46,DD46,DA46,CX46,CS46) | DL46: =SUM(DG46,DD46,DA46,CX46) | DM46: =DL46/DK46
A47: 3 | B47: 5 | C47: 33 | D47: =(A47*B47*C47)*IF($E$45="8 hour days",8,10) | E47: System 1 | F47: =I47/(D47/C47) | G47: Floor Type | I47: =E20 | J47: =E34 | K47: =J47/I47 | L47: 3 | M47: 3 | N47: 500 - 1500 sf | O47: Guys | P47: 3 | Q47: =P47 | R47: =P47 | S47: =P47 | T47: =P47 | U47: =P47 | V47: =P47 | W47: =P47 | AB47: Guys | AC47: 3 | AD47: =AC47 | AE47: =AC47 | AF47: =AC47 | AH47: =AC47 | AJ47: =AC47 | AW47: 36000 | AZ47: =AW47 | BC47: =AW47+AZ47 | BF47: =BC47 | BG47: =IF(AW47<=#REF!,#REF!,IF(AW47<=#REF!,#REF!,IF(AW47<=#REF!,#REF!,IF(AW47<=#REF!,#REF!,IF(AW47<=#REF!,#REF!,IF(AW47<=#REF!,#REF!,IF(AW47<=#REF!,#REF!,0.05))))))) | BH47: =BG47*AW47 | BJ47: =IF(AZ47<=#REF!,#REF!,IF(AZ47<=#REF!,#REF!,IF(AZ47<=#REF!,#REF!,IF(AZ47<=#REF!,#REF!,IF(AZ47<=#REF!,#REF!,IF(AZ47<=#REF!,#REF!,IF(AZ47<=#REF!,#REF!,0.05))))))) | BK47: =BJ47*AZ47 | BM47: =IF(BC47<=#REF!,#REF!,IF(BC47<=#REF!,#REF!,IF(BC47<=#REF!,#REF!,IF(BC47<=#REF!,#REF!,IF(BC47<=#REF!,#REF!,IF(BC47<=#REF!,#REF!,IF(BC47<=#REF!,#REF!,0.05))))))) | BN47: =BM47*SUM(BK47,BH47,BC47) | BP47: =IF(BF47<=#REF!,#REF!,IF(BF47<=#REF!,#REF!,IF(BF47<=#REF!,#REF!,IF(BF47<=#REF!,#REF!,IF(BF47<=#REF!,#REF!,IF(BF47<=#REF!,#REF!,IF(BF47<=#REF!,#REF!,0.05))))))) | BQ47: =BP47*BF47 | BS47: =0.07*SUM(BC47,BH47,BK47,BN47,BQ47) | BU47: =SUM(BS47,BQ47,BN47,BK47,BH47,BC47) | BV47: =SUM(BQ47,BN47,BK47,BH47) | BW47: =BV47/BU47 | CM47: 36000 | CP47: =CM47 | CS47: =CM47+CP47 | CV47: =CS47 | CW47: =IF(CM47<=BO$4,BN$4,IF(CM47<=BO$5,BN$5,IF(CM47<=BO$6,BN$6,IF(CM47<=BO$7,BN$7,IF(CM47<=BO$12,BN$12,IF(CM47<=BO$13,BN$13,IF(CM47<=BO$14,BN$14,0.05))))))) | CX47: =CW47*CM47 | CZ47: =IF(CP47<=BR$4,BQ$4,IF(CP47<=BR$5,BQ$5,IF(CP47<=BR$6,BQ$6,IF(CP47<=BR$7,BQ$7,IF(CP47<=BR$12,BQ$12,IF(CP47<=BR$13,BQ$13,IF(CP47<=BR$14,BQ$14,0.05))))))) | DA47: =CZ47*CP47 | DC47: =IF(CS47<=BU$4,BT$4,IF(CS47<=BU$5,BT$5,IF(CS47<=BU$6,BT$6,IF(CS47<=BU$7,BT$7,IF(CS47<=BU$12,BT$12,IF(CS47<=BU$13,BT$13,IF(CS47<=BU$14,BT$14,0.05))))))) | DD47: =DC47*SUM(DA47,CX47,CS47) | DF47: =IF(CV47<=BX$4,BW$4,IF(CV47<=BX$5,BW$5,IF(CV47<=BX$6,BW$6,IF(CV47<=BX$7,BW$7,IF(CV47<=BX$12,BW$12,IF(CV47<=BX$13,BW$13,IF(CV47<=BX$14,BW$14,0.05))))))) | DG47: =DF47*CV47 | DI47: =0.07*SUM(CS47,CX47,DA47,DD47,DG47) | DK47: =SUM(DI47,DG47,DD47,DA47,CX47,CS47) | DL47: =SUM(DG47,DD47,DA47,CX47) | DM47: =DL47/DK47
C48: =C47 | D48: =(A48*B48*C48)*IF($E$45="8 hour days",8,10) | E48: System 2 | F48: =I48/(D48/C48) | G48: Floor Type | I48: =E24 | J48: =E37 | K48: =J48/I48 | L48: 3 | M48: 3.5 | N48: 1,500 sf - 2,500 | O48: Days | P48: 1.5 | Q48: 1 | R48: 0.5 | S48: 1 | T48: 0 | U48: 0.5 | V48: 0 | W48: =U48 | AB48: Days | AC48: 1.5 | AD48: 1 | AE48: 0.5 | AF48: 1 | AH48: 0.5 | AJ48: 0.5 | AW48: 37000 | AZ48: =AW48 | BC48: =AW48+AZ48 | BF48: =BC48 | BG48: =IF(AW48<=#REF!,#REF!,IF(AW48<=#REF!,#REF!,IF(AW48<=#REF!,#REF!,IF(AW48<=#REF!,#REF!,IF(AW48<=#REF!,#REF!,IF(AW48<=#REF!,#REF!,IF(AW48<=#REF!,#REF!,0.05))))))) | BH48: =BG48*AW48 | BJ48: =IF(AZ48<=#REF!,#REF!,IF(AZ48<=#REF!,#REF!,IF(AZ48<=#REF!,#REF!,IF(AZ48<=#REF!,#REF!,IF(AZ48<=#REF!,#REF!,IF(AZ48<=#REF!,#REF!,IF(AZ48<=#REF!,#REF!,0.05))))))) | BK48: =BJ48*AZ48 | BM48: =IF(BC48<=#REF!,#REF!,IF(BC48<=#REF!,#REF!,IF(BC48<=#REF!,#REF!,IF(BC48<=#REF!,#REF!,IF(BC48<=#REF!,#REF!,IF(BC48<=#REF!,#REF!,IF(BC48<=#REF!,#REF!,0.05))))))) | BN48: =BM48*SUM(BK48,BH48,BC48) | BP48: =IF(BF48<=#REF!,#REF!,IF(BF48<=#REF!,#REF!,IF(BF48<=#REF!,#REF!,IF(BF48<=#REF!,#REF!,IF(BF48<=#REF!,#REF!,IF(BF48<=#REF!,#REF!,IF(BF48<=#REF!,#REF!,0.05))))))) | BQ48: =BP48*BF48 | BS48: =0.07*SUM(BC48,BH48,BK48,BN48,BQ48) | BU48: =SUM(BS48,BQ48,BN48,BK48,BH48,BC48) | BV48: =SUM(BQ48,BN48,BK48,BH48) | BW48: =BV48/BU48 | CM48: 37000 | CP48: =CM48 | CS48: =CM48+CP48 | CV48: =CS48 | CW48: =IF(CM48<=BO$4,BN$4,IF(CM48<=BO$5,BN$5,IF(CM48<=BO$6,BN$6,IF(CM48<=BO$7,BN$7,IF(CM48<=BO$12,BN$12,IF(CM48<=BO$13,BN$13,IF(CM48<=BO$14,BN$14,0.05))))))) | CX48: =CW48*CM48 | CZ48: =IF(CP48<=BR$4,BQ$4,IF(CP48<=BR$5,BQ$5,IF(CP48<=BR$6,BQ$6,IF(CP48<=BR$7,BQ$7,IF(CP48<=BR$12,BQ$12,IF(CP48<=BR$13,BQ$13,IF(CP48<=BR$14,BQ$14,0.05))))))) | DA48: =CZ48*CP48 | DC48: =IF(CS48<=BU$4,BT$4,IF(CS48<=BU$5,BT$5,IF(CS48<=BU$6,BT$6,IF(CS48<=BU$7,BT$7,IF(CS48<=BU$12,BT$12,IF(CS48<=BU$13,BT$13,IF(CS48<=BU$14,BT$14,0.05))))))) | DD48: =DC48*SUM(DA48,CX48,CS48) | DF48: =IF(CV48<=BX$4,BW$4,IF(CV48<=BX$5,BW$5,IF(CV48<=BX$6,BW$6,IF(CV48<=BX$7,BW$7,IF(CV48<=BX$12,BW$12,IF(CV48<=BX$13,BW$13,IF(CV48<=BX$14,BW$14,0.05))))))) | DG48: =DF48*CV48 | DI48: =0.07*SUM(CS48,CX48,DA48,DD48,DG48) | DK48: =SUM(DI48,DG48,DD48,DA48,CX48,CS48) | DL48: =SUM(DG48,DD48,DA48,CX48) | DM48: =DL48/DK48
C49: =C47 | D49: =(A49*B49*C49)*IF($E$45="8 hour days",8,10) | F49: =I49/(D49/C49) | G49: Floor Type | I49: =H26 | J49: =H36 | K49: =J49/I49 | L49: 4 | M49: 4.5 | N49: 2,500 to 3,000 | P49: =P47*P48 | Q49: =Q47*Q48 | R49: =R47*R48 | S49: =S47*S48 | T49: =T47*T48 | U49: =U47*U48 | V49: =V47*V48 | W49: =W47*W48 | AC49: =AC47*AC48 | AD49: =AD47*AD48 | AE49: =AE47*AE48 | AF49: =AF47*AF48 | AG49: =AG47*AG48 | AH49: =AH47*AH48 | AI49: =AI47*AI48 | AJ49: =AJ47*AJ48
C50: =C47 | D50: =(A50*B50*C50)*IF($E$45="8 hour days",8,10) | F50: =I50/(D50/C50) | G50: Floor Type | I50: =H26 | J50: =H36 | K50: =J50/I50 | L50: 4.5 | M50: 5 | N50: 3,000 + | P50: =SUM(P49:W49) | Q50: factor | AC50: =SUM(AC49:AJ49) | AD50: factor | AW50: 37000 | AZ50: =AW50 | BC50: =AW50+AZ50 | BF50: =BC50 | BG50: =IF(AW50<=#REF!,#REF!,IF(AW50<=#REF!,#REF!,IF(AW50<=#REF!,#REF!,IF(AW50<=#REF!,#REF!,IF(AW50<=#REF!,#REF!,IF(AW50<=#REF!,#REF!,IF(AW50<=#REF!,#REF!,0.05))))))) | BH50: =BG50*AW50 | BJ50: =IF(AZ50<=#REF!,#REF!,IF(AZ50<=#REF!,#REF!,IF(AZ50<=#REF!,#REF!,IF(AZ50<=#REF!,#REF!,IF(AZ50<=#REF!,#REF!,IF(AZ50<=#REF!,#REF!,IF(AZ50<=#REF!,#REF!,0.05))))))) | BK50: =BJ50*AZ50 | BM50: =IF(BC50<=#REF!,#REF!,IF(BC50<=#REF!,#REF!,IF(BC50<=#REF!,#REF!,IF(BC50<=#REF!,#REF!,IF(BC50<=#REF!,#REF!,IF(BC50<=#REF!,#REF!,IF(BC50<=#REF!,#REF!,0.05))))))) | BN50: =BM50*SUM(BK50,BH50,BC50) | BP50: =IF(BF50<=#REF!,#REF!,IF(BF50<=#REF!,#REF!,IF(BF50<=#REF!,#REF!,IF(BF50<=#REF!,#REF!,IF(BF50<=#REF!,#REF!,IF(BF50<=#REF!,#REF!,IF(BF50<=#REF!,#REF!,0.05))))))) | BQ50: =BP50*BF50 | BS50: =0.07*SUM(BC50,BH50,BK50,BN50,BQ50) | BU50: =SUM(BS50,BQ50,BN50,BK50,BH50,BC50) | BV50: =SUM(BQ50,BN50,BK50,BH50) | BW50: =BV50/BU50 | CM50: 37000 | CP50: =CM50 | CS50: =CM50+CP50 | CV50: =CS50 | CW50: =IF(CM50<=BO$4,BN$4,IF(CM50<=BO$5,BN$5,IF(CM50<=BO$6,BN$6,IF(CM50<=BO$7,BN$7,IF(CM50<=BO$12,BN$12,IF(CM50<=BO$13,BN$13,IF(CM50<=BO$14,BN$14,0.05))))))) | CX50: =CW50*CM50 | CZ50: =IF(CP50<=BR$4,BQ$4,IF(CP50<=BR$5,BQ$5,IF(CP50<=BR$6,BQ$6,IF(CP50<=BR$7,BQ$7,IF(CP50<=BR$12,BQ$12,IF(CP50<=BR$13,BQ$13,IF(CP50<=BR$14,BQ$14,0.05))))))) | DA50: =CZ50*CP50 | DC50: =IF(CS50<=BU$4,BT$4,IF(CS50<=BU$5,BT$5,IF(CS50<=BU$6,BT$6,IF(CS50<=BU$7,BT$7,IF(CS50<=BU$12,BT$12,IF(CS50<=BU$13,BT$13,IF(CS50<=BU$14,BT$14,0.05))))))) | DD50: =DC50*SUM(DA50,CX50,CS50) | DF50: =IF(CV50<=BX$4,BW$4,IF(CV50<=BX$5,BW$5,IF(CV50<=BX$6,BW$6,IF(CV50<=BX$7,BW$7,IF(CV50<=BX$12,BW$12,IF(CV50<=BX$13,BW$13,IF(CV50<=BX$14,BW$14,0.05))))))) | DG50: =DF50*CV50 | DI50: =0.07*SUM(CS50,CX50,DA50,DD50,DG50) | DK50: =SUM(DI50,DG50,DD50,DA50,CX50,CS50) | DL50: =SUM(DG50,DD50,DA50,CX50) | DM50: =DL50/DK50
A51: Travel: Guys | B51: Hours | C51: Rate | H51: Sum of Above SF: | I51: =SUM(I47:I50) | J51: =SUM(J47:J50) | K51: =J51/I51 | O51: =O53/M41 | P51: 1/3 of sf | AW51: 38000 | AZ51: =AW51 | BC51: =AW51+AZ51 | BF51: =BC51 | BG51: =IF(AW51<=#REF!,#REF!,IF(AW51<=#REF!,#REF!,IF(AW51<=#REF!,#REF!,IF(AW51<=#REF!,#REF!,IF(AW51<=#REF!,#REF!,IF(AW51<=#REF!,#REF!,IF(AW51<=#REF!,#REF!,0.05))))))) | BH51: =BG51*AW51 | BJ51: =IF(AZ51<=#REF!,#REF!,IF(AZ51<=#REF!,#REF!,IF(AZ51<=#REF!,#REF!,IF(AZ51<=#REF!,#REF!,IF(AZ51<=#REF!,#REF!,IF(AZ51<=#REF!,#REF!,IF(AZ51<=#REF!,#REF!,0.05))))))) | BK51: =BJ51*AZ51 | BM51: =IF(BC51<=#REF!,#REF!,IF(BC51<=#REF!,#REF!,IF(BC51<=#REF!,#REF!,IF(BC51<=#REF!,#REF!,IF(BC51<=#REF!,#REF!,IF(BC51<=#REF!,#REF!,IF(BC51<=#REF!,#REF!,0.05))))))) | BN51: =BM51*SUM(BK51,BH51,BC51) | BP51: =IF(BF51<=#REF!,#REF!,IF(BF51<=#REF!,#REF!,IF(BF51<=#REF!,#REF!,IF(BF51<=#REF!,#REF!,IF(BF51<=#REF!,#REF!,IF(BF51<=#REF!,#REF!,IF(BF51<=#REF!,#REF!,0.05))))))) | BQ51: =BP51*BF51 | BS51: =0.07*SUM(BC51,BH51,BK51,BN51,BQ51) | BU51: =SUM(BS51,BQ51,BN51,BK51,BH51,BC51) | BV51: =SUM(BQ51,BN51,BK51,BH51) | BW51: =BV51/BU51 | CM51: 38000 | CP51: =CM51 | CS51: =CM51+CP51 | CV51: =CS51 | CW51: =IF(CM51<=BO$4,BN$4,IF(CM51<=BO$5,BN$5,IF(CM51<=BO$6,BN$6,IF(CM51<=BO$7,BN$7,IF(CM51<=BO$12,BN$12,IF(CM51<=BO$13,BN$13,IF(CM51<=BO$14,BN$14,0.05))))))) | CX51: =CW51*CM51 | CZ51: =IF(CP51<=BR$4,BQ$4,IF(CP51<=BR$5,BQ$5,IF(CP51<=BR$6,BQ$6,IF(CP51<=BR$7,BQ$7,IF(CP51<=BR$12,BQ$12,IF(CP51<=BR$13,BQ$13,IF(CP51<=BR$14,BQ$14,0.05))))))) | DA51: =CZ51*CP51 | DC51: =IF(CS51<=BU$4,BT$4,IF(CS51<=BU$5,BT$5,IF(CS51<=BU$6,BT$6,IF(CS51<=BU$7,BT$7,IF(CS51<=BU$12,BT$12,IF(CS51<=BU$13,BT$13,IF(CS51<=BU$14,BT$14,0.05))))))) | DD51: =DC51*SUM(DA51,CX51,CS51) | DF51: =IF(CV51<=BX$4,BW$4,IF(CV51<=BX$5,BW$5,IF(CV51<=BX$6,BW$6,IF(CV51<=BX$7,BW$7,IF(CV51<=BX$12,BW$12,IF(CV51<=BX$13,BW$13,IF(CV51<=BX$14,BW$14,0.05))))))) | DG51: =DF51*CV51 | DI51: =0.07*SUM(CS51,CX51,DA51,DD51,DG51) | DK51: =SUM(DI51,DG51,DD51,DA51,CX51,CS51) | DL51: =SUM(DG51,DD51,DA51,CX51) | DM51: =DL51/DK51
A52: =(A47*B47)+(A48*B48)+(A49*B49)+(A50*B50) | B52: 0 | C52: 33 | D52: =(A52*B52*C52) | E52: Drive Time: ? | I52: =(((D53-D52)/C47)/A47)/40 | J52: # of 40 hour weeks | M52: Holidays - Double Time | O52: =O53/M42 | P52: 1/2 of sf | AB52: (micro) Double Flake -or- Qrtz/ShpFlr | AW52: 39000 | AZ52: =AW52 | BC52: =AW52+AZ52 | BF52: =BC52 | BG52: =IF(AW52<=#REF!,#REF!,IF(AW52<=#REF!,#REF!,IF(AW52<=#REF!,#REF!,IF(AW52<=#REF!,#REF!,IF(AW52<=#REF!,#REF!,IF(AW52<=#REF!,#REF!,IF(AW52<=#REF!,#REF!,0.05))))))) | BH52: =BG52*AW52 | BJ52: =IF(AZ52<=#REF!,#REF!,IF(AZ52<=#REF!,#REF!,IF(AZ52<=#REF!,#REF!,IF(AZ52<=#REF!,#REF!,IF(AZ52<=#REF!,#REF!,IF(AZ52<=#REF!,#REF!,IF(AZ52<=#REF!,#REF!,0.05))))))) | BK52: =BJ52*AZ52 | BM52: =IF(BC52<=#REF!,#REF!,IF(BC52<=#REF!,#REF!,IF(BC52<=#REF!,#REF!,IF(BC52<=#REF!,#REF!,IF(BC52<=#REF!,#REF!,IF(BC52<=#REF!,#REF!,IF(BC52<=#REF!,#REF!,0.05))))))) | BN52: =BM52*SUM(BK52,BH52,BC52) | BP52: =IF(BF52<=#REF!,#REF!,IF(BF52<=#REF!,#REF!,IF(BF52<=#REF!,#REF!,IF(BF52<=#REF!,#REF!,IF(BF52<=#REF!,#REF!,IF(BF52<=#REF!,#REF!,IF(BF52<=#REF!,#REF!,0.05))))))) | BQ52: =BP52*BF52 | BS52: =0.07*SUM(BC52,BH52,BK52,BN52,BQ52) | BU52: =SUM(BS52,BQ52,BN52,BK52,BH52,BC52) | BV52: =SUM(BQ52,BN52,BK52,BH52) | BW52: =BV52/BU52 | CM52: 39000 | CP52: =CM52 | CS52: =CM52+CP52 | CV52: =CS52 | CW52: =IF(CM52<=BO$4,BN$4,IF(CM52<=BO$5,BN$5,IF(CM52<=BO$6,BN$6,IF(CM52<=BO$7,BN$7,IF(CM52<=BO$12,BN$12,IF(CM52<=BO$13,BN$13,IF(CM52<=BO$14,BN$14,0.05))))))) | CX52: =CW52*CM52 | CZ52: =IF(CP52<=BR$4,BQ$4,IF(CP52<=BR$5,BQ$5,IF(CP52<=BR$6,BQ$6,IF(CP52<=BR$7,BQ$7,IF(CP52<=BR$12,BQ$12,IF(CP52<=BR$13,BQ$13,IF(CP52<=BR$14,BQ$14,0.05))))))) | DA52: =CZ52*CP52 | DC52: =IF(CS52<=BU$4,BT$4,IF(CS52<=BU$5,BT$5,IF(CS52<=BU$6,BT$6,IF(CS52<=BU$7,BT$7,IF(CS52<=BU$12,BT$12,IF(CS52<=BU$13,BT$13,IF(CS52<=BU$14,BT$14,0.05))))))) | DD52: =DC52*SUM(DA52,CX52,CS52) | DF52: =IF(CV52<=BX$4,BW$4,IF(CV52<=BX$5,BW$5,IF(CV52<=BX$6,BW$6,IF(CV52<=BX$7,BW$7,IF(CV52<=BX$12,BW$12,IF(CV52<=BX$13,BW$13,IF(CV52<=BX$14,BW$14,0.05))))))) | DG52: =DF52*CV52 | DI52: =0.07*SUM(CS52,CX52,DA52,DD52,DG52) | DK52: =SUM(DI52,DG52,DD52,DA52,CX52,CS52) | DL52: =SUM(DG52,DD52,DA52,CX52) | DM52: =DL52/DK52
A53: Install Labor | D53: =ROUNDUP(SUM(D47:D52),0) | E53: =D53/B45 | F53: Labor $/SF | I53: =ROUNDUP(I52,0) | J53: # of weeks rounded up | M53: New Year's Day | O53: =I48 | P53: SF for System | Q53: =J48 | R53: LF Cove | S53: =Q53/O53 | T53: cove ratio | AB53: =B45 | AC53: SF for System | AD53: =D45 | AE53: LF Cove | AF53: =AD53/AB53 | AG53: cove ratio
A54: Labor Escalation | B54: (rate esc. only) | C54: =IF(D5="Yes",5%,0) | D54: =ROUNDUP((D53*C54),0) | E54: +5%IFPWorLong Lead Job (12+ months) | M54: Memorial Day | O54: (Avg.) Guys | P54: (Avg.) Days | Q54: Labor Value | R54: Wage Rate | AB54: (Avg.) Guys | AC54: (Avg.) Days | AD54: Labor Value | AE54: Wage Rate
A55: Labor Burden | C55: 0.12 | D55: =ROUNDUP((D53+D54)*C55,0) | I55: ** Cement Mason ** | K55: ** Painter ** | M55: July 4th | O55: 3 | P55: =P60/O55 | Q55: =O55*P55*R55*8 | R55: =C48 | AB55: 3 | AC55: =AC60/AB55 | AD55: =AB55*AC55*AE55*8 | AE55: =C47
I56: Prevailing Wage Rate: | J56: =SUM(J57:J58) | K56: Prevailing Wage Rate: | L56: =SUM(L57:L58) | M56: Labor Day | O56: UNIT | P56: Prep / Patch | Q56: Cove | R56: Prime | S56: Broadcast | T56: (? double BC ?) | U56: Grout | V56: (? double Grout ?) | W56: Topcoat | AB56: UNIT | AC56: Prep / Patch | AD56: Cove | AE56: Prime | AF56: Broadcast | AG56: (? double BC ?) | AH56: Grout | AI56: (? double Grout ?) | AJ56: Topcoat
A57: TOOLING & CONSUMABLES | B57: Quantity | C57: Cost | D57: Totals | I57: rate = | J57: 0 | K57: rate = | L57: 0 | M57: Thanksgiving | O57: Guys | P57: 3 | Q57: =P57 | R57: =P57 | S57: =P57 | T57: =P57 | U57: =P57 | V57: =P57 | W57: =P57 | AB57: Guys | AC57: 3 | AD57: =AC57 | AE57: =AC57 | AF57: =AC57 | AG57: =AC57 | AH57: =AC57 | AJ57: =AC57
A58: Moisture Test | B58: =ROUNDUP(IF(B45>2000,B45/1000,2),0) | C58: 35 | D58: =ROUNDUP(B58*C58,0) | I58: + fringes = | J58: 0 | K58: + fringes = | L58: 0 | M58: Christmas | O58: Days | P58: 1.5 | Q58: 1 | R58: 0.5 | S58: 1 | T58: 0 | U58: 0.5 | V58: 0 | W58: =U58 | AB58: Days | AC58: 1.5 | AD58: 1 | AE58: 0.5 | AF58: 1 | AG58: 1 | AH58: 0.5 | AJ58: 0.5
A59: Tooling & Consumables | B59: =B45 | C59: 0.33 | D59: =ROUNDUP(IF((B59*C59)>150,(B59*C59),150),0) | I59: Foreman *min. $32 Cement Mason | K59: Foreman *min. $32 Painter | P59: =P57*P58 | Q59: =Q57*Q58 | R59: =R57*R58 | S59: =S57*S58 | T59: =T57*T58 | U59: =U57*U58 | V59: =V57*V58 | W59: =W57*W58 | AC59: =AC57*AC58 | AD59: =AD57*AD58 | AE59: =AE57*AE58 | AF59: =AF57*AF58 | AG59: =AG57*AG58 | AH59: =AH57*AH58 | AI59: =AI57*AI58 | AJ59: =AJ57*AJ58
A60: Demo Tooling (/sf) | C60: 0.33 | D60: =ROUNDUP(B60*C60,0) | E60: ($0.17 glue/VCT/carpet or $0.33 demo tile) | I60: (Entry *min. $23 Cement Mason) | K60: (Entry *min. $23 Painter) | P60: =SUM(P59:W59) | Q60: factor | AC60: =SUM(AC59:AJ59) | AD60: factor
A61: Plastic | D61: =ROUNDUP(B61*C61,0) | I61: 1:1 "Entry" Half Wage | J61: =IF((J56/2)<23,23,(J56/2)) | K61: 1:1 "Entry" Half Wage | L61: =IF((L56/2)<23,23,(L56/2)) | AB61: SLB / MDB
A62: Tooling and Consumables Total | D62: =SUM(D58:D61) | J62: "Entry" Laborer for MO "State" Wage ONLY | L62: NOT davis-bacon | O62: =I49 | P62: SF for System | Q62: =J49 | R62: LF Cove | S62: =Q62/O62 | T62: cove ratio | AB62: =B45 | AC62: SF for System | AD62: =D45 | AE62: LF Cove | AF62: =AD62/AB62 | AG62: cove ratio
H63: =E45 | O63: (Avg.) Guys | P63: (Avg.) Days | Q63: Labor Value | R63: Wage Rate | AB63: (Avg.) Guys | AC63: (Avg.) Days | AD63: Labor Value | AE63: Wage Rate
A64: TRAVEL | B64: Quantity | C64: Cost | D64: Totals | G64: Total Man Hours | H64: =(((A47*B47)+(A48*B48)+(A49*B49)+(A50*B50))*IF($E$45="8 hour days",8,10))+(A52*B52) | O64: 3 | P64: =P69/O64 | Q64: =O64*P64*R64*8 | R64: =C49 | AB64: 3 | AC64: =AC69/AB64 | AD64: =AB64*AC64*AE64*8 | AE64: =C47
A65: Travel - Lodging | B65: =IF(B4="No",((D53-D52)/C47)/8) | C65: 70 | D65: =ROUNDUP(B65*C65,0) | G65: Total Days | H65: =H64/IF($E$45="8 hour days",8,10)/H66 | O65: UNIT | P65: Prep / Patch | Q65: Cove | R65: Prime | S65: Broadcast | T65: (? double BC ?) | U65: Grout | V65: (? double Grout ?) | W65: Topcoat | AB65: UNIT | AC65: Prep / Patch | AD65: Cove | AE65: Prime | AF65: SL/MD +Broadcast | AG65: (? double BC ?) | AH65: Grout | AI65: (? double Grout ?) | AJ65: Topcoat
A66: Travel - Food | B66: =B65 | C66: 45 | D66: =ROUNDUP(B66*C66,0) | G66: ^based on X crew size: | H66: =A47 | O66: Guys | P66: 3 | Q66: =P66 | R66: =P66 | S66: =P66 | T66: =P66 | U66: =P66 | V66: =P66 | W66: =P66 | AB66: Guys | AC66: 3 | AD66: =AC66 | AF66: =AC66 | AJ66: =AC66
O67: Days | P67: 1.5 | Q67: 1 | R67: 0.5 | S67: 1 | T67: 0 | U67: 0.5 | V67: 0 | W67: =U67 | AB67: Days | AC67: 1.5 | AD67: 1 | AF67: 1 | AJ67: 0.5
A68: Travel Costs Total | D68: =SUM(D65:D67) | P68: =P66*P67 | Q68: =Q66*Q67 | R68: =R66*R67 | S68: =S66*S67 | T68: =T66*T67 | U68: =U66*U67 | V68: =V66*V67 | W68: =W66*W67 | AC68: =AC66*AC67 | AD68: =AD66*AD67 | AE68: =AE66*AE67 | AF68: =AF66*AF67 | AG68: =AG66*AG67 | AH68: =AH66*AH67 | AI68: =AI66*AI67 | AJ68: =AJ66*AJ67
P69: =SUM(P68:W68) | Q69: factor | AC69: =SUM(AC68:AJ68) | AD69: factor
A70: SUB-TOTAL COSTS | D70: =ROUNDUP(SUM(D43,D53:D55,D62,D68),0) | E70: =D70/B45 | F70: Sub-Total $/SF | AB70: Hybrid Double BC
O71: =I50 | P71: SF for System | Q71: =J50 | R71: LF Cove | S71: =Q71/O71 | T71: cove ratio | AB71: =B45 | AC71: SF for System | AD71: =D45 | AE71: LF Cove | AF71: =AD71/AB71 | AG71: cove ratio
A72: MARKUP | B72: % | D72: Totals | F72: =SUM(D70,D82,D85) | G72: Total "Estimated Costs" w/taxes + fees + bond | I72: =F72/C87 | O72: (Avg.) Guys | P72: (Avg.) Days | Q72: Labor Value | R72: Wage Rate | AB72: (Avg.) Guys | AC72: (Avg.) Days | AD72: Labor Value | AE72: Wage Rate
A73: GP (before lines below) | B73: =IF(D70<6500,0.52,IF(D70<15000,0.45,IF(D70<22500,0.35,IF(D70<32500,0.32,0.3)))) | D73: =ROUNDUP(SUM(D70,D80,D83)/(1-B73),0)-ROUNDUP(SUM(D70,D80),0) | F73: =(((A47*B47)+(A48*B48)+(A49*B49)+(A50*B50))*IF($E$45="8 hour days",8,10))+(A52*B52) | G73: Man Hour Budget (Raken) | O73: 3 | P73: =P78/O73 | Q73: =O73*P73*R73*8 | R73: =C50 | AB73: 3 | AC73: =AC78/AB73 | AD73: =AB73*AC73*AE73*8 | AE73: =C47
A74: Hard Bid Discount | B74: =IF(B5="yes",IF(D70>=60000,-0.04,IF(B4="yes",IF(D70>=13000,-0.025,0)))) | D74: =ROUNDUP(SUM(D70,D73)*B74,0) | F74: =F87/H65 | G74: GP per Day | H74: =E45 | O74: UNIT | P74: Prep / Patch | Q74: Cove | R74: Prime | S74: Broadcast | T74: (? double BC ?) | U74: Grout | V74: (? double Grout ?) | W74: Topcoat | AB74: UNIT | AC74: Prep / Patch | AD74: Cove | AE74: Prime | AF74: SL + Broadcast | AG74: (? double BC ?) | AH74: Grout | AI74: (? double Grout ?) | AJ74: Topcoat
A75: Superintendent & PTO | B75: 0.03 | D75: =ROUNDUP(SUM(D70:D74,D77,D80,D83)*B75,0) | O75: Guys | P75: 3 | Q75: =P75 | R75: =P75 | S75: =P75 | T75: =P75 | U75: =P75 | V75: =P75 | W75: =P75 | AB75: Guys | AC75: 3 | AD75: =AC75 | AF75: =AC75 | AG75: =AC75 | AH75: =AC75 | AI75: =AC75 | AJ75: =AC75
A76: Soft Costs | B76: 0.13 | D76: =(ROUNDUP(SUM(D70:D75,D77,D80,D83)*B76,0))+0 | O76: Days | P76: 1.5 | Q76: 1 | R76: 0.5 | S76: 1 | T76: 0 | U76: 0.5 | V76: 0 | W76: =U76 | AB76: Days | AC76: 1.5 | AD76: 1 | AF76: 1 | AG76: 1 | AH76: 0.5 | AI76: 0.5 | AJ76: 0.5
A77: Contingency | B77: -- ?? --> | D77: 0 | P77: =P75*P76 | Q77: =Q75*Q76 | R77: =R75*R76 | S77: =S75*S76 | T77: =T75*T76 | U77: =U75*U76 | V77: =V75*V76 | W77: =W75*W76 | AC77: =AC75*AC76 | AD77: =AD75*AD76 | AE77: =AE75*AE76 | AF77: =AF75*AF76 | AG77: =AG75*AG76 | AH77: =AH75*AH76 | AI77: =AI75*AI76 | AJ77: =AJ75*AJ76
P78: =SUM(P77:W77) | Q78: factor | AC78: =SUM(AC77:AJ77) | AD78: factor
A79: TAXES & FEES | B79: % | D79: Totals | J79: =(J82-J80-J81) | AB79: Gard
A80: Sales Tax | B80: =IF($B$6="no",0,0.09475) | D80: =ROUNDUP(SUM(D43)*B80,0) | K80: sales tax (enter rounded) | AB80: =B45 | AC80: SF for System | AD80: =D45 | AE80: LF Cove | AF80: =AD80/AB80 | AG80: cove ratio
A81: =Polish!A75 | B81: =IF(D6="yes",0.1,0) | D81: =ROUNDUP(SUM(D53:D55,D62,D68,D73:D77,D83)*B81,0) | E81: =IF(D6="yes","*10% is placeholder. Adjust to actual if project awarded"," ") | K81: ks remodel (enter rounded) | AB81: (Avg.) Guys | AC81: (Avg.) Days | AD81: Labor Value | AE81: Wage Rate
A82: Total Taxes | D82: =SUM(D80:D81) | J82: =D88 | K82: total | AB82: 3 | AC82: =AC87/AB82 | AD82: =AB82*AC82*AE82*8 | AE82: =C47
A83: Fees + Textura + ? | D83: =ROUNDUP(B83*C83,0) | AB83: UNIT | AC83: Prep / Patch | AD83: Cove | AE83: Prime | AF83: Body/Gard | AG83: (? double BC ?) | AH83: Grout | AI83: (? double Grout ?) | AJ83: Topcoat
A84: Bond | B84: 0 | D84: =ROUNDUP(SUM(D70,D73,D74,D75:D77,D80,D81:D83)*B84,0) | AB84: Guys | AC84: 3 | AD84: =AC84 | AE84: =AC84 | AF84: =AC84 | AJ84: =AC84
A85: Total Fees + Bond | D85: =ROUNDUP(SUM(D83:D84),0) | K85: For PM's Reference | AB85: Days | AC85: 1.5 | AD85: 1 | AE85: 0.5 | AF85: 1 | AJ85: 0.5
B86: Linear Footage: | C86: =D45 | F86: Mark Up + Conting. | G86: GP / MH | H86: MarkUp + Soft Costs | J86: Material + Tooling % | K86: Labor % | L86: Travel % | AC86: =AC84*AC85 | AD86: =AD84*AD85 | AE86: =AE84*AE85 | AF86: =AF84*AF85 | AG86: =AG84*AG85 | AH86: =AH84*AH85 | AI86: =AI84*AI85 | AJ86: =AJ84*AJ85
B87: Square Footage: | C87: =B45 | E87: Less Sales Tax | F87: =SUM(D73,D74,D77) | G87: =F87/F73 | H87: =SUM(D73:D77) | J87: =(H43+D62)/D88 | K87: =(SUM(D53:D55)/D88) | L87: =D68/D88 | AC87: =SUM(AC86:AJ86) | AD87: factor
A88: TOTAL | C88: =D88/C87 | D88: =SUM(D70,D73:D77,D82,D85) | E88: =D88-(D80+D81) | F88: =F87/(D88) | G88: =C47 | H88: =H87/D88 | I88: 42% = Epoxy Goal
C89: =D89/C87 | D89: =D88-D81 | E89: (less ks remodel tax) | G89: LaborRate from Above | I89: (epx: 42% & pol: 45%) | J89: =SUM(D43,D62) | K89: =J89/J92 | L89: Material+Tooling | M89: % Breakdown
J90: =SUM(D53:D55,D68) | K90: =J90/J92 | L90: Labor + Travel
B91: Add for additional phase | C91: 4500 | J91: =SUM(D73:D77,D82,D85) | K91: =J91/J92 | L91: Mark-Up + Taxes
J92: =SUM(J89:J91) | K92: =SUM(K89:K91) | L92: Total
A94: System Step & Day Count
B95: SLB & MDB | D95: Trowel Hybrid | F95: Standard Hybrid | H95: Quartz BC | J95: Flake Double | L95: Flake Single | N95: Gard
A96: 1 | B96: Prep | C96: 1 | D96: Prep | E96: 1 | F96: Prep | G96: 1 | H96: Prep | I96: 1 | J96: Prep | K96: 1 | L96: Prep | M96: 1 | N96: Prep
A97: 2 | B97: SL/MD + Broadcast | C97: 2 | D97: SL + Broadcast | E97: 2 | F97: SL + Broadcast | G97: 2 | H97: Prime | I97: 2 | J97: Prime | K97: 2 | L97: Prime | M97: 2 | N97: Prime
A98: 3 | B98: Topcoat | C98: 3 | D98: Broadcast | E98: 3 | F98: Broadcast | G98: 3 | H98: Broadcast | I98: 3 | J98: Broadcast | K98: 3 | L98: Broadcast | M98: 3 | N98: Base Coat
A99: 4 | B99: Cove? | C99: 4 | D99: Grout | E99: 4 | F99: Grout | G99: 4 | H99: Broadcast | I99: 4 | J99: Broadcast | K99: 4 | L99: Grout | M99: 4 | N99: Topcoat
A100: 5 | B100: Extra Patch? | C100: 5 | D100: Extra Grout | E100: 5 | F100: Topcoat | G100: 5 | H100: Grout | I100: 5 | J100: Grout | K100: 5 | L100: Topcoat | M100: 5 | N100: Cove?
C101: 6 | D101: Topcoat | E101: 6 | F101: Cove? | G101: 6 | H101: Topcoat | I101: 6 | J101: Topcoat | K101: 6 | L101: Cove? | M101: 6 | N101: Extra Patch?
C102: 7 | D102: Cove? | E102: 7 | F102: Extra Patch? | G102: 7 | H102: Cove? | I102: 7 | J102: Cove? | K102: 7 | L102: Extra Patch?
...

Sheet Polish
A1: Project | B1: =Epoxy!B1 | G1: Bidding Contacts:
A2: Bid Date | B2: =Epoxy!B2 | G2: =Epoxy!G2 | H2: =Epoxy!H2 | I2: =Epoxy!I2 | J2: =Epoxy!J2 | K2: =Epoxy!K2
A3: Address | B3: =Epoxy!B3 | G3: =Epoxy!G3 | H3: =Epoxy!H3 | I3: =Epoxy!I3 | J3: =Epoxy!J3 | K3: =Epoxy!K3
A4: Local? | B4: Yes | C4: < 70 miles? | G4: =Epoxy!G4 | H4: =Epoxy!H4 | I4: =Epoxy!I4 | J4: =Epoxy!J4 | K4: =Epoxy!K4 | P4: Calculator for Polish Days - DO NOT DELETE
A5: Hard Bid? | B5: No | C5: PrevailingWage? | D5: =Epoxy!D5 | E5: =Epoxy!E5 | G5: =Epoxy!G5 | H5: =Epoxy!H5 | I5: =Epoxy!I5 | J5: =Epoxy!J5 | K5: =Epoxy!K5 | P5: =IF((B35/2500)<1,1,(B35/2500)) | Q5: # 2500 sf multiplier
A6: Taxable? | B6: =Epoxy!B6 | C6: Remodel Tax? | D6: =Epoxy!D6 | E6: =Epoxy!E6 | G6: =Epoxy!G6 | H6: =Epoxy!H6 | I6: =Epoxy!I6 | J6: =Epoxy!J6 | K6: =Epoxy!K6 | Q6: Aggregate? | R6: Polish System | S6: Dye | T6: Grout | U6: Demo Glue | V6: Tooling
A7: Approx Start Date | G7: =Epoxy!G7 | H7: =Epoxy!H7 | I7: =Epoxy!I7 | J7: =Epoxy!J7 | K7: =Epoxy!K7
A8: Architect | B8: =Epoxy!B8 | G8: =Epoxy!G8 | H8: =Epoxy!H8 | I8: =Epoxy!I8 | J8: =Epoxy!J8 | K8: =Epoxy!K8
A9: Drawings Dated | B9: =Epoxy!B9 | G9: =Epoxy!G9 | H9: =Epoxy!H9 | I9: =Epoxy!I9 | J9: =Epoxy!J9 | K9: =Epoxy!K9
A10: New / Reno: | G10: =Epoxy!G10 | H10: =Epoxy!H10 | I10: =Epoxy!I10 | J10: =Epoxy!J10 | K10: =Epoxy!K10 | Q10: =IF(F36="cream",Q14,IF(F36="S&P",Q15,IF(F36="full",Q16,0))) | R10: =IF(G36="traditional",IF(F36="S&P",R19,IF(F36="full",R20)),IF(G36="hybrid",IF(F36="cream",R14,0))) | S10: =IF(H36="yes dye",S14,0) | T10: =IF(I36="yes grout",T14,0) | U10: =IF(J36="yes demo glue",U14,0) | V10: =IF(F36="cream",V13,IF(F36="S&P",V14,IF(F36="full",V15,0.25))) | W10: =IF(G36="traditional",V16,0)
A12: Floor System- Polish:
R13: Hybrid | V13: =IF($E$18<=4000,validation!$E$32,IF($E$18<7000,validation!$E$33,validation!$E$34)) | W13: Pads (Cream) | X13: data on "validation" tab
P14: Cream | Q14: 3.5 | R14: 0 | S14: 0.5 | T14: 0.75 | U14: 1 | V14: =IF($E$18<=4000,validation!$I$32,IF($E$18<7000,validation!$I$33,validation!$I$34)) | W14: S&P | X14: data on "validation" tab
A15: Total Base Bid: | B15: =D82 | C15: $ / SF: | D15: =C82 | P15: S&P | Q15: 4.5 | R15: 0 | V15: =IF($E$18<=4000,validation!$M$32,IF($E$18<7000,validation!$M$33,validation!$M$34)) | W15: Full Aggregate | X15: data on "validation" tab
A16: MATERIAL - Patch | B16: Quantity | C16: Cost | D16: Total | H16: Standard Add's | I16: Cost / Unit | J16: SF -or- LF | K16: Total | P16: Full | Q16: 9 | R16: 0 | V16: 0.2 | W16: Traditoinal Tooling
B17: =E18 | C17: =IF(B10="New",0.05,0.15) | D17: =B17*C17 | H17: Ram Board | I17: =IF(J17<=1000,validation!$R$4,IF(J17<1500,validation!$R$6,IF(J17<2000,validation!$R$8,IF(J17<2500,validation!$R$10,IF(J17<=3000,validation!$R$12,IF(J17<3500,validation!$R$14,IF(J17<4000,validation!$R$16,IF(J17<5000,validation!$R$18,validation!$R$20)))))))) | J17: =B35 | K17: =ROUNDUP((I17*J17),0) | L17: LF | M17: $ / LF | R17: Traditional
D18: =B18*C18 | E18: 0 | F18: SF | H18: Joint Filler | I18: =IF(J18<=1000,validation!$U$4,IF(J18<1500,validation!$U$6,IF(J18<2000,validation!$U$8,IF(J18<2500,validation!$U$10,IF(J18<=3000,validation!$U$12,IF(J18<3500,validation!$U$14,IF(J18<4000,validation!$U$16,IF(J18<5000,validation!$U$18,validation!$U$20)))))))) | J18: =B35 | K18: =ROUNDUP((I18*J18),0) | L18: =0.2*J18 | M18: =K18/L18 | P18: Cream | R18: 0
A19: MATERIAL - Floor | E19: 0 | F19: LF | H19: 4" Rubber Cove (/LF) | I19: =IF(J19<=100,validation!$R$24,IF(J19<150,validation!$R$26,IF(J19<200,validation!$R$28,IF(J19<250,validation!$R$30,IF(J19<=300,validation!$R$32,IF(J19<350,validation!$R$34,IF(J19<400,validation!$R$36,IF(J19<500,validation!$R$38,validation!$R$40)))))))) | J19: =E19 | K19: =ROUNDUP((I19*J19),0) | M19: *Double for removal of existing soft joints | P19: S&P | R19: 2
A20: Densifier | B20: =E18 | C20: 0.07 | D20: =B20*C20 | H20: 6" Rubber Cove (/LF) | I20: =IF(J19<=100,validation!$U$24,IF(J19<150,validation!$U$26,IF(J19<200,validation!$U$28,IF(J19<250,validation!$U$30,IF(J19<=300,validation!$U$32,IF(J19<350,validation!$U$34,IF(J19<400,validation!$U$36,IF(J19<500,validation!$U$38,validation!$U$40)))))))) | J20: =E19 | K20: =ROUNDUP((I20*J20),0) | P20: Full | R20: 2
A21: Sealer | B21: =E18 | C21: 0.1 | D21: =B21*C21 | H21: 4" Line Striping (/LF) | I21: =IF(J21<=100,validation!$R$44,IF(J21<150,validation!$R$46,IF(J21<200,validation!$R$48,IF(J21<250,validation!$R$50,IF(J21<=300,validation!$R$52,IF(J21<350,validation!$R$54,IF(J21<400,validation!$R$56,IF(J21<500,validation!$R$58,validation!$R$60)))))))) | J21: 0 | K21: =ROUNDUP((I21*J21),0) | M21: Polish: | N21: ='Stnd Alts'!E292 | O21: Mock-Up*
A22: Grout Compound? | B22: =IF(I36="Yes Grout",E18) | C22: 0.11 | D22: =B22*C22 | H22: 6" Line Striping (/LF) | I22: =IF(J21<=100,validation!$U$44,IF(J21<150,validation!$U$46,IF(J21<200,validation!$U$48,IF(J21<250,validation!$U$50,IF(J21<=300,validation!$U$52,IF(J21<350,validation!$U$54,IF(J21<400,validation!$U$56,IF(J21<500,validation!$U$58,validation!$U$60)))))))) | J22: 0 | K22: =ROUNDUP((I22*J22),0) | M22: **In Town** | N22: ='Stnd Alts'!E194 | O22: Mob Fee* | P22: *see "Stnd Alts" tab
D23: =B23*C23
A24: MATERIAL - Dye | E24: Dye? 'Yes' or 'No'
A25: Dye | B25: =IF(E25="Yes",E18) | C25: 0.14 | D25: =B25*C25 | E25: No | O25: Takeoff Tab | P25: sf | Q25: lf | R25: extra cell | S25: extra cell | T25: extra cell
A26: Dye | B26: =IF(E25="Yes",E18) | C26: 0.14 | D26: =B26*C26 | H26: Potential Add Options (over & above Low Sheen - Cream Hybrid) | K26: (could be more) | L26: (no joints) | O26: =Takeoff!B14 | P26: =Takeoff!C14 | Q26: =Takeoff!D14 | R26: =Takeoff!E14 | S26: =Takeoff!F14 | T26: =Takeoff!G14
D27: =B27*C27 | H27: =E18 | I27: $/SF | J27: Total Add | K27: Typical Range | L27: Total w/ Opt. | M27: Total $/SF | O27: =Takeoff!I14 | P27: =Takeoff!J14 | Q27: =Takeoff!K14 | R27: =Takeoff!L14 | S27: =Takeoff!M14 | T27: =Takeoff!N14
A28: MATERIAL - Joint Filler | E28: Joint Filler? 'Yes' or 'No' | F28: Removal of Existing? | H28: Salt & Pepper | I28: 1.2 | J28: =ROUNDUP((I28*$H$27),0) | K28: ($0.75 - $1.90) | L28: =J28+$D$82 | M28: =L28/$H$27 | O28: =Takeoff!P14 | P28: =Takeoff!Q14 | Q28: =Takeoff!R14 | R28: =Takeoff!S14 | S28: =Takeoff!T14 | T28: =Takeoff!U14
A29: Joint Filler (10 gal kit) | B29: =ROUNDUP(IF(E29="yes",(E18/3500),0),0) | C29: 500 | D29: =B29*C29 | E29: Yes | F29: No | H29: Standard Sheen | I29: 0.9 | J29: =ROUNDUP((I29*$H$27),0) | K29: ($0.65 - $1.25) | L29: =J29+$D$82 | M29: =L29/$H$27 | O29: =Takeoff!I3 | P29: =Takeoff!J3 | Q29: =Takeoff!K3 | R29: =Takeoff!L3 | S29: =Takeoff!M3 | T29: =Takeoff!N3
D30: =B30*C30 | H30: Dye | I30: 1.02 | J30: =ROUNDUP((I30*$H$27),0) | K30: ($0.80 - $1.25) | L30: =J30+$D$82 | M30: =L30/$H$27
A31: Material Sub Total | D31: =ROUNDUP(SUM(D17:D30),0)
A32: Shipping | B32: 0.02 | D32: =ROUNDUP(D31*B32,0) | H32: Material Budget | K32: divided SF | L32: =B35/M32 | M32: 4 | N32: # divided by
A33: Material Total | D33: =SUM(D31:D32) | E33: =D33/B35 | F33: Material $/SF | H33: =D33 | K33: divided SF | L33: =B35/M33 | M33: 3 | N33: # divided by
K34: divided SF | L34: =B35/M34 | M34: 2 | N34: # divided by
A35: Square Footage: | B35: =E18 | C35: Linear Footage: | D35: =E19 | E35: 8 hour days | F35: =D35/B35 | G35: : Ratio of Cove-Floor | H35: 10%-20% = Normal | I35: (Grout for Full Agg Only) | K35: TOTAL SF | L35: =B35
A36: Labor: Guys | B36: Days | C36: Rate (PW?) | D36: Totals | E36: =(IF(D5="Yes","PW","TOTAL DAYS")) | F36: S&P | G36: Hybrid | H36: Dye? | I36: Grout? | J36: Demo Glue? | K36: Estimated SF/MH | L36: SF/MH Benchmark
A37: 3 | B37: =E37 | C37: 33 | D37: =(A37*B37*C37)*IF($E$35="8 hour days",8,10) | E37: =ROUNDUP(SUM(F37:J37),0) | F37: =ROUNDUP(Q10*$P$5,1) | G37: =ROUNDUP(R10*$P$5,1) | H37: =ROUNDUP(S10*$P$5,1) | I37: =ROUNDUP(T10*$P$5,1) | J37: =ROUNDUP(U10*$P$5,1) | K37: =B35/(D37/C37) | L37: S&P: 18-25
A38: 3 | B38: =E38 | C38: =C37 | D38: =(A38*B38*C38)*IF($E$35="8 hour days",8,10) | E38: =ROUNDUP(SUM(F38:J38),0) | F38: =ROUNDUP(Q11*$P$5,1) | G38: =ROUNDUP(R11*$P$5,1) | H38: =ROUNDUP(S11*$P$5,1) | I38: =ROUNDUP(T11*$P$5,1) | J38: =ROUNDUP(U11*$P$5,1) | K38: =B34/(D38/C38) | L38: Cream: 22-30
A39: Mock-Up: Guys | B39: Days | C39: Rate | F39: # of 10,000 | G39: (5 passes) S&P | H39: 5 - 7 days per 10k | I39: (3 passes) Cream | J39: 4 days per 10k
A40: 3 | B40: 0.5 | C40: =C37 | D40: =(A40*B40*C40)*IF($E$35="8 hour days",8,10) | E40: ( = 1.5 guys x 1 day) | F40: =B35/10000 | G40: Trowel Labor: | H40: =F40*6 | I40: Trowel Labor: | J40: =F40*4 | K40: Polish Man Power: If < 1k sf, 2 guys (except Full Agg.)
A41: Joint Filler: Guys | B41: Days | C41: Rate | F41: Trowel Labor Based on 3 guys | H41: Add Dye: (1 day/10k) | I41: =F40*1 | J41: *Add Dumpster*
A42: =IF(F29="NO",3,4) | B42: =(MROUND(IF(E29="no",0,IF(E18<1000,0.75,IF(E18<2500,1,IF(E18<10000,2,IF(E18<15000,3,E18/4500))))),0.5))/2 | C42: =C37 | D42: =(A42*B42*C42)*IF($E$35="8 hour days",8,10) | N42: Cream: (3 passes) 100 resin, 200 resin, 400 resin
A43: Travel: Guys | B43: Hours | N43: S&P: (5 passes) 60/80 metal, 50 resin, 100 resin, 200 resin, 400 resin
A44: =(A37*B37)+(A38*B38)+(A40*B40)+(A42*B42) | B44: =Epoxy!B52 | C44: 33 | D44: =(A44*B44*C44) | E44: =Epoxy!E52 | I44: =(((D45-D44)/C37)/A37)/40 | J44: # of 40 hour weeks | N44: Full/Large: (9[+] passes) BushHammers, 16 metal, 30 metal, (grout) 60/80 metal,
A45: Labor Total | D45: =ROUNDUP(SUM(D37:D44),0) | E45: =D45/B35 | F45: Labor $/SF | I45: =ROUNDUP(I44,0) | J45: # of weeks rounded up | O45: 50 resin, (grout) 100 resin, 200 resin, 400 resin, 800 resin, etc..?
A46: Labor Escalation | B46: (rate esc. only) | C46: =IF(D5="Yes",5%,0) | D46: =ROUNDUP((D45*C46),0) | E46: +5%IFPWorLong Lead Job (12+ months)
A47: Labor Burden | C47: 0.12 | D47: =ROUNDUP((D45+D46)*C47,0) | I47: ** Cement Mason ** | K47: ** Painter ** | N47: Holidays - Double Time
I48: Prevailing Wage Rate: | J48: =SUM(J49:J50) | K48: P. Wage Rate: | L48: =SUM(L49:L50) | N48: New Year's Day
A49: TOOLING & CONSUMABLES | B49: Quantity | C49: Cost | D49: Totals | I49: rate = | J49: 0 | K49: rate = | L49: 0 | N49: Memorial Day
I50: + fringes = | J50: 0 | K50: + fringes = | L50: 0 | N50: July 4th
A51: Tooling & Consumables | B51: =B35 | C51: =(SUM(V10:W10))*1.08 | D51: =ROUNDUP(IF((B51*C51)>150,(B51*C51),150),0) | E51: *data pulled from calculator (+8%) ---> | I51: Foreman *min. $32 Cement Mason | K51: Foreman *min. $32 Painter | N51: Labor Day
A52: Demo Tooling (/sf) | C52: 0.33 | D52: =ROUNDUP(B52*C52,0) | E52: ($0.17 glue/VCT/carpet or $0.33 demo tile) | I52: (Entry *min. $23 Cement Mason) | K52: (Entry *min. $23 Painter) | N52: Thanksgiving
A53: Slurry Hardener | B53: =ROUNDUP(B35/5000,0) | C53: 210 | D53: =ROUNDUP(B53*C53,0) | E53: (at min. 1 bag per 5,000sf) | I53: 1:1 "Entry" Half Wage | J53: =IF((J48/2)<23,23,(J48/2)) | K53: 1:1 "Entry" Half Wage | L53: =IF((L48/2)<23,23,(L48/2)) | N53: Christmas
A54: Plastic (per LF) | B54: =IF(E25="yes",D35,IF(B35>4999,IF(B10="reno",D35))) | C54: 0.25 | D54: =ROUNDUP(B54*C54,0) | E54: Dye or Reno 5k sf+? | J54: "Entry" Laborer for MO "State" Wage ONLY | L54: NOT davis-bacon
A55: Tooling and Consumables Total | D55: =SUM(D50:D54) | H55: =E35
G56: Total Man Hours | H56: =(((A37*B37)+(A38*B38)+(A40*B40)+(A42*B42))*IF($E$35="8 hour days",8,10))+(A44*B44)
A57: TRAVEL | B57: Quantity | C57: Cost | D57: Totals | G57: Total Days | H57: =H56/IF($E$35="8 hour days",8,10)/H58
A58: Travel - Lodging | B58: =IF(B4="No",((D45-D44)/C37)/8) | C58: 70 | D58: =ROUNDUP(B58*C58,0) | G58: ^based on X crew size: | H58: =A37 | R58: Will's orig Joint Filler Labor Formula: | S58: =(MROUND(IF(E29="no",0,IF(E18<1000,0.75,IF(E18<2500,1,IF(E18<10000,2,IF(E18<15000,3,E18/3750))))),0.5))
A59: Travel - Food | B59: =B58 | C59: 45 | D59: =ROUNDUP(B59*C59,0) | S59: NOTE: **3750** above end of formula
D60: =ROUNDUP(B60*C60,0)
A61: Travel Costs Total | D61: =SUM(D58:D60)
A64: SUB-TOTAL COSTS | D64: =ROUNDUP(SUM(D33,D45:D47,D55,D61),0) | E64: =D64/B35 | F64: Sub-Total $/SF
A66: MARKUP | B66: % | D66: Totals | F66: =SUM(D64,D76,D79) | G66: Total "Estimated Costs" w/taxes + fees + bond | I66: =F66/C81
A67: GP (before lines below) | B67: =IF(D64<6500,0.52,IF(D64<15000,0.45,IF(D64<22500,0.35,IF(D64<32500,0.32,0.3)))) | D67: =ROUNDUP(SUM(D64,D74,D77)/(1-B67),0)-ROUNDUP(SUM(D64,D74,D77),0) | F67: =(((A37*B37)+(A38*B38)+(A40*B40)+(A42*B42))*IF($E$35="8 hour days",8,10))+(A44*B44) | G67: Man Hour Budget (Raken)
A68: Hard Bid Discount | B68: =IF(B5="yes",IF(D64>=60000,-0.04,IF(B4="yes",IF(D64>=13000,-0.025,0)))) | D68: =ROUNDUP(SUM(D64,D67)*B68,0) | F68: =F81/H57 | G68: GP per Day | H68: =E35
A69: Superintendent & PTO | B69: 0.027 | D69: =ROUNDUP(SUM(D64:D68,D71,D74,D77)*B69,0)
A70: Soft Costs | B70: 0.16 | D70: =(ROUNDUP(SUM(D64:D69,D71,D74,D77)*B70,0))+0
A71: Contingency | B71: -- ?? --> | D71: 0
A73: TAXES & FEES | B73: % | D73: Totals | J73: =(J76-J74-J75)
A74: Sales Tax | B74: =IF($B$6="no",0,0.09475) | D74: =ROUNDUP(SUM(D33)*B74,0) | K74: sales tax (enter rounded)
A75: Kansas Remodel Tax | B75: =IF(D6="yes",0.1,0) | D75: =ROUNDUP(SUM(D45:D47,D55,D61,D67:D71,D77)*B75,0) | E75: =IF(D6="yes","*10% is placeholder. Adjust to actual if project awarded"," ") | K75: ks remodel (enter rounded)
A76: Total Taxes | D76: =SUM(D74:D75) | J76: =D82 | K76: total
A77: Fees + Textura + ? | D77: =ROUNDUP(B77*C77,0)
A78: Bond | B78: 0 | D78: =ROUNDUP(SUM(D64,D67,D68,D69:D71,D74,D75:D77)*B78,0) | J78: =C81*N78 | K78: Deduct VE for Grind & Sealin lieu of S&P ONLY | N78: -2 | O78: $ /sf deduct
A79: Total Fees + Bond | D79: =ROUNDUP(SUM(D77:D78),0) | K79: ^^ new total would be: ---> | L79: =D82+J78 | M79: =L79/C81
F80: Mark Up + Conting. | G80: GP / MH | H80: MarkUp + Soft Costs | K80: For PM's Reference
B81: Square Footage: | C81: =B35 | E81: Less Sales Tax | F81: =SUM(D67:D68,D71) | G81: =F81/F67 | H81: =SUM(D67:D71) | J81: Material + Tooling % | K81: Labor % | L81: Travel %
A82: TOTAL | C82: =D82/C81 | D82: =SUM(D64,D67:D71,D76,D79) | E82: =D82-(D74+D75) | F82: =F81/(D82) | G82: =C37 | H82: =H81/D82 | I82: 45% = Polish Goal | J82: =(H33+D55)/D82 | K82: =(SUM(D45:D47)/D82) | L82: =D61/D82
C83: =D83/C81 | D83: =D82-D75 | E83: (less ks remodel tax, no joints) | G83: LaborRate from Above | I83: (epx: 42% & pol: 45%)
J84: =SUM(D33,D55) | K84: =J84/J87 | L84: Material+Tooling | M84: % Breakdown
B85: Add for additional phase | C85: 4500 | J85: =SUM(D45:D47,D61) | K85: =J85/J87 | L85: Labor + Travel
J86: =SUM(D67:D71,D76,D79) | K86: =J86/J87 | L86: Mark-Up+Tax
J87: =SUM(J84:J86) | K87: =SUM(K84:K86) | L87: Total

Sheet Gyp (USG 1-8")
A1: =B16 | B1: : Base Bid | G1: Bidding Contacts: | M1: Layout | N1: Layout
A2: Project | M2: Building # | N2: Floor # | O2: Total SF per Floor | P2: SF-Soft Surfaces | Q2: SF-Hard Surfaces | R2: SF-Corridors | S2: Bags | T2: Mobilizations | U2: Alt Mobs. | V2: Days per Area | W2: Mat Totals | X2: Bag Totals
A3: Bid Date | O3: =SUM(P3:R3) | S3: =((P3+Q3+R3)/F22)*H33
A4: Address | O4: =SUM(P4:R4) | S4: =((P4+Q4+R4)/F22)*H33
A5: Local? | B5: Yes | C5: < 70 miles? | D5: Look-Up on Google Earth | O5: =SUM(P5:R5) | S5: =((P5+Q5+R5)/F22)*H33
A6: Miles Away | B6: 0 | O6: =SUM(P6:R6) | S6: =((P6+Q6+R6)/F22)*H33 | AM6: 1000 | AP6: =AM6 | AS6: =AM6+AP6 | AV6: =AS6 | AW6: =IF(AM6<=#REF!,#REF!,IF(AM6<=#REF!,#REF!,IF(AM6<=#REF!,#REF!,IF(AM6<=#REF!,#REF!,IF(AM6<=#REF!,#REF!,IF(AM6<=#REF!,#REF!,IF(AM6<=#REF!,#REF!,0.05))))))) | AX6: =AW6*AM6 | AZ6: =IF(AP6<=#REF!,#REF!,IF(AP6<=#REF!,#REF!,IF(AP6<=#REF!,#REF!,IF(AP6<=#REF!,#REF!,IF(AP6<=#REF!,#REF!,IF(AP6<=#REF!,#REF!,IF(AP6<=#REF!,#REF!,0.05))))))) | BA6: =AZ6*AP6 | BC6: =IF(AS6<=#REF!,#REF!,IF(AS6<=#REF!,#REF!,IF(AS6<=#REF!,#REF!,IF(AS6<=#REF!,#REF!,IF(AS6<=#REF!,#REF!,IF(AS6<=#REF!,#REF!,IF(AS6<=#REF!,#REF!,0.05))))))) | BD6: =BC6*SUM(BA6,AX6,AS6) | BF6: =IF(AV6<=#REF!,#REF!,IF(AV6<=#REF!,#REF!,IF(AV6<=#REF!,#REF!,IF(AV6<=#REF!,#REF!,IF(AV6<=#REF!,#REF!,IF(AV6<=#REF!,#REF!,IF(AV6<=#REF!,#REF!,0.05))))))) | BG6: =BF6*AV6 | BI6: =0.07*SUM(AS6,AX6,BA6,BD6,BG6) | BK6: =SUM(BI6,BG6,BD6,BA6,AX6,AS6) | BL6: =SUM(BG6,BD6,BA6,AX6) | BM6: =BL6/BK6 | BP6: 0.1 | BQ6: 5000 | BS6: 0.35 | BT6: 2000 | BV6: 0.28 | BW6: 9000 | BY6: 0 | BZ6: 9000 | CC6: 1000 | CF6: =CC6 | CI6: =CC6+CF6 | CL6: =CI6 | CM6: =IF(CC6<=BQ$6,BP$6,IF(CC6<=BQ$7,BP$7,IF(CC6<=BQ$8,BP$8,IF(CC6<=BQ$9,BP$9,IF(CC6<=BQ$14,BP$14,IF(CC6<=BQ$15,BP$15,IF(CC6<=BQ$16,BP$16,0.05))))))) | CN6: =CM6*CC6 | CP6: =IF(CF6<=BT$6,BS$6,IF(CF6<=BT$7,BS$7,IF(CF6<=BT$8,BS$8,IF(CF6<=BT$9,BS$9,IF(CF6<=BT$14,BS$14,IF(CF6<=BT$15,BS$15,IF(CF6<=BT$16,BS$16,0.05))))))) | CQ6: =CP6*CF6 | CS6: =IF(CI6<=BW$6,BV$6,IF(CI6<=BW$7,BV$7,IF(CI6<=BW$8,BV$8,IF(CI6<=BW$9,BV$9,IF(CI6<=BW$14,BV$14,IF(CI6<=BW$15,BV$15,IF(CI6<=BW$16,BV$16,0.05))))))) | CT6: =CS6*SUM(CQ6,CN6,CI6) | CV6: =IF(CL6<=BZ$6,BY$6,IF(CL6<=BZ$7,BY$7,IF(CL6<=BZ$8,BY$8,IF(CL6<=BZ$9,BY$9,IF(CL6<=BZ$14,BY$14,IF(CL6<=BZ$15,BY$15,IF(CL6<=BZ$16,BY$16,0.05))))))) | CW6: =CV6*CL6 | CY6: =0.07*SUM(CI6,CN6,CQ6,CT6,CW6) | DA6: =SUM(CY6,CW6,CT6,CQ6,CN6,CI6) | DB6: =SUM(CW6,CT6,CQ6,CN6) | DC6: =DB6/DA6
A7: Hard Bid? | B7: No | C7: PrevailingWage? | D7: =Epoxy!D5 | E7: =Epoxy!E5 | F7: Total SF: | G7: =G9+I9+K9 | O7: =SUM(P7:R7) | S7: =((P7+Q7+R7)/F22)*H33 | AM7: 2000 | AP7: =AM7 | AS7: =AM7+AP7 | AV7: =AS7 | AW7: =IF(AM7<=#REF!,#REF!,IF(AM7<=#REF!,#REF!,IF(AM7<=#REF!,#REF!,IF(AM7<=#REF!,#REF!,IF(AM7<=#REF!,#REF!,IF(AM7<=#REF!,#REF!,IF(AM7<=#REF!,#REF!,0.05))))))) | AX7: =AW7*AM7 | AZ7: =IF(AP7<=#REF!,#REF!,IF(AP7<=#REF!,#REF!,IF(AP7<=#REF!,#REF!,IF(AP7<=#REF!,#REF!,IF(AP7<=#REF!,#REF!,IF(AP7<=#REF!,#REF!,IF(AP7<=#REF!,#REF!,0.05))))))) | BA7: =AZ7*AP7 | BC7: =IF(AS7<=#REF!,#REF!,IF(AS7<=#REF!,#REF!,IF(AS7<=#REF!,#REF!,IF(AS7<=#REF!,#REF!,IF(AS7<=#REF!,#REF!,IF(AS7<=#REF!,#REF!,IF(AS7<=#REF!,#REF!,0.05))))))) | BD7: =BC7*SUM(BA7,AX7,AS7) | BF7: =IF(AV7<=#REF!,#REF!,IF(AV7<=#REF!,#REF!,IF(AV7<=#REF!,#REF!,IF(AV7<=#REF!,#REF!,IF(AV7<=#REF!,#REF!,IF(AV7<=#REF!,#REF!,IF(AV7<=#REF!,#REF!,0.05))))))) | BG7: =BF7*AV7 | BI7: =0.07*SUM(AS7,AX7,BA7,BD7,BG7) | BK7: =SUM(BI7,BG7,BD7,BA7,AX7,AS7) | BL7: =SUM(BG7,BD7,BA7,AX7) | BM7: =BL7/BK7 | BP7: 0.05 | BQ7: 1000000000 | BS7: 0.3 | BT7: 3000 | BV7: 0.24 | BW7: 14000 | BY7: -0.04 | BZ7: 14000 | CC7: 2000 | CF7: =CC7 | CI7: =CC7+CF7 | CL7: =CI7 | CM7: =IF(CC7<=BQ$6,BP$6,IF(CC7<=BQ$7,BP$7,IF(CC7<=BQ$8,BP$8,IF(CC7<=BQ$9,BP$9,IF(CC7<=BQ$14,BP$14,IF(CC7<=BQ$15,BP$15,IF(CC7<=BQ$16,BP$16,0.05))))))) | CN7: =CM7*CC7 | CP7: =IF(CF7<=BT$6,BS$6,IF(CF7<=BT$7,BS$7,IF(CF7<=BT$8,BS$8,IF(CF7<=BT$9,BS$9,IF(CF7<=BT$14,BS$14,IF(CF7<=BT$15,BS$15,IF(CF7<=BT$16,BS$16,0.05))))))) | CQ7: =CP7*CF7 | CS7: =IF(CI7<=BW$6,BV$6,IF(CI7<=BW$7,BV$7,IF(CI7<=BW$8,BV$8,IF(CI7<=BW$9,BV$9,IF(CI7<=BW$14,BV$14,IF(CI7<=BW$15,BV$15,IF(CI7<=BW$16,BV$16,0.05))))))) | CT7: =CS7*SUM(CQ7,CN7,CI7) | CV7: =IF(CL7<=BZ$6,BY$6,IF(CL7<=BZ$7,BY$7,IF(CL7<=BZ$8,BY$8,IF(CL7<=BZ$9,BY$9,IF(CL7<=BZ$14,BY$14,IF(CL7<=BZ$15,BY$15,IF(CL7<=BZ$16,BY$16,0.05))))))) | CW7: =CV7*CL7 | CY7: =0.07*SUM(CI7,CN7,CQ7,CT7,CW7) | DA7: =SUM(CY7,CW7,CT7,CQ7,CN7,CI7) | DB7: =SUM(CW7,CT7,CQ7,CN7) | DC7: =DB7/DA7
A8: Taxable? | B8: Yes | C8: Remodel Tax? | D8: =Epoxy!D6 | E8: =Epoxy!E6 | F8: Unit | H8: Unit | J8: Corridor | O8: =SUM(P8:R8) | S8: =((P8+Q8+R8)/F22)*H33 | AM8: 3000 | AP8: =AM8 | AS8: =AM8+AP8 | AV8: =AS8 | AW8: =IF(AM8<=#REF!,#REF!,IF(AM8<=#REF!,#REF!,IF(AM8<=#REF!,#REF!,IF(AM8<=#REF!,#REF!,IF(AM8<=#REF!,#REF!,IF(AM8<=#REF!,#REF!,IF(AM8<=#REF!,#REF!,0.05))))))) | AX8: =AW8*AM8 | AZ8: =IF(AP8<=#REF!,#REF!,IF(AP8<=#REF!,#REF!,IF(AP8<=#REF!,#REF!,IF(AP8<=#REF!,#REF!,IF(AP8<=#REF!,#REF!,IF(AP8<=#REF!,#REF!,IF(AP8<=#REF!,#REF!,0.05))))))) | BA8: =AZ8*AP8 | BC8: =IF(AS8<=#REF!,#REF!,IF(AS8<=#REF!,#REF!,IF(AS8<=#REF!,#REF!,IF(AS8<=#REF!,#REF!,IF(AS8<=#REF!,#REF!,IF(AS8<=#REF!,#REF!,IF(AS8<=#REF!,#REF!,0.05))))))) | BD8: =BC8*SUM(BA8,AX8,AS8) | BF8: =IF(AV8<=#REF!,#REF!,IF(AV8<=#REF!,#REF!,IF(AV8<=#REF!,#REF!,IF(AV8<=#REF!,#REF!,IF(AV8<=#REF!,#REF!,IF(AV8<=#REF!,#REF!,IF(AV8<=#REF!,#REF!,0.05))))))) | BG8: =BF8*AV8 | BI8: =0.07*SUM(AS8,AX8,BA8,BD8,BG8) | BK8: =SUM(BI8,BG8,BD8,BA8,AX8,AS8) | BL8: =SUM(BG8,BD8,BA8,AX8) | BM8: =BL8/BK8 | BP8: 0.05 | BQ8: 1000000000 | BS8: 0.2 | BT8: 4000 | BV8: 0.22 | BW8: 19000 | BY8: -0.05 | BZ8: 19000 | CC8: 3000 | CF8: =CC8 | CI8: =CC8+CF8 | CL8: =CI8 | CM8: =IF(CC8<=BQ$6,BP$6,IF(CC8<=BQ$7,BP$7,IF(CC8<=BQ$8,BP$8,IF(CC8<=BQ$9,BP$9,IF(CC8<=BQ$14,BP$14,IF(CC8<=BQ$15,BP$15,IF(CC8<=BQ$16,BP$16,0.05))))))) | CN8: =CM8*CC8 | CP8: =IF(CF8<=BT$6,BS$6,IF(CF8<=BT$7,BS$7,IF(CF8<=BT$8,BS$8,IF(CF8<=BT$9,BS$9,IF(CF8<=BT$14,BS$14,IF(CF8<=BT$15,BS$15,IF(CF8<=BT$16,BS$16,0.05))))))) | CQ8: =CP8*CF8 | CS8: =IF(CI8<=BW$6,BV$6,IF(CI8<=BW$7,BV$7,IF(CI8<=BW$8,BV$8,IF(CI8<=BW$9,BV$9,IF(CI8<=BW$14,BV$14,IF(CI8<=BW$15,BV$15,IF(CI8<=BW$16,BV$16,0.05))))))) | CT8: =CS8*SUM(CQ8,CN8,CI8) | CV8: =IF(CL8<=BZ$6,BY$6,IF(CL8<=BZ$7,BY$7,IF(CL8<=BZ$8,BY$8,IF(CL8<=BZ$9,BY$9,IF(CL8<=BZ$14,BY$14,IF(CL8<=BZ$15,BY$15,IF(CL8<=BZ$16,BY$16,0.05))))))) | CW8: =CV8*CL8 | CY8: =0.07*SUM(CI8,CN8,CQ8,CT8,CW8) | DA8: =SUM(CY8,CW8,CT8,CQ8,CN8,CI8) | DB8: =SUM(CW8,CT8,CQ8,CN8) | DC8: =DB8/DA8
A9: Approx Start Date | F9: SF - Soft Surfaces: | G9: =P28 | H9: SF - Hard Surfaces: | I9: =Q28 | J9: SF - Corridors: | K9: =R28 | O9: =SUM(P9:R9) | S9: =((P9+Q9+R9)/F22)*H33 | AM9: 4000 | AP9: =AM9 | AS9: =AM9+AP9 | AV9: =AS9 | AW9: =IF(AM9<=#REF!,#REF!,IF(AM9<=#REF!,#REF!,IF(AM9<=#REF!,#REF!,IF(AM9<=#REF!,#REF!,IF(AM9<=#REF!,#REF!,IF(AM9<=#REF!,#REF!,IF(AM9<=#REF!,#REF!,0.05))))))) | AX9: =AW9*AM9 | AZ9: =IF(AP9<=#REF!,#REF!,IF(AP9<=#REF!,#REF!,IF(AP9<=#REF!,#REF!,IF(AP9<=#REF!,#REF!,IF(AP9<=#REF!,#REF!,IF(AP9<=#REF!,#REF!,IF(AP9<=#REF!,#REF!,0.05))))))) | BA9: =AZ9*AP9 | BC9: =IF(AS9<=#REF!,#REF!,IF(AS9<=#REF!,#REF!,IF(AS9<=#REF!,#REF!,IF(AS9<=#REF!,#REF!,IF(AS9<=#REF!,#REF!,IF(AS9<=#REF!,#REF!,IF(AS9<=#REF!,#REF!,0.05))))))) | BD9: =BC9*SUM(BA9,AX9,AS9) | BF9: =IF(AV9<=#REF!,#REF!,IF(AV9<=#REF!,#REF!,IF(AV9<=#REF!,#REF!,IF(AV9<=#REF!,#REF!,IF(AV9<=#REF!,#REF!,IF(AV9<=#REF!,#REF!,IF(AV9<=#REF!,#REF!,0.05))))))) | BG9: =BF9*AV9 | BI9: =0.07*SUM(AS9,AX9,BA9,BD9,BG9) | BK9: =SUM(BI9,BG9,BD9,BA9,AX9,AS9) | BL9: =SUM(BG9,BD9,BA9,AX9) | BM9: =BL9/BK9 | BP9: 0.05 | BQ9: 1000000000 | BS9: 0.1 | BT9: 7000 | BV9: 0.2 | BW9: 24000 | BY9: -0.05 | BZ9: 34000 | CC9: 4000 | CF9: =CC9 | CI9: =CC9+CF9 | CL9: =CI9 | CM9: =IF(CC9<=BQ$6,BP$6,IF(CC9<=BQ$7,BP$7,IF(CC9<=BQ$8,BP$8,IF(CC9<=BQ$9,BP$9,IF(CC9<=BQ$14,BP$14,IF(CC9<=BQ$15,BP$15,IF(CC9<=BQ$16,BP$16,0.05))))))) | CN9: =CM9*CC9 | CP9: =IF(CF9<=BT$6,BS$6,IF(CF9<=BT$7,BS$7,IF(CF9<=BT$8,BS$8,IF(CF9<=BT$9,BS$9,IF(CF9<=BT$14,BS$14,IF(CF9<=BT$15,BS$15,IF(CF9<=BT$16,BS$16,0.05))))))) | CQ9: =CP9*CF9 | CS9: =IF(CI9<=BW$6,BV$6,IF(CI9<=BW$7,BV$7,IF(CI9<=BW$8,BV$8,IF(CI9<=BW$9,BV$9,IF(CI9<=BW$14,BV$14,IF(CI9<=BW$15,BV$15,IF(CI9<=BW$16,BV$16,0.05))))))) | CT9: =CS9*SUM(CQ9,CN9,CI9) | CV9: =IF(CL9<=BZ$6,BY$6,IF(CL9<=BZ$7,BY$7,IF(CL9<=BZ$8,BY$8,IF(CL9<=BZ$9,BY$9,IF(CL9<=BZ$14,BY$14,IF(CL9<=BZ$15,BY$15,IF(CL9<=BZ$16,BY$16,0.05))))))) | CW9: =CV9*CL9 | CY9: =0.07*SUM(CI9,CN9,CQ9,CT9,CW9) | DA9: =SUM(CY9,CW9,CT9,CQ9,CN9,CI9) | DB9: =SUM(CW9,CT9,CQ9,CN9) | DC9: =DB9/DA9
A10: Architect | F10: Ave Thickness: | G10: 0.75 | H10: Ave Thickness: | I10: 0.75 | J10: Ave Thickness: | K10: =G10 | O10: =SUM(P10:R10) | S10: =((P10+Q10+R10)/F22)*H33
A11: Drawings Dated | F11: Mix Design: (default= 2500psi @1.8) | G11: 1.8 | H11: Mix Design: | I11: =G11 | J11: Mix Design: | K11: =G11 | O11: =SUM(P11:R11) | S11: =((P11+Q11+R11)/F22)*H33
A12: New / Reno: | B12: New | F12: Yield Per Bag (1/8") | G12: 254.52 | H12: Yield Per Bag (1/8") | I12: 254.52 | J12: Yield Per Bag (1/8") | K12: 254.52 | O12: =SUM(P12:R12) | S12: =((P12+Q12+R12)/F22)*H33
A13: Hallow Plank Subfloor: | B13: No | F13: Bag Type: | G13: Levelrock 2500 | H13: Bag Type: | I13: =G13 | J13: Bag Type: | K13: =G13 | O13: =SUM(P13:R13) | S13: =((P13+Q13+R13)/F22)*H33
A14: ISO Strip at All Areas: | B14: No | F14: Yield at 3/4" | G14: 40 | H14: 42 more realistic | O14: =SUM(P14:R14) | S14: =((P14+Q14+R14)/F22)*H33 | AM14: 5000 | AP14: =AM14 | AS14: =AM14+AP14 | AV14: =AS14 | AW14: =IF(AM14<=#REF!,#REF!,IF(AM14<=#REF!,#REF!,IF(AM14<=#REF!,#REF!,IF(AM14<=#REF!,#REF!,IF(AM14<=#REF!,#REF!,IF(AM14<=#REF!,#REF!,IF(AM14<=#REF!,#REF!,0.05))))))) | AX14: =AW14*AM14 | AZ14: =IF(AP14<=#REF!,#REF!,IF(AP14<=#REF!,#REF!,IF(AP14<=#REF!,#REF!,IF(AP14<=#REF!,#REF!,IF(AP14<=#REF!,#REF!,IF(AP14<=#REF!,#REF!,IF(AP14<=#REF!,#REF!,0.05))))))) | BA14: =AZ14*AP14 | BC14: =IF(AS14<=#REF!,#REF!,IF(AS14<=#REF!,#REF!,IF(AS14<=#REF!,#REF!,IF(AS14<=#REF!,#REF!,IF(AS14<=#REF!,#REF!,IF(AS14<=#REF!,#REF!,IF(AS14<=#REF!,#REF!,0.05))))))) | BD14: =BC14*SUM(BA14,AX14,AS14) | BF14: =IF(AV14<=#REF!,#REF!,IF(AV14<=#REF!,#REF!,IF(AV14<=#REF!,#REF!,IF(AV14<=#REF!,#REF!,IF(AV14<=#REF!,#REF!,IF(AV14<=#REF!,#REF!,IF(AV14<=#REF!,#REF!,0.05))))))) | BG14: =BF14*AV14 | BI14: =0.07*SUM(AS14,AX14,BA14,BD14,BG14) | BK14: =SUM(BI14,BG14,BD14,BA14,AX14,AS14) | BL14: =SUM(BG14,BD14,BA14,AX14) | BM14: =BL14/BK14 | BP14: 0.05 | BQ14: 1000000000 | BS14: 0.05 | BT14: 10000 | BV14: 0.18 | BW14: 1000000000 | BY14: -0.055 | BZ14: 44000 | CC14: 5000 | CF14: =CC14 | CI14: =CC14+CF14 | CL14: =CI14 | CM14: =IF(CC14<=BQ$6,BP$6,IF(CC14<=BQ$7,BP$7,IF(CC14<=BQ$8,BP$8,IF(CC14<=BQ$9,BP$9,IF(CC14<=BQ$14,BP$14,IF(CC14<=BQ$15,BP$15,IF(CC14<=BQ$16,BP$16,0.05))))))) | CN14: =CM14*CC14 | CP14: =IF(CF14<=BT$6,BS$6,IF(CF14<=BT$7,BS$7,IF(CF14<=BT$8,BS$8,IF(CF14<=BT$9,BS$9,IF(CF14<=BT$14,BS$14,IF(CF14<=BT$15,BS$15,IF(CF14<=BT$16,BS$16,0.05))))))) | CQ14: =CP14*CF14 | CS14: =IF(CI14<=BW$6,BV$6,IF(CI14<=BW$7,BV$7,IF(CI14<=BW$8,BV$8,IF(CI14<=BW$9,BV$9,IF(CI14<=BW$14,BV$14,IF(CI14<=BW$15,BV$15,IF(CI14<=BW$16,BV$16,0.05))))))) | CT14: =CS14*SUM(CQ14,CN14,CI14) | CV14: =IF(CL14<=BZ$6,BY$6,IF(CL14<=BZ$7,BY$7,IF(CL14<=BZ$8,BY$8,IF(CL14<=BZ$9,BY$9,IF(CL14<=BZ$14,BY$14,IF(CL14<=BZ$15,BY$15,IF(CL14<=BZ$16,BY$16,0.05))))))) | CW14: =CV14*CL14 | CY14: =0.07*SUM(CI14,CN14,CQ14,CT14,CW14) | DA14: =SUM(CY14,CW14,CT14,CQ14,CN14,CI14) | DB14: =SUM(CW14,CT14,CQ14,CN14) | DC14: =DB14/DA14
A15: Metal Lath Reinfrcmnt: | B15: No | F15: Yield per 1/8" | G15: =G14*6 | O15: =SUM(P15:R15) | S15: =((P15+Q15+R15)/F22)*H33 | AM15: 6000 | AP15: =AM15 | AS15: =AM15+AP15 | AV15: =AS15 | AW15: =IF(AM15<=#REF!,#REF!,IF(AM15<=#REF!,#REF!,IF(AM15<=#REF!,#REF!,IF(AM15<=#REF!,#REF!,IF(AM15<=#REF!,#REF!,IF(AM15<=#REF!,#REF!,IF(AM15<=#REF!,#REF!,0.05))))))) | AX15: =AW15*AM15 | AZ15: =IF(AP15<=#REF!,#REF!,IF(AP15<=#REF!,#REF!,IF(AP15<=#REF!,#REF!,IF(AP15<=#REF!,#REF!,IF(AP15<=#REF!,#REF!,IF(AP15<=#REF!,#REF!,IF(AP15<=#REF!,#REF!,0.05))))))) | BA15: =AZ15*AP15 | BC15: =IF(AS15<=#REF!,#REF!,IF(AS15<=#REF!,#REF!,IF(AS15<=#REF!,#REF!,IF(AS15<=#REF!,#REF!,IF(AS15<=#REF!,#REF!,IF(AS15<=#REF!,#REF!,IF(AS15<=#REF!,#REF!,0.05))))))) | BD15: =BC15*SUM(BA15,AX15,AS15) | BF15: =IF(AV15<=#REF!,#REF!,IF(AV15<=#REF!,#REF!,IF(AV15<=#REF!,#REF!,IF(AV15<=#REF!,#REF!,IF(AV15<=#REF!,#REF!,IF(AV15<=#REF!,#REF!,IF(AV15<=#REF!,#REF!,0.05))))))) | BG15: =BF15*AV15 | BI15: =0.07*SUM(AS15,AX15,BA15,BD15,BG15) | BK15: =SUM(BI15,BG15,BD15,BA15,AX15,AS15) | BL15: =SUM(BG15,BD15,BA15,AX15) | BM15: =BL15/BK15 | BP15: 0.05 | BQ15: 1000000000 | BS15: 0.03 | BT15: 1000000000 | BV15: 0.18 | BW15: 1000000000 | BY15: -0.06 | BZ15: 1000000000 | CC15: 6000 | CF15: =CC15 | CI15: =CC15+CF15 | CL15: =CI15 | CM15: =IF(CC15<=BQ$6,BP$6,IF(CC15<=BQ$7,BP$7,IF(CC15<=BQ$8,BP$8,IF(CC15<=BQ$9,BP$9,IF(CC15<=BQ$14,BP$14,IF(CC15<=BQ$15,BP$15,IF(CC15<=BQ$16,BP$16,0.05))))))) | CN15: =CM15*CC15 | CP15: =IF(CF15<=BT$6,BS$6,IF(CF15<=BT$7,BS$7,IF(CF15<=BT$8,BS$8,IF(CF15<=BT$9,BS$9,IF(CF15<=BT$14,BS$14,IF(CF15<=BT$15,BS$15,IF(CF15<=BT$16,BS$16,0.05))))))) | CQ15: =CP15*CF15 | CS15: =IF(CI15<=BW$6,BV$6,IF(CI15<=BW$7,BV$7,IF(CI15<=BW$8,BV$8,IF(CI15<=BW$9,BV$9,IF(CI15<=BW$14,BV$14,IF(CI15<=BW$15,BV$15,IF(CI15<=BW$16,BV$16,0.05))))))) | CT15: =CS15*SUM(CQ15,CN15,CI15) | CV15: =IF(CL15<=BZ$6,BY$6,IF(CL15<=BZ$7,BY$7,IF(CL15<=BZ$8,BY$8,IF(CL15<=BZ$9,BY$9,IF(CL15<=BZ$14,BY$14,IF(CL15<=BZ$15,BY$15,IF(CL15<=BZ$16,BY$16,0.05))))))) | CW15: =CV15*CL15 | CY15: =0.07*SUM(CI15,CN15,CQ15,CT15,CW15) | DA15: =SUM(CY15,CW15,CT15,CQ15,CN15,CI15) | DB15: =SUM(CW15,CT15,CQ15,CN15) | DC15: =DB15/DA15
A16: System- Gyp: | B16: N12 1/8" | C16: + 3/4" Gyp | D16: 1.8 Mix:2500psi | F16: Eights req at Thickness | G16: 6 | H16: *change this depending on depth, 1"=8… 3/4"=6* | O16: =SUM(P16:R16) | S16: =((P16+Q16+R16)/F22)*H33 | AM16: 7000 | AP16: =AM16 | AS16: =AM16+AP16 | AV16: =AS16 | AW16: =IF(AM16<=#REF!,#REF!,IF(AM16<=#REF!,#REF!,IF(AM16<=#REF!,#REF!,IF(AM16<=#REF!,#REF!,IF(AM16<=#REF!,#REF!,IF(AM16<=#REF!,#REF!,IF(AM16<=#REF!,#REF!,0.05))))))) | AX16: =AW16*AM16 | AZ16: =IF(AP16<=#REF!,#REF!,IF(AP16<=#REF!,#REF!,IF(AP16<=#REF!,#REF!,IF(AP16<=#REF!,#REF!,IF(AP16<=#REF!,#REF!,IF(AP16<=#REF!,#REF!,IF(AP16<=#REF!,#REF!,0.05))))))) | BA16: =AZ16*AP16 | BC16: =IF(AS16<=#REF!,#REF!,IF(AS16<=#REF!,#REF!,IF(AS16<=#REF!,#REF!,IF(AS16<=#REF!,#REF!,IF(AS16<=#REF!,#REF!,IF(AS16<=#REF!,#REF!,IF(AS16<=#REF!,#REF!,0.05))))))) | BD16: =BC16*SUM(BA16,AX16,AS16) | BF16: =IF(AV16<=#REF!,#REF!,IF(AV16<=#REF!,#REF!,IF(AV16<=#REF!,#REF!,IF(AV16<=#REF!,#REF!,IF(AV16<=#REF!,#REF!,IF(AV16<=#REF!,#REF!,IF(AV16<=#REF!,#REF!,0.05))))))) | BG16: =BF16*AV16 | BI16: =0.07*SUM(AS16,AX16,BA16,BD16,BG16) | BK16: =SUM(BI16,BG16,BD16,BA16,AX16,AS16) | BL16: =SUM(BG16,BD16,BA16,AX16) | BM16: =BL16/BK16 | BP16: 0.05 | BQ16: 1000000000 | BS16: 0.03 | BT16: 1000000000 | BV16: 0.18 | BW16: 1000000000 | BY16: 0 | BZ16: 1000000000 | CC16: 7000 | CF16: =CC16 | CI16: =CC16+CF16 | CL16: =CI16 | CM16: =IF(CC16<=BQ$6,BP$6,IF(CC16<=BQ$7,BP$7,IF(CC16<=BQ$8,BP$8,IF(CC16<=BQ$9,BP$9,IF(CC16<=BQ$14,BP$14,IF(CC16<=BQ$15,BP$15,IF(CC16<=BQ$16,BP$16,0.05))))))) | CN16: =CM16*CC16 | CP16: =IF(CF16<=BT$6,BS$6,IF(CF16<=BT$7,BS$7,IF(CF16<=BT$8,BS$8,IF(CF16<=BT$9,BS$9,IF(CF16<=BT$14,BS$14,IF(CF16<=BT$15,BS$15,IF(CF16<=BT$16,BS$16,0.05))))))) | CQ16: =CP16*CF16 | CS16: =IF(CI16<=BW$6,BV$6,IF(CI16<=BW$7,BV$7,IF(CI16<=BW$8,BV$8,IF(CI16<=BW$9,BV$9,IF(CI16<=BW$14,BV$14,IF(CI16<=BW$15,BV$15,IF(CI16<=BW$16,BV$16,0.05))))))) | CT16: =CS16*SUM(CQ16,CN16,CI16) | CV16: =IF(CL16<=BZ$6,BY$6,IF(CL16<=BZ$7,BY$7,IF(CL16<=BZ$8,BY$8,IF(CL16<=BZ$9,BY$9,IF(CL16<=BZ$14,BY$14,IF(CL16<=BZ$15,BY$15,IF(CL16<=BZ$16,BY$16,0.05))))))) | CW16: =CV16*CL16 | CY16: =0.07*SUM(CI16,CN16,CQ16,CT16,CW16) | DA16: =SUM(CY16,CW16,CT16,CQ16,CN16,CI16) | DB16: =SUM(CW16,CT16,CQ16,CN16) | DC16: =DB16/DA16
A17: ** USG ** | F17: Yield/FT | G17: =G15/G16 | O17: =SUM(P17:R17) | S17: =((P17+Q17+R17)/F22)*H33 | AM17: 8000 | AP17: =AM17 | AS17: =AM17+AP17 | AV17: =AS17 | AW17: =IF(AM17<=#REF!,#REF!,IF(AM17<=#REF!,#REF!,IF(AM17<=#REF!,#REF!,IF(AM17<=#REF!,#REF!,IF(AM17<=#REF!,#REF!,IF(AM17<=#REF!,#REF!,IF(AM17<=#REF!,#REF!,0.05))))))) | AX17: =AW17*AM17 | AZ17: =IF(AP17<=#REF!,#REF!,IF(AP17<=#REF!,#REF!,IF(AP17<=#REF!,#REF!,IF(AP17<=#REF!,#REF!,IF(AP17<=#REF!,#REF!,IF(AP17<=#REF!,#REF!,IF(AP17<=#REF!,#REF!,0.05))))))) | BA17: =AZ17*AP17 | BC17: =IF(AS17<=#REF!,#REF!,IF(AS17<=#REF!,#REF!,IF(AS17<=#REF!,#REF!,IF(AS17<=#REF!,#REF!,IF(AS17<=#REF!,#REF!,IF(AS17<=#REF!,#REF!,IF(AS17<=#REF!,#REF!,0.05))))))) | BD17: =BC17*SUM(BA17,AX17,AS17) | BF17: =IF(AV17<=#REF!,#REF!,IF(AV17<=#REF!,#REF!,IF(AV17<=#REF!,#REF!,IF(AV17<=#REF!,#REF!,IF(AV17<=#REF!,#REF!,IF(AV17<=#REF!,#REF!,IF(AV17<=#REF!,#REF!,0.05))))))) | BG17: =BF17*AV17 | BI17: =0.07*SUM(AS17,AX17,BA17,BD17,BG17) | BK17: =SUM(BI17,BG17,BD17,BA17,AX17,AS17) | BL17: =SUM(BG17,BD17,BA17,AX17) | BM17: =BL17/BK17 | CC17: 8000 | CF17: =CC17 | CI17: =CC17+CF17 | CL17: =CI17 | CM17: =IF(CC17<=BQ$6,BP$6,IF(CC17<=BQ$7,BP$7,IF(CC17<=BQ$8,BP$8,IF(CC17<=BQ$9,BP$9,IF(CC17<=BQ$14,BP$14,IF(CC17<=BQ$15,BP$15,IF(CC17<=BQ$16,BP$16,0.05))))))) | CN17: =CM17*CC17 | CP17: =IF(CF17<=BT$6,BS$6,IF(CF17<=BT$7,BS$7,IF(CF17<=BT$8,BS$8,IF(CF17<=BT$9,BS$9,IF(CF17<=BT$14,BS$14,IF(CF17<=BT$15,BS$15,IF(CF17<=BT$16,BS$16,0.05))))))) | CQ17: =CP17*CF17 | CS17: =IF(CI17<=BW$6,BV$6,IF(CI17<=BW$7,BV$7,IF(CI17<=BW$8,BV$8,IF(CI17<=BW$9,BV$9,IF(CI17<=BW$14,BV$14,IF(CI17<=BW$15,BV$15,IF(CI17<=BW$16,BV$16,0.05))))))) | CT17: =CS17*SUM(CQ17,CN17,CI17) | CV17: =IF(CL17<=BZ$6,BY$6,IF(CL17<=BZ$7,BY$7,IF(CL17<=BZ$8,BY$8,IF(CL17<=BZ$9,BY$9,IF(CL17<=BZ$14,BY$14,IF(CL17<=BZ$15,BY$15,IF(CL17<=BZ$16,BY$16,0.05))))))) | CW17: =CV17*CL17 | CY17: =0.07*SUM(CI17,CN17,CQ17,CT17,CW17) | DA17: =SUM(CY17,CW17,CT17,CQ17,CN17,CI17) | DB17: =SUM(CW17,CT17,CQ17,CN17) | DC17: =DB17/DA17
A18: Total Base Bid: | B18: =E87 | D18: $ / SF: | E18: =C87 | F18: Gyp Waste | G18: 0.03 | H18: *Adjust these if needed | O18: =SUM(P18:R18) | S18: =((P18+Q18+R18)/F22)*H33 | AM18: 9000 | AP18: =AM18 | AS18: =AM18+AP18 | AV18: =AS18 | AW18: =IF(AM18<=#REF!,#REF!,IF(AM18<=#REF!,#REF!,IF(AM18<=#REF!,#REF!,IF(AM18<=#REF!,#REF!,IF(AM18<=#REF!,#REF!,IF(AM18<=#REF!,#REF!,IF(AM18<=#REF!,#REF!,0.05))))))) | AX18: =AW18*AM18 | AZ18: =IF(AP18<=#REF!,#REF!,IF(AP18<=#REF!,#REF!,IF(AP18<=#REF!,#REF!,IF(AP18<=#REF!,#REF!,IF(AP18<=#REF!,#REF!,IF(AP18<=#REF!,#REF!,IF(AP18<=#REF!,#REF!,0.05))))))) | BA18: =AZ18*AP18 | BC18: =IF(AS18<=#REF!,#REF!,IF(AS18<=#REF!,#REF!,IF(AS18<=#REF!,#REF!,IF(AS18<=#REF!,#REF!,IF(AS18<=#REF!,#REF!,IF(AS18<=#REF!,#REF!,IF(AS18<=#REF!,#REF!,0.05))))))) | BD18: =BC18*SUM(BA18,AX18,AS18) | BF18: =IF(AV18<=#REF!,#REF!,IF(AV18<=#REF!,#REF!,IF(AV18<=#REF!,#REF!,IF(AV18<=#REF!,#REF!,IF(AV18<=#REF!,#REF!,IF(AV18<=#REF!,#REF!,IF(AV18<=#REF!,#REF!,0.05))))))) | BG18: =BF18*AV18 | BI18: =0.07*SUM(AS18,AX18,BA18,BD18,BG18) | BK18: =SUM(BI18,BG18,BD18,BA18,AX18,AS18) | BL18: =SUM(BG18,BD18,BA18,AX18) | BM18: =BL18/BK18 | CC18: 9000 | CF18: =CC18 | CI18: =CC18+CF18 | CL18: =CI18 | CM18: =IF(CC18<=BQ$6,BP$6,IF(CC18<=BQ$7,BP$7,IF(CC18<=BQ$8,BP$8,IF(CC18<=BQ$9,BP$9,IF(CC18<=BQ$14,BP$14,IF(CC18<=BQ$15,BP$15,IF(CC18<=BQ$16,BP$16,0.05))))))) | CN18: =CM18*CC18 | CP18: =IF(CF18<=BT$6,BS$6,IF(CF18<=BT$7,BS$7,IF(CF18<=BT$8,BS$8,IF(CF18<=BT$9,BS$9,IF(CF18<=BT$14,BS$14,IF(CF18<=BT$15,BS$15,IF(CF18<=BT$16,BS$16,0.05))))))) | CQ18: =CP18*CF18 | CS18: =IF(CI18<=BW$6,BV$6,IF(CI18<=BW$7,BV$7,IF(CI18<=BW$8,BV$8,IF(CI18<=BW$9,BV$9,IF(CI18<=BW$14,BV$14,IF(CI18<=BW$15,BV$15,IF(CI18<=BW$16,BV$16,0.05))))))) | CT18: =CS18*SUM(CQ18,CN18,CI18) | CV18: =IF(CL18<=BZ$6,BY$6,IF(CL18<=BZ$7,BY$7,IF(CL18<=BZ$8,BY$8,IF(CL18<=BZ$9,BY$9,IF(CL18<=BZ$14,BY$14,IF(CL18<=BZ$15,BY$15,IF(CL18<=BZ$16,BY$16,0.05))))))) | CW18: =CV18*CL18 | CY18: =0.07*SUM(CI18,CN18,CQ18,CT18,CW18) | DA18: =SUM(CY18,CW18,CT18,CQ18,CN18,CI18) | DB18: =SUM(CW18,CT18,CQ18,CN18) | DC18: =DB18/DA18
A19: MATERIAL - | B19: Quantity | C19: Units | D19: Cost/Unit | E19: Subtotal | F19: Sand Waste | G19: 0.1 | H19: for large bids | O19: =SUM(P19:R19) | S19: =((P19+Q19+R19)/F22)*H33 | AM19: 10000 | AP19: =AM19 | AS19: =AM19+AP19 | AV19: =AS19 | AW19: =IF(AM19<=#REF!,#REF!,IF(AM19<=#REF!,#REF!,IF(AM19<=#REF!,#REF!,IF(AM19<=#REF!,#REF!,IF(AM19<=#REF!,#REF!,IF(AM19<=#REF!,#REF!,IF(AM19<=#REF!,#REF!,0.05))))))) | AX19: =AW19*AM19 | AZ19: =IF(AP19<=#REF!,#REF!,IF(AP19<=#REF!,#REF!,IF(AP19<=#REF!,#REF!,IF(AP19<=#REF!,#REF!,IF(AP19<=#REF!,#REF!,IF(AP19<=#REF!,#REF!,IF(AP19<=#REF!,#REF!,0.05))))))) | BA19: =AZ19*AP19 | BC19: =IF(AS19<=#REF!,#REF!,IF(AS19<=#REF!,#REF!,IF(AS19<=#REF!,#REF!,IF(AS19<=#REF!,#REF!,IF(AS19<=#REF!,#REF!,IF(AS19<=#REF!,#REF!,IF(AS19<=#REF!,#REF!,0.05))))))) | BD19: =BC19*SUM(BA19,AX19,AS19) | BF19: =IF(AV19<=#REF!,#REF!,IF(AV19<=#REF!,#REF!,IF(AV19<=#REF!,#REF!,IF(AV19<=#REF!,#REF!,IF(AV19<=#REF!,#REF!,IF(AV19<=#REF!,#REF!,IF(AV19<=#REF!,#REF!,0.05))))))) | BG19: =BF19*AV19 | BI19: =0.07*SUM(AS19,AX19,BA19,BD19,BG19) | BK19: =SUM(BI19,BG19,BD19,BA19,AX19,AS19) | BL19: =SUM(BG19,BD19,BA19,AX19) | BM19: =BL19/BK19 | CC19: 10000 | CF19: =CC19 | CI19: =CC19+CF19 | CL19: =CI19 | CM19: =IF(CC19<=BQ$6,BP$6,IF(CC19<=BQ$7,BP$7,IF(CC19<=BQ$8,BP$8,IF(CC19<=BQ$9,BP$9,IF(CC19<=BQ$14,BP$14,IF(CC19<=BQ$15,BP$15,IF(CC19<=BQ$16,BP$16,0.05))))))) | CN19: =CM19*CC19 | CP19: =IF(CF19<=BT$6,BS$6,IF(CF19<=BT$7,BS$7,IF(CF19<=BT$8,BS$8,IF(CF19<=BT$9,BS$9,IF(CF19<=BT$14,BS$14,IF(CF19<=BT$15,BS$15,IF(CF19<=BT$16,BS$16,0.05))))))) | CQ19: =CP19*CF19 | CS19: =IF(CI19<=BW$6,BV$6,IF(CI19<=BW$7,BV$7,IF(CI19<=BW$8,BV$8,IF(CI19<=BW$9,BV$9,IF(CI19<=BW$14,BV$14,IF(CI19<=BW$15,BV$15,IF(CI19<=BW$16,BV$16,0.05))))))) | CT19: =CS19*SUM(CQ19,CN19,CI19) | CV19: =IF(CL19<=BZ$6,BY$6,IF(CL19<=BZ$7,BY$7,IF(CL19<=BZ$8,BY$8,IF(CL19<=BZ$9,BY$9,IF(CL19<=BZ$14,BY$14,IF(CL19<=BZ$15,BY$15,IF(CL19<=BZ$16,BY$16,0.05))))))) | CW19: =CV19*CL19 | CY19: =0.07*SUM(CI19,CN19,CQ19,CT19,CW19) | DA19: =SUM(CY19,CW19,CT19,CQ19,CN19,CI19) | DB19: =SUM(CW19,CT19,CQ19,CN19) | DC19: =DB19/DA19
E20: =B20*D20 | F20: Sound Mat Waste | G20: 0.04 | O20: =SUM(P20:R20) | S20: =((P20+Q20+R20)/F22)*H33 | AM20: 11000 | AP20: =AM20 | AS20: =AM20+AP20 | AV20: =AS20 | AW20: =IF(AM20<=#REF!,#REF!,IF(AM20<=#REF!,#REF!,IF(AM20<=#REF!,#REF!,IF(AM20<=#REF!,#REF!,IF(AM20<=#REF!,#REF!,IF(AM20<=#REF!,#REF!,IF(AM20<=#REF!,#REF!,0.05))))))) | AX20: =AW20*AM20 | AZ20: =IF(AP20<=#REF!,#REF!,IF(AP20<=#REF!,#REF!,IF(AP20<=#REF!,#REF!,IF(AP20<=#REF!,#REF!,IF(AP20<=#REF!,#REF!,IF(AP20<=#REF!,#REF!,IF(AP20<=#REF!,#REF!,0.05))))))) | BA20: =AZ20*AP20 | BC20: =IF(AS20<=#REF!,#REF!,IF(AS20<=#REF!,#REF!,IF(AS20<=#REF!,#REF!,IF(AS20<=#REF!,#REF!,IF(AS20<=#REF!,#REF!,IF(AS20<=#REF!,#REF!,IF(AS20<=#REF!,#REF!,0.05))))))) | BD20: =BC20*SUM(BA20,AX20,AS20) | BF20: =IF(AV20<=#REF!,#REF!,IF(AV20<=#REF!,#REF!,IF(AV20<=#REF!,#REF!,IF(AV20<=#REF!,#REF!,IF(AV20<=#REF!,#REF!,IF(AV20<=#REF!,#REF!,IF(AV20<=#REF!,#REF!,0.05))))))) | BG20: =BF20*AV20 | BI20: =0.07*SUM(AS20,AX20,BA20,BD20,BG20) | BK20: =SUM(BI20,BG20,BD20,BA20,AX20,AS20) | BL20: =SUM(BG20,BD20,BA20,AX20) | BM20: =BL20/BK20 | CC20: 11000 | CF20: =CC20 | CI20: =CC20+CF20 | CL20: =CI20 | CM20: =IF(CC20<=BQ$6,BP$6,IF(CC20<=BQ$7,BP$7,IF(CC20<=BQ$8,BP$8,IF(CC20<=BQ$9,BP$9,IF(CC20<=BQ$14,BP$14,IF(CC20<=BQ$15,BP$15,IF(CC20<=BQ$16,BP$16,0.05))))))) | CN20: =CM20*CC20 | CP20: =IF(CF20<=BT$6,BS$6,IF(CF20<=BT$7,BS$7,IF(CF20<=BT$8,BS$8,IF(CF20<=BT$9,BS$9,IF(CF20<=BT$14,BS$14,IF(CF20<=BT$15,BS$15,IF(CF20<=BT$16,BS$16,0.05))))))) | CQ20: =CP20*CF20 | CS20: =IF(CI20<=BW$6,BV$6,IF(CI20<=BW$7,BV$7,IF(CI20<=BW$8,BV$8,IF(CI20<=BW$9,BV$9,IF(CI20<=BW$14,BV$14,IF(CI20<=BW$15,BV$15,IF(CI20<=BW$16,BV$16,0.05))))))) | CT20: =CS20*SUM(CQ20,CN20,CI20) | CV20: =IF(CL20<=BZ$6,BY$6,IF(CL20<=BZ$7,BY$7,IF(CL20<=BZ$8,BY$8,IF(CL20<=BZ$9,BY$9,IF(CL20<=BZ$14,BY$14,IF(CL20<=BZ$15,BY$15,IF(CL20<=BZ$16,BY$16,0.05))))))) | CW20: =CV20*CL20 | CY20: =0.07*SUM(CI20,CN20,CQ20,CT20,CW20) | DA20: =SUM(CY20,CW20,CT20,CQ20,CN20,CI20) | DB20: =SUM(CW20,CT20,CQ20,CN20) | DC20: =DB20/DA20
A21: USG Levelrock | E21: =B21*D21 | O21: =SUM(P21:R21) | S21: =((P21+Q21+R21)/F22)*H33 | AM21: 12000 | AP21: =AM21 | AS21: =AM21+AP21 | AV21: =AS21 | AW21: =IF(AM21<=#REF!,#REF!,IF(AM21<=#REF!,#REF!,IF(AM21<=#REF!,#REF!,IF(AM21<=#REF!,#REF!,IF(AM21<=#REF!,#REF!,IF(AM21<=#REF!,#REF!,IF(AM21<=#REF!,#REF!,0.05))))))) | AX21: =AW21*AM21 | AZ21: =IF(AP21<=#REF!,#REF!,IF(AP21<=#REF!,#REF!,IF(AP21<=#REF!,#REF!,IF(AP21<=#REF!,#REF!,IF(AP21<=#REF!,#REF!,IF(AP21<=#REF!,#REF!,IF(AP21<=#REF!,#REF!,0.05))))))) | BA21: =AZ21*AP21 | BC21: =IF(AS21<=#REF!,#REF!,IF(AS21<=#REF!,#REF!,IF(AS21<=#REF!,#REF!,IF(AS21<=#REF!,#REF!,IF(AS21<=#REF!,#REF!,IF(AS21<=#REF!,#REF!,IF(AS21<=#REF!,#REF!,0.05))))))) | BD21: =BC21*SUM(BA21,AX21,AS21) | BF21: =IF(AV21<=#REF!,#REF!,IF(AV21<=#REF!,#REF!,IF(AV21<=#REF!,#REF!,IF(AV21<=#REF!,#REF!,IF(AV21<=#REF!,#REF!,IF(AV21<=#REF!,#REF!,IF(AV21<=#REF!,#REF!,0.05))))))) | BG21: =BF21*AV21 | BI21: =0.07*SUM(AS21,AX21,BA21,BD21,BG21) | BK21: =SUM(BI21,BG21,BD21,BA21,AX21,AS21) | BL21: =SUM(BG21,BD21,BA21,AX21) | BM21: =BL21/BK21 | CC21: 12000 | CF21: =CC21 | CI21: =CC21+CF21 | CL21: =CI21 | CM21: =IF(CC21<=BQ$6,BP$6,IF(CC21<=BQ$7,BP$7,IF(CC21<=BQ$8,BP$8,IF(CC21<=BQ$9,BP$9,IF(CC21<=BQ$14,BP$14,IF(CC21<=BQ$15,BP$15,IF(CC21<=BQ$16,BP$16,0.05))))))) | CN21: =CM21*CC21 | CP21: =IF(CF21<=BT$6,BS$6,IF(CF21<=BT$7,BS$7,IF(CF21<=BT$8,BS$8,IF(CF21<=BT$9,BS$9,IF(CF21<=BT$14,BS$14,IF(CF21<=BT$15,BS$15,IF(CF21<=BT$16,BS$16,0.05))))))) | CQ21: =CP21*CF21 | CS21: =IF(CI21<=BW$6,BV$6,IF(CI21<=BW$7,BV$7,IF(CI21<=BW$8,BV$8,IF(CI21<=BW$9,BV$9,IF(CI21<=BW$14,BV$14,IF(CI21<=BW$15,BV$15,IF(CI21<=BW$16,BV$16,0.05))))))) | CT21: =CS21*SUM(CQ21,CN21,CI21) | CV21: =IF(CL21<=BZ$6,BY$6,IF(CL21<=BZ$7,BY$7,IF(CL21<=BZ$8,BY$8,IF(CL21<=BZ$9,BY$9,IF(CL21<=BZ$14,BY$14,IF(CL21<=BZ$15,BY$15,IF(CL21<=BZ$16,BY$16,0.05))))))) | CW21: =CV21*CL21 | CY21: =0.07*SUM(CI21,CN21,CQ21,CT21,CW21) | DA21: =SUM(CY21,CW21,CT21,CQ21,CN21,CI21) | DB21: =SUM(CW21,CT21,CQ21,CN21) | DC21: =DB21/DA21
A22: MATERIAL - Gypsum Underlayments | E22: =B22*D22 | F22: =SUM(F23:F25) | G22: SF Total | H22: Ave Gyp Thickness | I22: 1/8's Req at Thickness | J22: Yield/FT | K22: 1.8 = 2500 psi | L22: 1.4 = 3000 psi | O22: =SUM(P22:R22) | S22: =((P22+Q22+R22)/F22)*H33 | AM22: 13000 | AP22: =AM22 | AS22: =AM22+AP22 | AV22: =AS22 | AW22: =IF(AM22<=#REF!,#REF!,IF(AM22<=#REF!,#REF!,IF(AM22<=#REF!,#REF!,IF(AM22<=#REF!,#REF!,IF(AM22<=#REF!,#REF!,IF(AM22<=#REF!,#REF!,IF(AM22<=#REF!,#REF!,0.05))))))) | AX22: =AW22*AM22 | AZ22: =IF(AP22<=#REF!,#REF!,IF(AP22<=#REF!,#REF!,IF(AP22<=#REF!,#REF!,IF(AP22<=#REF!,#REF!,IF(AP22<=#REF!,#REF!,IF(AP22<=#REF!,#REF!,IF(AP22<=#REF!,#REF!,0.05))))))) | BA22: =AZ22*AP22 | BC22: =IF(AS22<=#REF!,#REF!,IF(AS22<=#REF!,#REF!,IF(AS22<=#REF!,#REF!,IF(AS22<=#REF!,#REF!,IF(AS22<=#REF!,#REF!,IF(AS22<=#REF!,#REF!,IF(AS22<=#REF!,#REF!,0.05))))))) | BD22: =BC22*SUM(BA22,AX22,AS22) | BF22: =IF(AV22<=#REF!,#REF!,IF(AV22<=#REF!,#REF!,IF(AV22<=#REF!,#REF!,IF(AV22<=#REF!,#REF!,IF(AV22<=#REF!,#REF!,IF(AV22<=#REF!,#REF!,IF(AV22<=#REF!,#REF!,0.05))))))) | BG22: =BF22*AV22 | BI22: =0.07*SUM(AS22,AX22,BA22,BD22,BG22) | BK22: =SUM(BI22,BG22,BD22,BA22,AX22,AS22) | BL22: =SUM(BG22,BD22,BA22,AX22) | BM22: =BL22/BK22 | CC22: 13000 | CF22: =CC22 | CI22: =CC22+CF22 | CL22: =CI22 | CM22: =IF(CC22<=BQ$6,BP$6,IF(CC22<=BQ$7,BP$7,IF(CC22<=BQ$8,BP$8,IF(CC22<=BQ$9,BP$9,IF(CC22<=BQ$14,BP$14,IF(CC22<=BQ$15,BP$15,IF(CC22<=BQ$16,BP$16,0.05))))))) | CN22: =CM22*CC22 | CP22: =IF(CF22<=BT$6,BS$6,IF(CF22<=BT$7,BS$7,IF(CF22<=BT$8,BS$8,IF(CF22<=BT$9,BS$9,IF(CF22<=BT$14,BS$14,IF(CF22<=BT$15,BS$15,IF(CF22<=BT$16,BS$16,0.05))))))) | CQ22: =CP22*CF22 | CS22: =IF(CI22<=BW$6,BV$6,IF(CI22<=BW$7,BV$7,IF(CI22<=BW$8,BV$8,IF(CI22<=BW$9,BV$9,IF(CI22<=BW$14,BV$14,IF(CI22<=BW$15,BV$15,IF(CI22<=BW$16,BV$16,0.05))))))) | CT22: =CS22*SUM(CQ22,CN22,CI22) | CV22: =IF(CL22<=BZ$6,BY$6,IF(CL22<=BZ$7,BY$7,IF(CL22<=BZ$8,BY$8,IF(CL22<=BZ$9,BY$9,IF(CL22<=BZ$14,BY$14,IF(CL22<=BZ$15,BY$15,IF(CL22<=BZ$16,BY$16,0.05))))))) | CW22: =CV22*CL22 | CY22: =0.07*SUM(CI22,CN22,CQ22,CT22,CW22) | DA22: =SUM(CY22,CW22,CT22,CQ22,CN22,CI22) | DB22: =SUM(CW22,CT22,CQ22,CN22) | DC22: =DB22/DA22
A23: Levelrock 2500 (SSA) | B23: =(F23/J23)*(1+G18) | C23: bags w/ waste | D23: 14.08 | E23: =B23*D23 | F23: =G9 | G23: SF - Soft Surfaces | H23: =G10 | I23: =H23*8 | J23: =IF(G11=P52,R52,IF(G11=P54,R54)) | K23: 40 | L23: 34 | O23: =SUM(P23:R23) | S23: =((P23+Q23+R23)/F22)*H33 | AM23: 14000 | AP23: =AM23 | AS23: =AM23+AP23 | AV23: =AS23 | AW23: =IF(AM23<=#REF!,#REF!,IF(AM23<=#REF!,#REF!,IF(AM23<=#REF!,#REF!,IF(AM23<=#REF!,#REF!,IF(AM23<=#REF!,#REF!,IF(AM23<=#REF!,#REF!,IF(AM23<=#REF!,#REF!,0.05))))))) | AX23: =AW23*AM23 | AZ23: =IF(AP23<=#REF!,#REF!,IF(AP23<=#REF!,#REF!,IF(AP23<=#REF!,#REF!,IF(AP23<=#REF!,#REF!,IF(AP23<=#REF!,#REF!,IF(AP23<=#REF!,#REF!,IF(AP23<=#REF!,#REF!,0.05))))))) | BA23: =AZ23*AP23 | BC23: =IF(AS23<=#REF!,#REF!,IF(AS23<=#REF!,#REF!,IF(AS23<=#REF!,#REF!,IF(AS23<=#REF!,#REF!,IF(AS23<=#REF!,#REF!,IF(AS23<=#REF!,#REF!,IF(AS23<=#REF!,#REF!,0.05))))))) | BD23: =BC23*SUM(BA23,AX23,AS23) | BF23: =IF(AV23<=#REF!,#REF!,IF(AV23<=#REF!,#REF!,IF(AV23<=#REF!,#REF!,IF(AV23<=#REF!,#REF!,IF(AV23<=#REF!,#REF!,IF(AV23<=#REF!,#REF!,IF(AV23<=#REF!,#REF!,0.05))))))) | BG23: =BF23*AV23 | BI23: =0.07*SUM(AS23,AX23,BA23,BD23,BG23) | BK23: =SUM(BI23,BG23,BD23,BA23,AX23,AS23) | BL23: =SUM(BG23,BD23,BA23,AX23) | BM23: =BL23/BK23 | CC23: 14000 | CF23: =CC23 | CI23: =CC23+CF23 | CL23: =CI23 | CM23: =IF(CC23<=BQ$6,BP$6,IF(CC23<=BQ$7,BP$7,IF(CC23<=BQ$8,BP$8,IF(CC23<=BQ$9,BP$9,IF(CC23<=BQ$14,BP$14,IF(CC23<=BQ$15,BP$15,IF(CC23<=BQ$16,BP$16,0.05))))))) | CN23: =CM23*CC23 | CP23: =IF(CF23<=BT$6,BS$6,IF(CF23<=BT$7,BS$7,IF(CF23<=BT$8,BS$8,IF(CF23<=BT$9,BS$9,IF(CF23<=BT$14,BS$14,IF(CF23<=BT$15,BS$15,IF(CF23<=BT$16,BS$16,0.05))))))) | CQ23: =CP23*CF23 | CS23: =IF(CI23<=BW$6,BV$6,IF(CI23<=BW$7,BV$7,IF(CI23<=BW$8,BV$8,IF(CI23<=BW$9,BV$9,IF(CI23<=BW$14,BV$14,IF(CI23<=BW$15,BV$15,IF(CI23<=BW$16,BV$16,0.05))))))) | CT23: =CS23*SUM(CQ23,CN23,CI23) | CV23: =IF(CL23<=BZ$6,BY$6,IF(CL23<=BZ$7,BY$7,IF(CL23<=BZ$8,BY$8,IF(CL23<=BZ$9,BY$9,IF(CL23<=BZ$14,BY$14,IF(CL23<=BZ$15,BY$15,IF(CL23<=BZ$16,BY$16,0.05))))))) | CW23: =CV23*CL23 | CY23: =0.07*SUM(CI23,CN23,CQ23,CT23,CW23) | DA23: =SUM(CY23,CW23,CT23,CQ23,CN23,CI23) | DB23: =SUM(CW23,CT23,CQ23,CN23) | DC23: =DB23/DA23
A24: Levelrock 2500 (HSA) | B24: =(F24/J24)*(1+G18) | C24: =C23 | D24: =D23 | E24: =B24*D24 | F24: =I9 | G24: SF - Hard Surfaces | H24: =I10 | I24: =H24*8 | J24: =IF(I11=P52,S52,IF(I11=P54,S54)) | K24: 42 | L24: 36 | O24: =SUM(P24:R24) | S24: =((P24+Q24+R24)/F22)*H33 | AM24: 15000 | AP24: =AM24 | AS24: =AM24+AP24 | AV24: =AS24 | AW24: =IF(AM24<=#REF!,#REF!,IF(AM24<=#REF!,#REF!,IF(AM24<=#REF!,#REF!,IF(AM24<=#REF!,#REF!,IF(AM24<=#REF!,#REF!,IF(AM24<=#REF!,#REF!,IF(AM24<=#REF!,#REF!,0.05))))))) | AX24: =AW24*AM24 | AZ24: =IF(AP24<=#REF!,#REF!,IF(AP24<=#REF!,#REF!,IF(AP24<=#REF!,#REF!,IF(AP24<=#REF!,#REF!,IF(AP24<=#REF!,#REF!,IF(AP24<=#REF!,#REF!,IF(AP24<=#REF!,#REF!,0.05))))))) | BA24: =AZ24*AP24 | BC24: =IF(AS24<=#REF!,#REF!,IF(AS24<=#REF!,#REF!,IF(AS24<=#REF!,#REF!,IF(AS24<=#REF!,#REF!,IF(AS24<=#REF!,#REF!,IF(AS24<=#REF!,#REF!,IF(AS24<=#REF!,#REF!,0.05))))))) | BD24: =BC24*SUM(BA24,AX24,AS24) | BF24: =IF(AV24<=#REF!,#REF!,IF(AV24<=#REF!,#REF!,IF(AV24<=#REF!,#REF!,IF(AV24<=#REF!,#REF!,IF(AV24<=#REF!,#REF!,IF(AV24<=#REF!,#REF!,IF(AV24<=#REF!,#REF!,0.05))))))) | BG24: =BF24*AV24 | BI24: =0.07*SUM(AS24,AX24,BA24,BD24,BG24) | BK24: =SUM(BI24,BG24,BD24,BA24,AX24,AS24) | BL24: =SUM(BG24,BD24,BA24,AX24) | BM24: =BL24/BK24 | CC24: 15000 | CF24: =CC24 | CI24: =CC24+CF24 | CL24: =CI24 | CM24: =IF(CC24<=BQ$6,BP$6,IF(CC24<=BQ$7,BP$7,IF(CC24<=BQ$8,BP$8,IF(CC24<=BQ$9,BP$9,IF(CC24<=BQ$14,BP$14,IF(CC24<=BQ$15,BP$15,IF(CC24<=BQ$16,BP$16,0.05))))))) | CN24: =CM24*CC24 | CP24: =IF(CF24<=BT$6,BS$6,IF(CF24<=BT$7,BS$7,IF(CF24<=BT$8,BS$8,IF(CF24<=BT$9,BS$9,IF(CF24<=BT$14,BS$14,IF(CF24<=BT$15,BS$15,IF(CF24<=BT$16,BS$16,0.05))))))) | CQ24: =CP24*CF24 | CS24: =IF(CI24<=BW$6,BV$6,IF(CI24<=BW$7,BV$7,IF(CI24<=BW$8,BV$8,IF(CI24<=BW$9,BV$9,IF(CI24<=BW$14,BV$14,IF(CI24<=BW$15,BV$15,IF(CI24<=BW$16,BV$16,0.05))))))) | CT24: =CS24*SUM(CQ24,CN24,CI24) | CV24: =IF(CL24<=BZ$6,BY$6,IF(CL24<=BZ$7,BY$7,IF(CL24<=BZ$8,BY$8,IF(CL24<=BZ$9,BY$9,IF(CL24<=BZ$14,BY$14,IF(CL24<=BZ$15,BY$15,IF(CL24<=BZ$16,BY$16,0.05))))))) | CW24: =CV24*CL24 | CY24: =0.07*SUM(CI24,CN24,CQ24,CT24,CW24) | DA24: =SUM(CY24,CW24,CT24,CQ24,CN24,CI24) | DB24: =SUM(CW24,CT24,CQ24,CN24) | DC24: =DB24/DA24
A25: Levelrock 2500 (Corr) | B25: =(F25/J25)*(1+G18) | C25: =C23 | D25: =D23 | E25: =B25*D25 | F25: =K9 | G25: SF - Corridors | H25: =K10 | I25: =H25*8 | J25: =IF(K11=P52,T52,IF(K11=P54,T54)) | K25: 40 | L25: 34 | O25: =SUM(P25:R25) | S25: =((P25+Q25+R25)/F22)*H33 | AM25: 16000 | AP25: =AM25 | AS25: =AM25+AP25 | AV25: =AS25 | AW25: =IF(AM25<=#REF!,#REF!,IF(AM25<=#REF!,#REF!,IF(AM25<=#REF!,#REF!,IF(AM25<=#REF!,#REF!,IF(AM25<=#REF!,#REF!,IF(AM25<=#REF!,#REF!,IF(AM25<=#REF!,#REF!,0.05))))))) | AX25: =AW25*AM25 | AZ25: =IF(AP25<=#REF!,#REF!,IF(AP25<=#REF!,#REF!,IF(AP25<=#REF!,#REF!,IF(AP25<=#REF!,#REF!,IF(AP25<=#REF!,#REF!,IF(AP25<=#REF!,#REF!,IF(AP25<=#REF!,#REF!,0.05))))))) | BA25: =AZ25*AP25 | BC25: =IF(AS25<=#REF!,#REF!,IF(AS25<=#REF!,#REF!,IF(AS25<=#REF!,#REF!,IF(AS25<=#REF!,#REF!,IF(AS25<=#REF!,#REF!,IF(AS25<=#REF!,#REF!,IF(AS25<=#REF!,#REF!,0.05))))))) | BD25: =BC25*SUM(BA25,AX25,AS25) | BF25: =IF(AV25<=#REF!,#REF!,IF(AV25<=#REF!,#REF!,IF(AV25<=#REF!,#REF!,IF(AV25<=#REF!,#REF!,IF(AV25<=#REF!,#REF!,IF(AV25<=#REF!,#REF!,IF(AV25<=#REF!,#REF!,0.05))))))) | BG25: =BF25*AV25 | BI25: =0.07*SUM(AS25,AX25,BA25,BD25,BG25) | BK25: =SUM(BI25,BG25,BD25,BA25,AX25,AS25) | BL25: =SUM(BG25,BD25,BA25,AX25) | BM25: =BL25/BK25 | CC25: 16000 | CF25: =CC25 | CI25: =CC25+CF25 | CL25: =CI25 | CM25: =IF(CC25<=BQ$6,BP$6,IF(CC25<=BQ$7,BP$7,IF(CC25<=BQ$8,BP$8,IF(CC25<=BQ$9,BP$9,IF(CC25<=BQ$14,BP$14,IF(CC25<=BQ$15,BP$15,IF(CC25<=BQ$16,BP$16,0.05))))))) | CN25: =CM25*CC25 | CP25: =IF(CF25<=BT$6,BS$6,IF(CF25<=BT$7,BS$7,IF(CF25<=BT$8,BS$8,IF(CF25<=BT$9,BS$9,IF(CF25<=BT$14,BS$14,IF(CF25<=BT$15,BS$15,IF(CF25<=BT$16,BS$16,0.05))))))) | CQ25: =CP25*CF25 | CS25: =IF(CI25<=BW$6,BV$6,IF(CI25<=BW$7,BV$7,IF(CI25<=BW$8,BV$8,IF(CI25<=BW$9,BV$9,IF(CI25<=BW$14,BV$14,IF(CI25<=BW$15,BV$15,IF(CI25<=BW$16,BV$16,0.05))))))) | CT25: =CS25*SUM(CQ25,CN25,CI25) | CV25: =IF(CL25<=BZ$6,BY$6,IF(CL25<=BZ$7,BY$7,IF(CL25<=BZ$8,BY$8,IF(CL25<=BZ$9,BY$9,IF(CL25<=BZ$14,BY$14,IF(CL25<=BZ$15,BY$15,IF(CL25<=BZ$16,BY$16,0.05))))))) | CW25: =CV25*CL25 | CY25: =0.07*SUM(CI25,CN25,CQ25,CT25,CW25) | DA25: =SUM(CY25,CW25,CT25,CQ25,CN25,CI25) | DB25: =SUM(CW25,CT25,CQ25,CN25) | DC25: =DB25/DA25
A26: MATERIAL - Extras | K26: NO Mat = 42 | L26: NO Mat = 36 | O26: =SUM(P26:R26) | S26: =((P26+Q26+R26)/F22)*H33 | AM26: 17000 | AP26: =AM26 | AS26: =AM26+AP26 | AV26: =AS26 | AW26: =IF(AM26<=#REF!,#REF!,IF(AM26<=#REF!,#REF!,IF(AM26<=#REF!,#REF!,IF(AM26<=#REF!,#REF!,IF(AM26<=#REF!,#REF!,IF(AM26<=#REF!,#REF!,IF(AM26<=#REF!,#REF!,0.05))))))) | AX26: =AW26*AM26 | AZ26: =IF(AP26<=#REF!,#REF!,IF(AP26<=#REF!,#REF!,IF(AP26<=#REF!,#REF!,IF(AP26<=#REF!,#REF!,IF(AP26<=#REF!,#REF!,IF(AP26<=#REF!,#REF!,IF(AP26<=#REF!,#REF!,0.05))))))) | BA26: =AZ26*AP26 | BC26: =IF(AS26<=#REF!,#REF!,IF(AS26<=#REF!,#REF!,IF(AS26<=#REF!,#REF!,IF(AS26<=#REF!,#REF!,IF(AS26<=#REF!,#REF!,IF(AS26<=#REF!,#REF!,IF(AS26<=#REF!,#REF!,0.05))))))) | BD26: =BC26*SUM(BA26,AX26,AS26) | BF26: =IF(AV26<=#REF!,#REF!,IF(AV26<=#REF!,#REF!,IF(AV26<=#REF!,#REF!,IF(AV26<=#REF!,#REF!,IF(AV26<=#REF!,#REF!,IF(AV26<=#REF!,#REF!,IF(AV26<=#REF!,#REF!,0.05))))))) | BG26: =BF26*AV26 | BI26: =0.07*SUM(AS26,AX26,BA26,BD26,BG26) | BK26: =SUM(BI26,BG26,BD26,BA26,AX26,AS26) | BL26: =SUM(BG26,BD26,BA26,AX26) | BM26: =BL26/BK26 | CC26: 17000 | CF26: =CC26 | CI26: =CC26+CF26 | CL26: =CI26 | CM26: =IF(CC26<=BQ$6,BP$6,IF(CC26<=BQ$7,BP$7,IF(CC26<=BQ$8,BP$8,IF(CC26<=BQ$9,BP$9,IF(CC26<=BQ$14,BP$14,IF(CC26<=BQ$15,BP$15,IF(CC26<=BQ$16,BP$16,0.05))))))) | CN26: =CM26*CC26 | CP26: =IF(CF26<=BT$6,BS$6,IF(CF26<=BT$7,BS$7,IF(CF26<=BT$8,BS$8,IF(CF26<=BT$9,BS$9,IF(CF26<=BT$14,BS$14,IF(CF26<=BT$15,BS$15,IF(CF26<=BT$16,BS$16,0.05))))))) | CQ26: =CP26*CF26 | CS26: =IF(CI26<=BW$6,BV$6,IF(CI26<=BW$7,BV$7,IF(CI26<=BW$8,BV$8,IF(CI26<=BW$9,BV$9,IF(CI26<=BW$14,BV$14,IF(CI26<=BW$15,BV$15,IF(CI26<=BW$16,BV$16,0.05))))))) | CT26: =CS26*SUM(CQ26,CN26,CI26) | CV26: =IF(CL26<=BZ$6,BY$6,IF(CL26<=BZ$7,BY$7,IF(CL26<=BZ$8,BY$8,IF(CL26<=BZ$9,BY$9,IF(CL26<=BZ$14,BY$14,IF(CL26<=BZ$15,BY$15,IF(CL26<=BZ$16,BY$16,0.05))))))) | CW26: =CV26*CL26 | CY26: =0.07*SUM(CI26,CN26,CQ26,CT26,CW26) | DA26: =SUM(CY26,CW26,CT26,CQ26,CN26,CI26) | DB26: =SUM(CW26,CT26,CQ26,CN26) | DC26: =DB26/DA26
A27: USG Primer (53gal Drum) | B27: =(F23+F25)/1200 | C27: gallons | D27: =891/53 | E27: =B27*D27 | F27: *Sealer @ Soft Surfc & Corridors ONLY | G27: ($21.60 = $108 /5 gal -or- $16.81 = $891 /53 gal drum)-Aug2024 | O27: =SUM(P27:R27) | S27: =((P27+Q27+R27)/F22)*H33 | AM27: 18000 | AP27: =AM27 | AS27: =AM27+AP27 | AV27: =AS27 | AW27: =IF(AM27<=#REF!,#REF!,IF(AM27<=#REF!,#REF!,IF(AM27<=#REF!,#REF!,IF(AM27<=#REF!,#REF!,IF(AM27<=#REF!,#REF!,IF(AM27<=#REF!,#REF!,IF(AM27<=#REF!,#REF!,0.05))))))) | AX27: =AW27*AM27 | AZ27: =IF(AP27<=#REF!,#REF!,IF(AP27<=#REF!,#REF!,IF(AP27<=#REF!,#REF!,IF(AP27<=#REF!,#REF!,IF(AP27<=#REF!,#REF!,IF(AP27<=#REF!,#REF!,IF(AP27<=#REF!,#REF!,0.05))))))) | BA27: =AZ27*AP27 | BC27: =IF(AS27<=#REF!,#REF!,IF(AS27<=#REF!,#REF!,IF(AS27<=#REF!,#REF!,IF(AS27<=#REF!,#REF!,IF(AS27<=#REF!,#REF!,IF(AS27<=#REF!,#REF!,IF(AS27<=#REF!,#REF!,0.05))))))) | BD27: =BC27*SUM(BA27,AX27,AS27) | BF27: =IF(AV27<=#REF!,#REF!,IF(AV27<=#REF!,#REF!,IF(AV27<=#REF!,#REF!,IF(AV27<=#REF!,#REF!,IF(AV27<=#REF!,#REF!,IF(AV27<=#REF!,#REF!,IF(AV27<=#REF!,#REF!,0.05))))))) | BG27: =BF27*AV27 | BI27: =0.07*SUM(AS27,AX27,BA27,BD27,BG27) | BK27: =SUM(BI27,BG27,BD27,BA27,AX27,AS27) | BL27: =SUM(BG27,BD27,BA27,AX27) | BM27: =BL27/BK27 | CC27: 18000 | CF27: =CC27 | CI27: =CC27+CF27 | CL27: =CI27 | CM27: =IF(CC27<=BQ$6,BP$6,IF(CC27<=BQ$7,BP$7,IF(CC27<=BQ$8,BP$8,IF(CC27<=BQ$9,BP$9,IF(CC27<=BQ$14,BP$14,IF(CC27<=BQ$15,BP$15,IF(CC27<=BQ$16,BP$16,0.05))))))) | CN27: =CM27*CC27 | CP27: =IF(CF27<=BT$6,BS$6,IF(CF27<=BT$7,BS$7,IF(CF27<=BT$8,BS$8,IF(CF27<=BT$9,BS$9,IF(CF27<=BT$14,BS$14,IF(CF27<=BT$15,BS$15,IF(CF27<=BT$16,BS$16,0.05))))))) | CQ27: =CP27*CF27 | CS27: =IF(CI27<=BW$6,BV$6,IF(CI27<=BW$7,BV$7,IF(CI27<=BW$8,BV$8,IF(CI27<=BW$9,BV$9,IF(CI27<=BW$14,BV$14,IF(CI27<=BW$15,BV$15,IF(CI27<=BW$16,BV$16,0.05))))))) | CT27: =CS27*SUM(CQ27,CN27,CI27) | CV27: =IF(CL27<=BZ$6,BY$6,IF(CL27<=BZ$7,BY$7,IF(CL27<=BZ$8,BY$8,IF(CL27<=BZ$9,BY$9,IF(CL27<=BZ$14,BY$14,IF(CL27<=BZ$15,BY$15,IF(CL27<=BZ$16,BY$16,0.05))))))) | CW27: =CV27*CL27 | CY27: =0.07*SUM(CI27,CN27,CQ27,CT27,CW27) | DA27: =SUM(CY27,CW27,CT27,CQ27,CN27,CI27) | DB27: =SUM(CW27,CT27,CQ27,CN27) | DC27: =DB27/DA27
A28: ISO Strip 3" adhsv (roll) | B28: =IF(B14="Yes",((F23+F24+F25)/(1200*1.8)),(F24/(1200*1.8))) | C28: rolls | D28: 48.75 | E28: =B28*D28 | G28: (16 rolls /bag: $48.75 = $780 /16) = 450 LF /roll | N28: =SUM(P28:R28) | O28: =SUM(O3:O27) | P28: =SUM(P3:P27) | Q28: =SUM(Q3:Q27) | R28: =SUM(R3:R27) | S28: =SUM(S3:S27) | T28: =SUM(T3:T27) | U28: =SUM(U3:U27) | V28: =SUM(V3:V27) | ... X28: =SUM(X3:X27) | AM28: 19000 | AP28: =AM28 | AS28: =AM28+AP28 | AV28: =AS28 | AW28: =IF(AM28<=#REF!,#REF!,IF(AM28<=#REF!,#REF!,IF(AM28<=#REF!,#REF!,IF(AM28<=#REF!,#REF!,IF(AM28<=#REF!,#REF!,IF(AM28<=#REF!,#REF!,IF(AM28<=#REF!,#REF!,0.05))))))) | AX28: =AW28*AM28 | AZ28: =IF(AP28<=#REF!,#REF!,IF(AP28<=#REF!,#REF!,IF(AP28<=#REF!,#REF!,IF(AP28<=#REF!,#REF!,IF(AP28<=#REF!,#REF!,IF(AP28<=#REF!,#REF!,IF(AP28<=#REF!,#REF!,0.05))))))) | BA28: =AZ28*AP28 | BC28: =IF(AS28<=#REF!,#REF!,IF(AS28<=#REF!,#REF!,IF(AS28<=#REF!,#REF!,IF(AS28<=#REF!,#REF!,IF(AS28<=#REF!,#REF!,IF(AS28<=#REF!,#REF!,IF(AS28<=#REF!,#REF!,0.05))))))) | BD28: =BC28*SUM(BA28,AX28,AS28) | BF28: =IF(AV28<=#REF!,#REF!,IF(AV28<=#REF!,#REF!,IF(AV28<=#REF!,#REF!,IF(AV28<=#REF!,#REF!,IF(AV28<=#REF!,#REF!,IF(AV28<=#REF!,#REF!,IF(AV28<=#REF!,#REF!,0.05))))))) | BG28: =BF28*AV28 | BI28: =0.07*SUM(AS28,AX28,BA28,BD28,BG28) | BK28: =SUM(BI28,BG28,BD28,BA28,AX28,AS28) | BL28: =SUM(BG28,BD28,BA28,AX28) | BM28: =BL28/BK28 | CC28: 19000 | CF28: =CC28 | CI28: =CC28+CF28 | CL28: =CI28 | CM28: =IF(CC28<=BQ$6,BP$6,IF(CC28<=BQ$7,BP$7,IF(CC28<=BQ$8,BP$8,IF(CC28<=BQ$9,BP$9,IF(CC28<=BQ$14,BP$14,IF(CC28<=BQ$15,BP$15,IF(CC28<=BQ$16,BP$16,0.05))))))) | CN28: =CM28*CC28 | CP28: =IF(CF28<=BT$6,BS$6,IF(CF28<=BT$7,BS$7,IF(CF28<=BT$8,BS$8,IF(CF28<=BT$9,BS$9,IF(CF28<=BT$14,BS$14,IF(CF28<=BT$15,BS$15,IF(CF28<=BT$16,BS$16,0.05))))))) | CQ28: =CP28*CF28 | CS28: =IF(CI28<=BW$6,BV$6,IF(CI28<=BW$7,BV$7,IF(CI28<=BW$8,BV$8,IF(CI28<=BW$9,BV$9,IF(CI28<=BW$14,BV$14,IF(CI28<=BW$15,BV$15,IF(CI28<=BW$16,BV$16,0.05))))))) | CT28: =CS28*SUM(CQ28,CN28,CI28) | CV28: =IF(CL28<=BZ$6,BY$6,IF(CL28<=BZ$7,BY$7,IF(CL28<=BZ$8,BY$8,IF(CL28<=BZ$9,BY$9,IF(CL28<=BZ$14,BY$14,IF(CL28<=BZ$15,BY$15,IF(CL28<=BZ$16,BY$16,0.05))))))) | CW28: =CV28*CL28 | CY28: =0.07*SUM(CI28,CN28,CQ28,CT28,CW28) | DA28: =SUM(CY28,CW28,CT28,CQ28,CN28,CI28) | DB28: =SUM(CW28,CT28,CQ28,CN28) | DC28: =DB28/DA28
A29: Joint Tape (rolls) | B29: =F24/240 | C29: rolls | D29: 5.75 | E29: =B29*D29 | O29: Soft Surf + Corrs. | AY29: 20000 | BB29: =AY29 | BE29: =AY29+BB29 | BH29: =BE29 | BI29: =IF(AY29<=#REF!,#REF!,IF(AY29<=#REF!,#REF!,IF(AY29<=#REF!,#REF!,IF(AY29<=#REF!,#REF!,IF(AY29<=#REF!,#REF!,IF(AY29<=#REF!,#REF!,IF(AY29<=#REF!,#REF!,0.05))))))) | BJ29: =BI29*AY29 | BL29: =IF(BB29<=#REF!,#REF!,IF(BB29<=#REF!,#REF!,IF(BB29<=#REF!,#REF!,IF(BB29<=#REF!,#REF!,IF(BB29<=#REF!,#REF!,IF(BB29<=#REF!,#REF!,IF(BB29<=#REF!,#REF!,0.05))))))) | BM29: =BL29*BB29 | BO29: =IF(BE29<=#REF!,#REF!,IF(BE29<=#REF!,#REF!,IF(BE29<=#REF!,#REF!,IF(BE29<=#REF!,#REF!,IF(BE29<=#REF!,#REF!,IF(BE29<=#REF!,#REF!,IF(BE29<=#REF!,#REF!,0.05))))))) | BP29: =BO29*SUM(BM29,BJ29,BE29) | BR29: =IF(BH29<=#REF!,#REF!,IF(BH29<=#REF!,#REF!,IF(BH29<=#REF!,#REF!,IF(BH29<=#REF!,#REF!,IF(BH29<=#REF!,#REF!,IF(BH29<=#REF!,#REF!,IF(BH29<=#REF!,#REF!,0.05))))))) | BS29: =BR29*BH29 | BU29: =0.07*SUM(BE29,BJ29,BM29,BP29,BS29) | BW29: =SUM(BU29,BS29,BP29,BM29,BJ29,BE29) | BX29: =SUM(BS29,BP29,BM29,BJ29) | BY29: =BX29/BW29 | CO29: 20000 | CR29: =CO29 | CU29: =CO29+CR29 | CX29: =CU29 | CY29: =IF(CO29<=BQ$6,BP$6,IF(CO29<=BQ$7,BP$7,IF(CO29<=BQ$8,BP$8,IF(CO29<=BQ$9,BP$9,IF(CO29<=BQ$14,BP$14,IF(CO29<=BQ$15,BP$15,IF(CO29<=BQ$16,BP$16,0.05))))))) | CZ29: =CY29*CO29 | DB29: =IF(CR29<=BT$6,BS$6,IF(CR29<=BT$7,BS$7,IF(CR29<=BT$8,BS$8,IF(CR29<=BT$9,BS$9,IF(CR29<=BT$14,BS$14,IF(CR29<=BT$15,BS$15,IF(CR29<=BT$16,BS$16,0.05))))))) | DC29: =DB29*CR29 | DE29: =IF(CU29<=BW$6,BV$6,IF(CU29<=BW$7,BV$7,IF(CU29<=BW$8,BV$8,IF(CU29<=BW$9,BV$9,IF(CU29<=BW$14,BV$14,IF(CU29<=BW$15,BV$15,IF(CU29<=BW$16,BV$16,0.05))))))) | DF29: =DE29*SUM(DC29,CZ29,CU29) | DH29: =IF(CX29<=BZ$6,BY$6,IF(CX29<=BZ$7,BY$7,IF(CX29<=BZ$8,BY$8,IF(CX29<=BZ$9,BY$9,IF(CX29<=BZ$14,BY$14,IF(CX29<=BZ$15,BY$15,IF(CX29<=BZ$16,BY$16,0.05))))))) | DI29: =DH29*CX29 | DK29: =0.07*SUM(CU29,CZ29,DC29,DF29,DI29) | DM29: =SUM(DK29,DI29,DF29,DC29,CZ29,CU29) | DN29: =SUM(DI29,DF29,DC29,CZ29) | DO29: =DN29/DM29
E30: =B30*D30 | H30: =(F22/300)/0.1 | I30: Add for Sealer | J30: =(sf / 300) / 10% = Sealer *Material ONLY* | O30: =SUM(P28,R28) | P30: % Soft Surf | Q30: % Hard Surf / Mat | R30: % Corridors | AY30: 21000 | BB30: =AY30 | BE30: =AY30+BB30 | BH30: =BE30 | BI30: =IF(AY30<=#REF!,#REF!,IF(AY30<=#REF!,#REF!,IF(AY30<=#REF!,#REF!,IF(AY30<=#REF!,#REF!,IF(AY30<=#REF!,#REF!,IF(AY30<=#REF!,#REF!,IF(AY30<=#REF!,#REF!,0.05))))))) | BJ30: =BI30*AY30 | BL30: =IF(BB30<=#REF!,#REF!,IF(BB30<=#REF!,#REF!,IF(BB30<=#REF!,#REF!,IF(BB30<=#REF!,#REF!,IF(BB30<=#REF!,#REF!,IF(BB30<=#REF!,#REF!,IF(BB30<=#REF!,#REF!,0.05))))))) | BM30: =BL30*BB30 | BO30: =IF(BE30<=#REF!,#REF!,IF(BE30<=#REF!,#REF!,IF(BE30<=#REF!,#REF!,IF(BE30<=#REF!,#REF!,IF(BE30<=#REF!,#REF!,IF(BE30<=#REF!,#REF!,IF(BE30<=#REF!,#REF!,0.05))))))) | BP30: =BO30*SUM(BM30,BJ30,BE30) | BR30: =IF(BH30<=#REF!,#REF!,IF(BH30<=#REF!,#REF!,IF(BH30<=#REF!,#REF!,IF(BH30<=#REF!,#REF!,IF(BH30<=#REF!,#REF!,IF(BH30<=#REF!,#REF!,IF(BH30<=#REF!,#REF!,0.05))))))) | BS30: =BR30*BH30 | BU30: =0.07*SUM(BE30,BJ30,BM30,BP30,BS30) | BW30: =SUM(BU30,BS30,BP30,BM30,BJ30,BE30) | BX30: =SUM(BS30,BP30,BM30,BJ30) | BY30: =BX30/BW30 | CO30: 21000 | CR30: =CO30 | CU30: =CO30+CR30 | CX30: =CU30 | CY30: =IF(CO30<=BQ$6,BP$6,IF(CO30<=BQ$7,BP$7,IF(CO30<=BQ$8,BP$8,IF(CO30<=BQ$9,BP$9,IF(CO30<=BQ$14,BP$14,IF(CO30<=BQ$15,BP$15,IF(CO30<=BQ$16,BP$16,0.05))))))) | CZ30: =CY30*CO30 | DB30: =IF(CR30<=BT$6,BS$6,IF(CR30<=BT$7,BS$7,IF(CR30<=BT$8,BS$8,IF(CR30<=BT$9,BS$9,IF(CR30<=BT$14,BS$14,IF(CR30<=BT$15,BS$15,IF(CR30<=BT$16,BS$16,0.05))))))) | DC30: =DB30*CR30 | DE30: =IF(CU30<=BW$6,BV$6,IF(CU30<=BW$7,BV$7,IF(CU30<=BW$8,BV$8,IF(CU30<=BW$9,BV$9,IF(CU30<=BW$14,BV$14,IF(CU30<=BW$15,BV$15,IF(CU30<=BW$16,BV$16,0.05))))))) | DF30: =DE30*SUM(DC30,CZ30,CU30) | DH30: =IF(CX30<=BZ$6,BY$6,IF(CX30<=BZ$7,BY$7,IF(CX30<=BZ$8,BY$8,IF(CX30<=BZ$9,BY$9,IF(CX30<=BZ$14,BY$14,IF(CX30<=BZ$15,BY$15,IF(CX30<=BZ$16,BY$16,0.05))))))) | DI30: =DH30*CX30 | DK30: =0.07*SUM(CU30,CZ30,DC30,DF30,DI30) | DM30: =SUM(DK30,DI30,DF30,DC30,CZ30,CU30) | DN30: =SUM(DI30,DF30,DC30,CZ30) | DO30: =DN30/DM30
E31: =B31*D31 | H31: =ROUNDUP((((2*8)*(C46)*(1+C53)*(1+C54))*(1+G83))*G55,0) | I31: Add for Offsite Storage | J31: 2 guys x 8 hrs + Markups x # of mobz | O31: =O30/N28 | P31: =P28/N28 | Q31: =Q28/N28 | R31: =R28/N28 | AY31: 22000 | BB31: =AY31 | BE31: =AY31+BB31 | BH31: =BE31 | BI31: =IF(AY31<=#REF!,#REF!,IF(AY31<=#REF!,#REF!,IF(AY31<=#REF!,#REF!,IF(AY31<=#REF!,#REF!,IF(AY31<=#REF!,#REF!,IF(AY31<=#REF!,#REF!,IF(AY31<=#REF!,#REF!,0.05))))))) | BJ31: =BI31*AY31 | BL31: =IF(BB31<=#REF!,#REF!,IF(BB31<=#REF!,#REF!,IF(BB31<=#REF!,#REF!,IF(BB31<=#REF!,#REF!,IF(BB31<=#REF!,#REF!,IF(BB31<=#REF!,#REF!,IF(BB31<=#REF!,#REF!,0.05))))))) | BM31: =BL31*BB31 | BO31: =IF(BE31<=#REF!,#REF!,IF(BE31<=#REF!,#REF!,IF(BE31<=#REF!,#REF!,IF(BE31<=#REF!,#REF!,IF(BE31<=#REF!,#REF!,IF(BE31<=#REF!,#REF!,IF(BE31<=#REF!,#REF!,0.05))))))) | BP31: =BO31*SUM(BM31,BJ31,BE31) | BR31: =IF(BH31<=#REF!,#REF!,IF(BH31<=#REF!,#REF!,IF(BH31<=#REF!,#REF!,IF(BH31<=#REF!,#REF!,IF(BH31<=#REF!,#REF!,IF(BH31<=#REF!,#REF!,IF(BH31<=#REF!,#REF!,0.05))))))) | BS31: =BR31*BH31 | BU31: =0.07*SUM(BE31,BJ31,BM31,BP31,BS31) | BW31: =SUM(BU31,BS31,BP31,BM31,BJ31,BE31) | BX31: =SUM(BS31,BP31,BM31,BJ31) | BY31: =BX31/BW31 | CO31: 22000 | CR31: =CO31 | CU31: =CO31+CR31 | CX31: =CU31 | CY31: =IF(CO31<=BQ$6,BP$6,IF(CO31<=BQ$7,BP$7,IF(CO31<=BQ$8,BP$8,IF(CO31<=BQ$9,BP$9,IF(CO31<=BQ$14,BP$14,IF(CO31<=BQ$15,BP$15,IF(CO31<=BQ$16,BP$16,0.05))))))) | CZ31: =CY31*CO31 | DB31: =IF(CR31<=BT$6,BS$6,IF(CR31<=BT$7,BS$7,IF(CR31<=BT$8,BS$8,IF(CR31<=BT$9,BS$9,IF(CR31<=BT$14,BS$14,IF(CR31<=BT$15,BS$15,IF(CR31<=BT$16,BS$16,0.05))))))) | DC31: =DB31*CR31 | DE31: =IF(CU31<=BW$6,BV$6,IF(CU31<=BW$7,BV$7,IF(CU31<=BW$8,BV$8,IF(CU31<=BW$9,BV$9,IF(CU31<=BW$14,BV$14,IF(CU31<=BW$15,BV$15,IF(CU31<=BW$16,BV$16,0.05))))))) | DF31: =DE31*SUM(DC31,CZ31,CU31) | DH31: =IF(CX31<=BZ$6,BY$6,IF(CX31<=BZ$7,BY$7,IF(CX31<=BZ$8,BY$8,IF(CX31<=BZ$9,BY$9,IF(CX31<=BZ$14,BY$14,IF(CX31<=BZ$15,BY$15,IF(CX31<=BZ$16,BY$16,0.05))))))) | DI31: =DH31*CX31 | DK31: =0.07*SUM(CU31,CZ31,DC31,DF31,DI31) | DM31: =SUM(DK31,DI31,DF31,DC31,CZ31,CU31) | DN31: =SUM(DI31,DF31,DC31,CZ31) | DO31: =DN31/DM31
A32: MATERIAL - Sand | AY32: 23000 | BB32: =AY32 | BE32: =AY32+BB32 | BH32: =BE32 | BI32: =IF(AY32<=#REF!,#REF!,IF(AY32<=#REF!,#REF!,IF(AY32<=#REF!,#REF!,IF(AY32<=#REF!,#REF!,IF(AY32<=#REF!,#REF!,IF(AY32<=#REF!,#REF!,IF(AY32<=#REF!,#REF!,0.05))))))) | BJ32: =BI32*AY32 | BL32: =IF(BB32<=#REF!,#REF!,IF(BB32<=#REF!,#REF!,IF(BB32<=#REF!,#REF!,IF(BB32<=#REF!,#REF!,IF(BB32<=#REF!,#REF!,IF(BB32<=#REF!,#REF!,IF(BB32<=#REF!,#REF!,0.05))))))) | BM32: =BL32*BB32 | BO32: =IF(BE32<=#REF!,#REF!,IF(BE32<=#REF!,#REF!,IF(BE32<=#REF!,#REF!,IF(BE32<=#REF!,#REF!,IF(BE32<=#REF!,#REF!,IF(BE32<=#REF!,#REF!,IF(BE32<=#REF!,#REF!,0.05))))))) | BP32: =BO32*SUM(BM32,BJ32,BE32) | BR32: =IF(BH32<=#REF!,#REF!,IF(BH32<=#REF!,#REF!,IF(BH32<=#REF!,#REF!,IF(BH32<=#REF!,#REF!,IF(BH32<=#REF!,#REF!,IF(BH32<=#REF!,#REF!,IF(BH32<=#REF!,#REF!,0.05))))))) | BS32: =BR32*BH32 | BU32: =0.07*SUM(BE32,BJ32,BM32,BP32,BS32) | BW32: =SUM(BU32,BS32,BP32,BM32,BJ32,BE32) | BX32: =SUM(BS32,BP32,BM32,BJ32) | BY32: =BX32/BW32 | CO32: 23000 | CR32: =CO32 | CU32: =CO32+CR32 | CX32: =CU32 | CY32: =IF(CO32<=BQ$6,BP$6,IF(CO32<=BQ$7,BP$7,IF(CO32<=BQ$8,BP$8,IF(CO32<=BQ$9,BP$9,IF(CO32<=BQ$14,BP$14,IF(CO32<=BQ$15,BP$15,IF(CO32<=BQ$16,BP$16,0.05))))))) | CZ32: =CY32*CO32 | DB32: =IF(CR32<=BT$6,BS$6,IF(CR32<=BT$7,BS$7,IF(CR32<=BT$8,BS$8,IF(CR32<=BT$9,BS$9,IF(CR32<=BT$14,BS$14,IF(CR32<=BT$15,BS$15,IF(CR32<=BT$16,BS$16,0.05))))))) | DC32: =DB32*CR32 | DE32: =IF(CU32<=BW$6,BV$6,IF(CU32<=BW$7,BV$7,IF(CU32<=BW$8,BV$8,IF(CU32<=BW$9,BV$9,IF(CU32<=BW$14,BV$14,IF(CU32<=BW$15,BV$15,IF(CU32<=BW$16,BV$16,0.05))))))) | DF32: =DE32*SUM(DC32,CZ32,CU32) | DH32: =IF(CX32<=BZ$6,BY$6,IF(CX32<=BZ$7,BY$7,IF(CX32<=BZ$8,BY$8,IF(CX32<=BZ$9,BY$9,IF(CX32<=BZ$14,BY$14,IF(CX32<=BZ$15,BY$15,IF(CX32<=BZ$16,BY$16,0.05))))))) | DI32: =DH32*CX32 | DK32: =0.07*SUM(CU32,CZ32,DC32,DF32,DI32) | DM32: =SUM(DK32,DI32,DF32,DC32,CZ32,CU32) | DN32: =SUM(DI32,DF32,DC32,CZ32) | DO32: =DN32/DM32
A33: Sand (per Ton) | B33: =((IF(G11=P52,Q52,IF(G11=P54,Q54))*H33)/2000)*(1+G19) | C33: tons w/ waste | D33: 35 | E33: =B33*D33 | F33: (Total Bags x Mix Design)/2000 | H33: =B23+B24+B25 | I33: Total Bags | AY33: 24000 | BB33: =AY33 | BE33: =AY33+BB33 | BH33: =BE33 | BI33: =IF(AY33<=#REF!,#REF!,IF(AY33<=#REF!,#REF!,IF(AY33<=#REF!,#REF!,IF(AY33<=#REF!,#REF!,IF(AY33<=#REF!,#REF!,IF(AY33<=#REF!,#REF!,IF(AY33<=#REF!,#REF!,0.05))))))) | BJ33: =BI33*AY33 | BL33: =IF(BB33<=#REF!,#REF!,IF(BB33<=#REF!,#REF!,IF(BB33<=#REF!,#REF!,IF(BB33<=#REF!,#REF!,IF(BB33<=#REF!,#REF!,IF(BB33<=#REF!,#REF!,IF(BB33<=#REF!,#REF!,0.05))))))) | BM33: =BL33*BB33 | BO33: =IF(BE33<=#REF!,#REF!,IF(BE33<=#REF!,#REF!,IF(BE33<=#REF!,#REF!,IF(BE33<=#REF!,#REF!,IF(BE33<=#REF!,#REF!,IF(BE33<=#REF!,#REF!,IF(BE33<=#REF!,#REF!,0.05))))))) | BP33: =BO33*SUM(BM33,BJ33,BE33) | BR33: =IF(BH33<=#REF!,#REF!,IF(BH33<=#REF!,#REF!,IF(BH33<=#REF!,#REF!,IF(BH33<=#REF!,#REF!,IF(BH33<=#REF!,#REF!,IF(BH33<=#REF!,#REF!,IF(BH33<=#REF!,#REF!,0.05))))))) | BS33: =BR33*BH33 | BU33: =0.07*SUM(BE33,BJ33,BM33,BP33,BS33) | BW33: =SUM(BU33,BS33,BP33,BM33,BJ33,BE33) | BX33: =SUM(BS33,BP33,BM33,BJ33) | BY33: =BX33/BW33 | CO33: 24000 | CR33: =CO33 | CU33: =CO33+CR33 | CX33: =CU33 | CY33: =IF(CO33<=BQ$6,BP$6,IF(CO33<=BQ$7,BP$7,IF(CO33<=BQ$8,BP$8,IF(CO33<=BQ$9,BP$9,IF(CO33<=BQ$14,BP$14,IF(CO33<=BQ$15,BP$15,IF(CO33<=BQ$16,BP$16,0.05))))))) | CZ33: =CY33*CO33 | DB33: =IF(CR33<=BT$6,BS$6,IF(CR33<=BT$7,BS$7,IF(CR33<=BT$8,BS$8,IF(CR33<=BT$9,BS$9,IF(CR33<=BT$14,BS$14,IF(CR33<=BT$15,BS$15,IF(CR33<=BT$16,BS$16,0.05))))))) | DC33: =DB33*CR33 | DE33: =IF(CU33<=BW$6,BV$6,IF(CU33<=BW$7,BV$7,IF(CU33<=BW$8,BV$8,IF(CU33<=BW$9,BV$9,IF(CU33<=BW$14,BV$14,IF(CU33<=BW$15,BV$15,IF(CU33<=BW$16,BV$16,0.05))))))) | DF33: =DE33*SUM(DC33,CZ33,CU33) | DH33: =IF(CX33<=BZ$6,BY$6,IF(CX33<=BZ$7,BY$7,IF(CX33<=BZ$8,BY$8,IF(CX33<=BZ$9,BY$9,IF(CX33<=BZ$14,BY$14,IF(CX33<=BZ$15,BY$15,IF(CX33<=BZ$16,BY$16,0.05))))))) | DI33: =DH33*CX33 | DK33: =0.07*SUM(CU33,CZ33,DC33,DF33,DI33) | DM33: =SUM(DK33,DI33,DF33,DC33,CZ33,CU33) | DN33: =SUM(DI33,DF33,DC33,CZ33) | DO33: =DN33/DM33
E34: =B34*D34 | AY34: 25000 | BB34: =AY34 | BE34: =AY34+BB34 | BH34: =BE34 | BI34: =IF(AY34<=#REF!,#REF!,IF(AY34<=#REF!,#REF!,IF(AY34<=#REF!,#REF!,IF(AY34<=#REF!,#REF!,IF(AY34<=#REF!,#REF!,IF(AY34<=#REF!,#REF!,IF(AY34<=#REF!,#REF!,0.05))))))) | BJ34: =BI34*AY34 | BL34: =IF(BB34<=#REF!,#REF!,IF(BB34<=#REF!,#REF!,IF(BB34<=#REF!,#REF!,IF(BB34<=#REF!,#REF!,IF(BB34<=#REF!,#REF!,IF(BB34<=#REF!,#REF!,IF(BB34<=#REF!,#REF!,0.05))))))) | BM34: =BL34*BB34 | BO34: =IF(BE34<=#REF!,#REF!,IF(BE34<=#REF!,#REF!,IF(BE34<=#REF!,#REF!,IF(BE34<=#REF!,#REF!,IF(BE34<=#REF!,#REF!,IF(BE34<=#REF!,#REF!,IF(BE34<=#REF!,#REF!,0.05))))))) | BP34: =BO34*SUM(BM34,BJ34,BE34) | BR34: =IF(BH34<=#REF!,#REF!,IF(BH34<=#REF!,#REF!,IF(BH34<=#REF!,#REF!,IF(BH34<=#REF!,#REF!,IF(BH34<=#REF!,#REF!,IF(BH34<=#REF!,#REF!,IF(BH34<=#REF!,#REF!,0.05))))))) | BS34: =BR34*BH34 | BU34: =0.07*SUM(BE34,BJ34,BM34,BP34,BS34) | BW34: =SUM(BU34,BS34,BP34,BM34,BJ34,BE34) | BX34: =SUM(BS34,BP34,BM34,BJ34) | BY34: =BX34/BW34 | CO34: 25000 | CR34: =CO34 | CU34: =CO34+CR34 | CX34: =CU34 | CY34: =IF(CO34<=BQ$6,BP$6,IF(CO34<=BQ$7,BP$7,IF(CO34<=BQ$8,BP$8,IF(CO34<=BQ$9,BP$9,IF(CO34<=BQ$14,BP$14,IF(CO34<=BQ$15,BP$15,IF(CO34<=BQ$16,BP$16,0.05))))))) | CZ34: =CY34*CO34 | DB34: =IF(CR34<=BT$6,BS$6,IF(CR34<=BT$7,BS$7,IF(CR34<=BT$8,BS$8,IF(CR34<=BT$9,BS$9,IF(CR34<=BT$14,BS$14,IF(CR34<=BT$15,BS$15,IF(CR34<=BT$16,BS$16,0.05))))))) | DC34: =DB34*CR34 | DE34: =IF(CU34<=BW$6,BV$6,IF(CU34<=BW$7,BV$7,IF(CU34<=BW$8,BV$8,IF(CU34<=BW$9,BV$9,IF(CU34<=BW$14,BV$14,IF(CU34<=BW$15,BV$15,IF(CU34<=BW$16,BV$16,0.05))))))) | DF34: =DE34*SUM(DC34,CZ34,CU34) | DH34: =IF(CX34<=BZ$6,BY$6,IF(CX34<=BZ$7,BY$7,IF(CX34<=BZ$8,BY$8,IF(CX34<=BZ$9,BY$9,IF(CX34<=BZ$14,BY$14,IF(CX34<=BZ$15,BY$15,IF(CX34<=BZ$16,BY$16,0.05))))))) | DI34: =DH34*CX34 | DK34: =0.07*SUM(CU34,CZ34,DC34,DF34,DI34) | DM34: =SUM(DK34,DI34,DF34,DC34,CZ34,CU34) | DN34: =SUM(DI34,DF34,DC34,CZ34) | DO34: =DN34/DM34
A35: MATERIAL - Sound Mat | B35: USG | I35: [GrassWorx = 384 (for all)] | O35: Sound Mat $$$$ | AY35: 26000 | BB35: =AY35 | BE35: =AY35+BB35 | BH35: =BE35 | BI35: =IF(AY35<=#REF!,#REF!,IF(AY35<=#REF!,#REF!,IF(AY35<=#REF!,#REF!,IF(AY35<=#REF!,#REF!,IF(AY35<=#REF!,#REF!,IF(AY35<=#REF!,#REF!,IF(AY35<=#REF!,#REF!,0.05))))))) | BJ35: =BI35*AY35 | BL35: =IF(BB35<=#REF!,#REF!,IF(BB35<=#REF!,#REF!,IF(BB35<=#REF!,#REF!,IF(BB35<=#REF!,#REF!,IF(BB35<=#REF!,#REF!,IF(BB35<=#REF!,#REF!,IF(BB35<=#REF!,#REF!,0.05))))))) | BM35: =BL35*BB35 | BO35: =IF(BE35<=#REF!,#REF!,IF(BE35<=#REF!,#REF!,IF(BE35<=#REF!,#REF!,IF(BE35<=#REF!,#REF!,IF(BE35<=#REF!,#REF!,IF(BE35<=#REF!,#REF!,IF(BE35<=#REF!,#REF!,0.05))))))) | BP35: =BO35*SUM(BM35,BJ35,BE35) | BR35: =IF(BH35<=#REF!,#REF!,IF(BH35<=#REF!,#REF!,IF(BH35<=#REF!,#REF!,IF(BH35<=#REF!,#REF!,IF(BH35<=#REF!,#REF!,IF(BH35<=#REF!,#REF!,IF(BH35<=#REF!,#REF!,0.05))))))) | BS35: =BR35*BH35 | BU35: =0.07*SUM(BE35,BJ35,BM35,BP35,BS35) | BW35: =SUM(BU35,BS35,BP35,BM35,BJ35,BE35) | BX35: =SUM(BS35,BP35,BM35,BJ35) | BY35: =BX35/BW35 | CO35: 26000 | CR35: =CO35 | CU35: =CO35+CR35 | CX35: =CU35 | CY35: =IF(CO35<=BQ$6,BP$6,IF(CO35<=BQ$7,BP$7,IF(CO35<=BQ$8,BP$8,IF(CO35<=BQ$9,BP$9,IF(CO35<=BQ$14,BP$14,IF(CO35<=BQ$15,BP$15,IF(CO35<=BQ$16,BP$16,0.05))))))) | CZ35: =CY35*CO35 | DB35: =IF(CR35<=BT$6,BS$6,IF(CR35<=BT$7,BS$7,IF(CR35<=BT$8,BS$8,IF(CR35<=BT$9,BS$9,IF(CR35<=BT$14,BS$14,IF(CR35<=BT$15,BS$15,IF(CR35<=BT$16,BS$16,0.05))))))) | DC35: =DB35*CR35 | DE35: =IF(CU35<=BW$6,BV$6,IF(CU35<=BW$7,BV$7,IF(CU35<=BW$8,BV$8,IF(CU35<=BW$9,BV$9,IF(CU35<=BW$14,BV$14,IF(CU35<=BW$15,BV$15,IF(CU35<=BW$16,BV$16,0.05))))))) | DF35: =DE35*SUM(DC35,CZ35,CU35) | DH35: =IF(CX35<=BZ$6,BY$6,IF(CX35<=BZ$7,BY$7,IF(CX35<=BZ$8,BY$8,IF(CX35<=BZ$9,BY$9,IF(CX35<=BZ$14,BY$14,IF(CX35<=BZ$15,BY$15,IF(CX35<=BZ$16,BY$16,0.05))))))) | DI35: =DH35*CX35 | DK35: =0.07*SUM(CU35,CZ35,DC35,DF35,DI35) | DM35: =SUM(DK35,DI35,DF35,DC35,CZ35,CU35) | DN35: =SUM(DI35,DF35,DC35,CZ35) | DO35: =DN35/DM35
A36: SAM-N12 (1/8") | B36: =ROUNDUP(IF(A36=O37,(F24/Q37),IF(A36=O38,(F24/Q38),IF(A36=O39,(F24/Q39),IF(A36=O40,(F24/Q40),IF(A36=O42,(F24/Q42),IF(A36=O43,(F24/Q43),IF(A36=O44,(F24/Q44),"none")))))))*(1+G20),0) | C36: rolls | D36: =IF(A36=O37,(P37),IF(A36=O38,(P38),IF(A36=O39,(P39),IF(A36=O40,(P40),IF(A36=O42,(P42),IF(A36=O43,(P43),IF(A36=O44,(P44),"none"))))))) | E36: =B36*D36 | H36: =IF(A36=O37,280,IF(A36=O38,208,IF(A36=O39,208,IF(A36=O40,260,IF(A36=O42,384,IF(A36=O43,384,IF(A36=O44,384,"error"))))))) | I36: Mat Rolls /Truck Load | K36: shipping on gyp = 20% | L36: =(ROUNDUP(SUM(E20:E26)*B40,0)) | O36: USG $: 1/8/2026 | P36: Price | Q36: Sqft per Roll | R36: $ per Sqft | S36: ($ per 10-2024) | AY36: 27000 | BB36: =AY36 | BE36: =AY36+BB36 | BH36: =BE36 | BI36: =IF(AY36<=#REF!,#REF!,IF(AY36<=#REF!,#REF!,IF(AY36<=#REF!,#REF!,IF(AY36<=#REF!,#REF!,IF(AY36<=#REF!,#REF!,IF(AY36<=#REF!,#REF!,IF(AY36<=#REF!,#REF!,0.05))))))) | BJ36: =BI36*AY36 | BL36: =IF(BB36<=#REF!,#REF!,IF(BB36<=#REF!,#REF!,IF(BB36<=#REF!,#REF!,IF(BB36<=#REF!,#REF!,IF(BB36<=#REF!,#REF!,IF(BB36<=#REF!,#REF!,IF(BB36<=#REF!,#REF!,0.05))))))) | BM36: =BL36*BB36 | BO36: =IF(BE36<=#REF!,#REF!,IF(BE36<=#REF!,#REF!,IF(BE36<=#REF!,#REF!,IF(BE36<=#REF!,#REF!,IF(BE36<=#REF!,#REF!,IF(BE36<=#REF!,#REF!,IF(BE36<=#REF!,#REF!,0.05))))))) | BP36: =BO36*SUM(BM36,BJ36,BE36) | BR36: =IF(BH36<=#REF!,#REF!,IF(BH36<=#REF!,#REF!,IF(BH36<=#REF!,#REF!,IF(BH36<=#REF!,#REF!,IF(BH36<=#REF!,#REF!,IF(BH36<=#REF!,#REF!,IF(BH36<=#REF!,#REF!,0.05))))))) | BS36: =BR36*BH36 | BU36: =0.07*SUM(BE36,BJ36,BM36,BP36,BS36) | BW36: =SUM(BU36,BS36,BP36,BM36,BJ36,BE36) | BX36: =SUM(BS36,BP36,BM36,BJ36) | BY36: =BX36/BW36 | CO36: 27000 | CR36: =CO36 | CU36: =CO36+CR36 | CX36: =CU36 | CY36: =IF(CO36<=BQ$6,BP$6,IF(CO36<=BQ$7,BP$7,IF(CO36<=BQ$8,BP$8,IF(CO36<=BQ$9,BP$9,IF(CO36<=BQ$14,BP$14,IF(CO36<=BQ$15,BP$15,IF(CO36<=BQ$16,BP$16,0.05))))))) | CZ36: =CY36*CO36 | DB36: =IF(CR36<=BT$6,BS$6,IF(CR36<=BT$7,BS$7,IF(CR36<=BT$8,BS$8,IF(CR36<=BT$9,BS$9,IF(CR36<=BT$14,BS$14,IF(CR36<=BT$15,BS$15,IF(CR36<=BT$16,BS$16,0.05))))))) | DC36: =DB36*CR36 | DE36: =IF(CU36<=BW$6,BV$6,IF(CU36<=BW$7,BV$7,IF(CU36<=BW$8,BV$8,IF(CU36<=BW$9,BV$9,IF(CU36<=BW$14,BV$14,IF(CU36<=BW$15,BV$15,IF(CU36<=BW$16,BV$16,0.05))))))) | DF36: =DE36*SUM(DC36,CZ36,CU36) | DH36: =IF(CX36<=BZ$6,BY$6,IF(CX36<=BZ$7,BY$7,IF(CX36<=BZ$8,BY$8,IF(CX36<=BZ$9,BY$9,IF(CX36<=BZ$14,BY$14,IF(CX36<=BZ$15,BY$15,IF(CX36<=BZ$16,BY$16,0.05))))))) | DI36: =DH36*CX36 | DK36: =0.07*SUM(CU36,CZ36,DC36,DF36,DI36) | DM36: =SUM(DK36,DI36,DF36,DC36,CZ36,CU36) | DN36: =SUM(DI36,DF36,DC36,CZ36) | DO36: =DN36/DM36
E37: =B37*D37 | H37: [280 = USG 1/8"] | I37: [Formulated = 448] | K37: shipping on mat,primr,iso,tape = 10% | L37: =(ROUNDUP(((SUM(E27:E31,IF(B36<448,(SUM(E35:E37)),0)))*D40),0)) | M37: 159k vs 159,300 Hard Surfaces | N37: 1/8" | O37: SAM-N12 (1/8") | P37: =Q37*R37 | Q37: 494 | R37: 0.48 | S37: Bag Price (2500) | T37: 14.08 | U37: -or- (3500) | V37: 18.6 | AY37: 28000 | BB37: =AY37 | BE37: =AY37+BB37 | BH37: =BE37 | BI37: =IF(AY37<=#REF!,#REF!,IF(AY37<=#REF!,#REF!,IF(AY37<=#REF!,#REF!,IF(AY37<=#REF!,#REF!,IF(AY37<=#REF!,#REF!,IF(AY37<=#REF!,#REF!,IF(AY37<=#REF!,#REF!,0.05))))))) | BJ37: =BI37*AY37 | BL37: =IF(BB37<=#REF!,#REF!,IF(BB37<=#REF!,#REF!,IF(BB37<=#REF!,#REF!,IF(BB37<=#REF!,#REF!,IF(BB37<=#REF!,#REF!,IF(BB37<=#REF!,#REF!,IF(BB37<=#REF!,#REF!,0.05))))))) | BM37: =BL37*BB37 | BO37: =IF(BE37<=#REF!,#REF!,IF(BE37<=#REF!,#REF!,IF(BE37<=#REF!,#REF!,IF(BE37<=#REF!,#REF!,IF(BE37<=#REF!,#REF!,IF(BE37<=#REF!,#REF!,IF(BE37<=#REF!,#REF!,0.05))))))) | BP37: =BO37*SUM(BM37,BJ37,BE37) | BR37: =IF(BH37<=#REF!,#REF!,IF(BH37<=#REF!,#REF!,IF(BH37<=#REF!,#REF!,IF(BH37<=#REF!,#REF!,IF(BH37<=#REF!,#REF!,IF(BH37<=#REF!,#REF!,IF(BH37<=#REF!,#REF!,0.05))))))) | BS37: =BR37*BH37 | BU37: =0.07*SUM(BE37,BJ37,BM37,BP37,BS37) | BW37: =SUM(BU37,BS37,BP37,BM37,BJ37,BE37) | BX37: =SUM(BS37,BP37,BM37,BJ37) | BY37: =BX37/BW37 | CO37: 28000 | CR37: =CO37 | CU37: =CO37+CR37 | CX37: =CU37 | CY37: =IF(CO37<=BQ$6,BP$6,IF(CO37<=BQ$7,BP$7,IF(CO37<=BQ$8,BP$8,IF(CO37<=BQ$9,BP$9,IF(CO37<=BQ$14,BP$14,IF(CO37<=BQ$15,BP$15,IF(CO37<=BQ$16,BP$16,0.05))))))) | CZ37: =CY37*CO37 | DB37: =IF(CR37<=BT$6,BS$6,IF(CR37<=BT$7,BS$7,IF(CR37<=BT$8,BS$8,IF(CR37<=BT$9,BS$9,IF(CR37<=BT$14,BS$14,IF(CR37<=BT$15,BS$15,IF(CR37<=BT$16,BS$16,0.05))))))) | DC37: =DB37*CR37 | DE37: =IF(CU37<=BW$6,BV$6,IF(CU37<=BW$7,BV$7,IF(CU37<=BW$8,BV$8,IF(CU37<=BW$9,BV$9,IF(CU37<=BW$14,BV$14,IF(CU37<=BW$15,BV$15,IF(CU37<=BW$16,BV$16,0.05))))))) | DF37: =DE37*SUM(DC37,CZ37,CU37) | DH37: =IF(CX37<=BZ$6,BY$6,IF(CX37<=BZ$7,BY$7,IF(CX37<=BZ$8,BY$8,IF(CX37<=BZ$9,BY$9,IF(CX37<=BZ$14,BY$14,IF(CX37<=BZ$15,BY$15,IF(CX37<=BZ$16,BY$16,0.05))))))) | DI37: =DH37*CX37 | DK37: =0.07*SUM(CU37,CZ37,DC37,DF37,DI37) | DM37: =SUM(DK37,DI37,DF37,DC37,CZ37,CU37) | DN37: =SUM(DI37,DF37,DC37,CZ37) | DO37: =DN37/DM37
A38: Material Sub Total | E38: =ROUNDUP(SUM(E20:E37),0) | H38: [208 = USG 1/4" +] | I38: [260 = USG 3/16"] | K38: combined= | L38: =SUM(L36:L37) | N38: 1/4" | O38: SAM-N25 (1/4") | P38: =Q38*R38 | Q38: 445 | R38: 0.55 | S38: Wood Primer | T38: =108/5 | U38: ($108 /5 gal) -or- ($891 /Drum | W38: x gallons ???) | AY38: 29000 | BB38: =AY38 | BE38: =AY38+BB38 | BH38: =BE38 | BI38: =IF(AY38<=#REF!,#REF!,IF(AY38<=#REF!,#REF!,IF(AY38<=#REF!,#REF!,IF(AY38<=#REF!,#REF!,IF(AY38<=#REF!,#REF!,IF(AY38<=#REF!,#REF!,IF(AY38<=#REF!,#REF!,0.05))))))) | BJ38: =BI38*AY38 | BL38: =IF(BB38<=#REF!,#REF!,IF(BB38<=#REF!,#REF!,IF(BB38<=#REF!,#REF!,IF(BB38<=#REF!,#REF!,IF(BB38<=#REF!,#REF!,IF(BB38<=#REF!,#REF!,IF(BB38<=#REF!,#REF!,0.05))))))) | BM38: =BL38*BB38 | BO38: =IF(BE38<=#REF!,#REF!,IF(BE38<=#REF!,#REF!,IF(BE38<=#REF!,#REF!,IF(BE38<=#REF!,#REF!,IF(BE38<=#REF!,#REF!,IF(BE38<=#REF!,#REF!,IF(BE38<=#REF!,#REF!,0.05))))))) | BP38: =BO38*SUM(BM38,BJ38,BE38) | BR38: =IF(BH38<=#REF!,#REF!,IF(BH38<=#REF!,#REF!,IF(BH38<=#REF!,#REF!,IF(BH38<=#REF!,#REF!,IF(BH38<=#REF!,#REF!,IF(BH38<=#REF!,#REF!,IF(BH38<=#REF!,#REF!,0.05))))))) | BS38: =BR38*BH38 | BU38: =0.07*SUM(BE38,BJ38,BM38,BP38,BS38) | BW38: =SUM(BU38,BS38,BP38,BM38,BJ38,BE38) | BX38: =SUM(BS38,BP38,BM38,BJ38) | BY38: =BX38/BW38 | CO38: 29000 | CR38: =CO38 | CU38: =CO38+CR38 | CX38: =CU38 | CY38: =IF(CO38<=BQ$6,BP$6,IF(CO38<=BQ$7,BP$7,IF(CO38<=BQ$8,BP$8,IF(CO38<=BQ$9,BP$9,IF(CO38<=BQ$14,BP$14,IF(CO38<=BQ$15,BP$15,IF(CO38<=BQ$16,BP$16,0.05))))))) | CZ38: =CY38*CO38 | DB38: =IF(CR38<=BT$6,BS$6,IF(CR38<=BT$7,BS$7,IF(CR38<=BT$8,BS$8,IF(CR38<=BT$9,BS$9,IF(CR38<=BT$14,BS$14,IF(CR38<=BT$15,BS$15,IF(CR38<=BT$16,BS$16,0.05))))))) | DC38: =DB38*CR38 | DE38: =IF(CU38<=BW$6,BV$6,IF(CU38<=BW$7,BV$7,IF(CU38<=BW$8,BV$8,IF(CU38<=BW$9,BV$9,IF(CU38<=BW$14,BV$14,IF(CU38<=BW$15,BV$15,IF(CU38<=BW$16,BV$16,0.05))))))) | DF38: =DE38*SUM(DC38,CZ38,CU38) | DH38: =IF(CX38<=BZ$6,BY$6,IF(CX38<=BZ$7,BY$7,IF(CX38<=BZ$8,BY$8,IF(CX38<=BZ$9,BY$9,IF(CX38<=BZ$14,BY$14,IF(CX38<=BZ$15,BY$15,IF(CX38<=BZ$16,BY$16,0.05))))))) | DI38: =DH38*CX38 | DK38: =0.07*SUM(CU38,CZ38,DC38,DF38,DI38) | DM38: =SUM(DK38,DI38,DF38,DC38,CZ38,CU38) | DN38: =SUM(DI38,DF38,DC38,CZ38) | DO38: =DN38/DM38
A39: Material Escalation | B39: 0.08 | E39: =ROUNDUP(SUM(E23:E31,E35:E37)*B39,0) | F39: escalation for gyp, extras + mat | K39: (**none on sand**) | N39: 3/8" | O39: SAM-N40 (3/8") | P39: =Q39*R39 | Q39: 330 | R39: 0.65 | S39: Iso | T39: 25 | U39: ISO ??? Which one ?? | AY39: 30000 | BB39: =AY39 | BE39: =AY39+BB39 | BH39: =BE39 | BI39: =IF(AY39<=#REF!,#REF!,IF(AY39<=#REF!,#REF!,IF(AY39<=#REF!,#REF!,IF(AY39<=#REF!,#REF!,IF(AY39<=#REF!,#REF!,IF(AY39<=#REF!,#REF!,IF(AY39<=#REF!,#REF!,0.05))))))) | BJ39: =BI39*AY39 | BL39: =IF(BB39<=#REF!,#REF!,IF(BB39<=#REF!,#REF!,IF(BB39<=#REF!,#REF!,IF(BB39<=#REF!,#REF!,IF(BB39<=#REF!,#REF!,IF(BB39<=#REF!,#REF!,IF(BB39<=#REF!,#REF!,0.05))))))) | BM39: =BL39*BB39 | BO39: =IF(BE39<=#REF!,#REF!,IF(BE39<=#REF!,#REF!,IF(BE39<=#REF!,#REF!,IF(BE39<=#REF!,#REF!,IF(BE39<=#REF!,#REF!,IF(BE39<=#REF!,#REF!,IF(BE39<=#REF!,#REF!,0.05))))))) | BP39: =BO39*SUM(BM39,BJ39,BE39) | BR39: =IF(BH39<=#REF!,#REF!,IF(BH39<=#REF!,#REF!,IF(BH39<=#REF!,#REF!,IF(BH39<=#REF!,#REF!,IF(BH39<=#REF!,#REF!,IF(BH39<=#REF!,#REF!,IF(BH39<=#REF!,#REF!,0.05))))))) | BS39: =BR39*BH39 | BU39: =0.07*SUM(BE39,BJ39,BM39,BP39,BS39) | BW39: =SUM(BU39,BS39,BP39,BM39,BJ39,BE39) | BX39: =SUM(BS39,BP39,BM39,BJ39) | BY39: =BX39/BW39 | CO39: 30000 | CR39: =CO39 | CU39: =CO39+CR39 | CX39: =CU39 | CY39: =IF(CO39<=BQ$6,BP$6,IF(CO39<=BQ$7,BP$7,IF(CO39<=BQ$8,BP$8,IF(CO39<=BQ$9,BP$9,IF(CO39<=BQ$14,BP$14,IF(CO39<=BQ$15,BP$15,IF(CO39<=BQ$16,BP$16,0.05))))))) | CZ39: =CY39*CO39 | DB39: =IF(CR39<=BT$6,BS$6,IF(CR39<=BT$7,BS$7,IF(CR39<=BT$8,BS$8,IF(CR39<=BT$9,BS$9,IF(CR39<=BT$14,BS$14,IF(CR39<=BT$15,BS$15,IF(CR39<=BT$16,BS$16,0.05))))))) | DC39: =DB39*CR39 | DE39: =IF(CU39<=BW$6,BV$6,IF(CU39<=BW$7,BV$7,IF(CU39<=BW$8,BV$8,IF(CU39<=BW$9,BV$9,IF(CU39<=BW$14,BV$14,IF(CU39<=BW$15,BV$15,IF(CU39<=BW$16,BV$16,0.05))))))) | DF39: =DE39*SUM(DC39,CZ39,CU39) | DH39: =IF(CX39<=BZ$6,BY$6,IF(CX39<=BZ$7,BY$7,IF(CX39<=BZ$8,BY$8,IF(CX39<=BZ$9,BY$9,IF(CX39<=BZ$14,BY$14,IF(CX39<=BZ$15,BY$15,IF(CX39<=BZ$16,BY$16,0.05))))))) | DI39: =DH39*CX39 | DK39: =0.07*SUM(CU39,CZ39,DC39,DF39,DI39) | DM39: =SUM(DK39,DI39,DF39,DC39,CZ39,CU39) | DN39: =SUM(DI39,DF39,DC39,CZ39) | DO39: =DN39/DM39
A40: Shipping On... Gyp Bags: | B40: 0.2 | C40: ... Ship Other: | D40: 0.1 | E40: =(ROUNDUP(SUM(E20:E26)*B40,0))+(ROUNDUP(((SUM(E27:E31,IF(B36<H36,(SUM(E35:E37)),0)))*D40),0)) | F40: Shipping: 20% on gyp bags, 10% on primer, iso, tape, mat (none on sand) | I40: Material Budget | N40: 3/16" | O40: SAM-N12 ULTRA (3/16") | P40: =Q40*R40 | Q40: 369 | R40: 0.64 | AY40: 31000 | BB40: =AY40 | BE40: =AY40+BB40 | BH40: =BE40 | BI40: =IF(AY40<=#REF!,#REF!,IF(AY40<=#REF!,#REF!,IF(AY40<=#REF!,#REF!,IF(AY40<=#REF!,#REF!,IF(AY40<=#REF!,#REF!,IF(AY40<=#REF!,#REF!,IF(AY40<=#REF!,#REF!,0.05))))))) | BJ40: =BI40*AY40 | BL40: =IF(BB40<=#REF!,#REF!,IF(BB40<=#REF!,#REF!,IF(BB40<=#REF!,#REF!,IF(BB40<=#REF!,#REF!,IF(BB40<=#REF!,#REF!,IF(BB40<=#REF!,#REF!,IF(BB40<=#REF!,#REF!,0.05))))))) | BM40: =BL40*BB40 | BO40: =IF(BE40<=#REF!,#REF!,IF(BE40<=#REF!,#REF!,IF(BE40<=#REF!,#REF!,IF(BE40<=#REF!,#REF!,IF(BE40<=#REF!,#REF!,IF(BE40<=#REF!,#REF!,IF(BE40<=#REF!,#REF!,0.05))))))) | BP40: =BO40*SUM(BM40,BJ40,BE40) | BR40: =IF(BH40<=#REF!,#REF!,IF(BH40<=#REF!,#REF!,IF(BH40<=#REF!,#REF!,IF(BH40<=#REF!,#REF!,IF(BH40<=#REF!,#REF!,IF(BH40<=#REF!,#REF!,IF(BH40<=#REF!,#REF!,0.05))))))) | BS40: =BR40*BH40 | BU40: =0.07*SUM(BE40,BJ40,BM40,BP40,BS40) | BW40: =SUM(BU40,BS40,BP40,BM40,BJ40,BE40) | BX40: =SUM(BS40,BP40,BM40,BJ40) | BY40: =BX40/BW40 | CO40: 31000 | CR40: =CO40 | CU40: =CO40+CR40 | CX40: =CU40 | CY40: =IF(CO40<=BQ$6,BP$6,IF(CO40<=BQ$7,BP$7,IF(CO40<=BQ$8,BP$8,IF(CO40<=BQ$9,BP$9,IF(CO40<=BQ$14,BP$14,IF(CO40<=BQ$15,BP$15,IF(CO40<=BQ$16,BP$16,0.05))))))) | CZ40: =CY40*CO40 | DB40: =IF(CR40<=BT$6,BS$6,IF(CR40<=BT$7,BS$7,IF(CR40<=BT$8,BS$8,IF(CR40<=BT$9,BS$9,IF(CR40<=BT$14,BS$14,IF(CR40<=BT$15,BS$15,IF(CR40<=BT$16,BS$16,0.05))))))) | DC40: =DB40*CR40 | DE40: =IF(CU40<=BW$6,BV$6,IF(CU40<=BW$7,BV$7,IF(CU40<=BW$8,BV$8,IF(CU40<=BW$9,BV$9,IF(CU40<=BW$14,BV$14,IF(CU40<=BW$15,BV$15,IF(CU40<=BW$16,BV$16,0.05))))))) | DF40: =DE40*SUM(DC40,CZ40,CU40) | DH40: =IF(CX40<=BZ$6,BY$6,IF(CX40<=BZ$7,BY$7,IF(CX40<=BZ$8,BY$8,IF(CX40<=BZ$9,BY$9,IF(CX40<=BZ$14,BY$14,IF(CX40<=BZ$15,BY$15,IF(CX40<=BZ$16,BY$16,0.05))))))) | DI40: =DH40*CX40 | DK40: =0.07*SUM(CU40,CZ40,DC40,DF40,DI40) | DM40: =SUM(DK40,DI40,DF40,DC40,CZ40,CU40) | DN40: =SUM(DI40,DF40,DC40,CZ40) | DO40: =DN40/DM40
A41: Material Total | E41: =SUM(E38:E40) | F41: =E41/B43 | G41: Material $/SF | I41: =E41 | O41: GrassWorx $: 10/2026 | P41: Price | Q41: Sqft per Roll | R41: $ per Sqft | S41: GrassWorx $: Oct 2026 (per email May 1, '26 from Tom Torello <tom.torello@grassworxllc.com> ) | AY41: 32000 | BB41: =AY41 | BE41: =AY41+BB41 | BH41: =BE41 | BI41: =IF(AY41<=#REF!,#REF!,IF(AY41<=#REF!,#REF!,IF(AY41<=#REF!,#REF!,IF(AY41<=#REF!,#REF!,IF(AY41<=#REF!,#REF!,IF(AY41<=#REF!,#REF!,IF(AY41<=#REF!,#REF!,0.05))))))) | BJ41: =BI41*AY41 | BL41: =IF(BB41<=#REF!,#REF!,IF(BB41<=#REF!,#REF!,IF(BB41<=#REF!,#REF!,IF(BB41<=#REF!,#REF!,IF(BB41<=#REF!,#REF!,IF(BB41<=#REF!,#REF!,IF(BB41<=#REF!,#REF!,0.05))))))) | BM41: =BL41*BB41 | BO41: =IF(BE41<=#REF!,#REF!,IF(BE41<=#REF!,#REF!,IF(BE41<=#REF!,#REF!,IF(BE41<=#REF!,#REF!,IF(BE41<=#REF!,#REF!,IF(BE41<=#REF!,#REF!,IF(BE41<=#REF!,#REF!,0.05))))))) | BP41: =BO41*SUM(BM41,BJ41,BE41) | BR41: =IF(BH41<=#REF!,#REF!,IF(BH41<=#REF!,#REF!,IF(BH41<=#REF!,#REF!,IF(BH41<=#REF!,#REF!,IF(BH41<=#REF!,#REF!,IF(BH41<=#REF!,#REF!,IF(BH41<=#REF!,#REF!,0.05))))))) | BS41: =BR41*BH41 | BU41: =0.07*SUM(BE41,BJ41,BM41,BP41,BS41) | BW41: =SUM(BU41,BS41,BP41,BM41,BJ41,BE41) | BX41: =SUM(BS41,BP41,BM41,BJ41) | BY41: =BX41/BW41 | CO41: 32000 | CR41: =CO41 | CU41: =CO41+CR41 | CX41: =CU41 | CY41: =IF(CO41<=BQ$6,BP$6,IF(CO41<=BQ$7,BP$7,IF(CO41<=BQ$8,BP$8,IF(CO41<=BQ$9,BP$9,IF(CO41<=BQ$14,BP$14,IF(CO41<=BQ$15,BP$15,IF(CO41<=BQ$16,BP$16,0.05))))))) | CZ41: =CY41*CO41 | DB41: =IF(CR41<=BT$6,BS$6,IF(CR41<=BT$7,BS$7,IF(CR41<=BT$8,BS$8,IF(CR41<=BT$9,BS$9,IF(CR41<=BT$14,BS$14,IF(CR41<=BT$15,BS$15,IF(CR41<=BT$16,BS$16,0.05))))))) | DC41: =DB41*CR41 | DE41: =IF(CU41<=BW$6,BV$6,IF(CU41<=BW$7,BV$7,IF(CU41<=BW$8,BV$8,IF(CU41<=BW$9,BV$9,IF(CU41<=BW$14,BV$14,IF(CU41<=BW$15,BV$15,IF(CU41<=BW$16,BV$16,0.05))))))) | DF41: =DE41*SUM(DC41,CZ41,CU41) | DH41: =IF(CX41<=BZ$6,BY$6,IF(CX41<=BZ$7,BY$7,IF(CX41<=BZ$8,BY$8,IF(CX41<=BZ$9,BY$9,IF(CX41<=BZ$14,BY$14,IF(CX41<=BZ$15,BY$15,IF(CX41<=BZ$16,BY$16,0.05))))))) | DI41: =DH41*CX41 | DK41: =0.07*SUM(CU41,CZ41,DC41,DF41,DI41) | DM41: =SUM(DK41,DI41,DF41,DC41,CZ41,CU41) | DN41: =SUM(DI41,DF41,DC41,CZ41) | DO41: =DN41/DM41
N42: 1/8" | O42: SC 190 (1/8") | P42: =Q42*R42 | Q42: 300 | R42: =0.35+0.04 | AY42: 33000 | BB42: =AY42 | BE42: =AY42+BB42 | BH42: =BE42 | BI42: =IF(AY42<=#REF!,#REF!,IF(AY42<=#REF!,#REF!,IF(AY42<=#REF!,#REF!,IF(AY42<=#REF!,#REF!,IF(AY42<=#REF!,#REF!,IF(AY42<=#REF!,#REF!,IF(AY42<=#REF!,#REF!,0.05))))))) | BJ42: =BI42*AY42 | BL42: =IF(BB42<=#REF!,#REF!,IF(BB42<=#REF!,#REF!,IF(BB42<=#REF!,#REF!,IF(BB42<=#REF!,#REF!,IF(BB42<=#REF!,#REF!,IF(BB42<=#REF!,#REF!,IF(BB42<=#REF!,#REF!,0.05))))))) | BM42: =BL42*BB42 | BO42: =IF(BE42<=#REF!,#REF!,IF(BE42<=#REF!,#REF!,IF(BE42<=#REF!,#REF!,IF(BE42<=#REF!,#REF!,IF(BE42<=#REF!,#REF!,IF(BE42<=#REF!,#REF!,IF(BE42<=#REF!,#REF!,0.05))))))) | BP42: =BO42*SUM(BM42,BJ42,BE42) | BR42: =IF(BH42<=#REF!,#REF!,IF(BH42<=#REF!,#REF!,IF(BH42<=#REF!,#REF!,IF(BH42<=#REF!,#REF!,IF(BH42<=#REF!,#REF!,IF(BH42<=#REF!,#REF!,IF(BH42<=#REF!,#REF!,0.05))))))) | BS42: =BR42*BH42 | BU42: =0.07*SUM(BE42,BJ42,BM42,BP42,BS42) | BW42: =SUM(BU42,BS42,BP42,BM42,BJ42,BE42) | BX42: =SUM(BS42,BP42,BM42,BJ42) | BY42: =BX42/BW42 | CO42: 33000 | CR42: =CO42 | CU42: =CO42+CR42 | CX42: =CU42 | CY42: =IF(CO42<=BQ$6,BP$6,IF(CO42<=BQ$7,BP$7,IF(CO42<=BQ$8,BP$8,IF(CO42<=BQ$9,BP$9,IF(CO42<=BQ$14,BP$14,IF(CO42<=BQ$15,BP$15,IF(CO42<=BQ$16,BP$16,0.05))))))) | CZ42: =CY42*CO42 | DB42: =IF(CR42<=BT$6,BS$6,IF(CR42<=BT$7,BS$7,IF(CR42<=BT$8,BS$8,IF(CR42<=BT$9,BS$9,IF(CR42<=BT$14,BS$14,IF(CR42<=BT$15,BS$15,IF(CR42<=BT$16,BS$16,0.05))))))) | DC42: =DB42*CR42 | DE42: =IF(CU42<=BW$6,BV$6,IF(CU42<=BW$7,BV$7,IF(CU42<=BW$8,BV$8,IF(CU42<=BW$9,BV$9,IF(CU42<=BW$14,BV$14,IF(CU42<=BW$15,BV$15,IF(CU42<=BW$16,BV$16,0.05))))))) | DF42: =DE42*SUM(DC42,CZ42,CU42) | DH42: =IF(CX42<=BZ$6,BY$6,IF(CX42<=BZ$7,BY$7,IF(CX42<=BZ$8,BY$8,IF(CX42<=BZ$9,BY$9,IF(CX42<=BZ$14,BY$14,IF(CX42<=BZ$15,BY$15,IF(CX42<=BZ$16,BY$16,0.05))))))) | DI42: =DH42*CX42 | DK42: =0.07*SUM(CU42,CZ42,DC42,DF42,DI42) | DM42: =SUM(DK42,DI42,DF42,DC42,CZ42,CU42) | DN42: =SUM(DI42,DF42,DC42,CZ42) | DO42: =DN42/DM42
A43: Square Footage: | B43: =F22 | C43: Linear Footage: | E43: =(IF(D7="Yes","PW","-")) | F43: 10 hour days | G43: Labor Production Rates (Hard Enter) | N43: 1/4" | O43: SC 250 (1/4") | P43: =Q43*R43 | Q43: 250 | R43: =0.38+0.04 | AY43: 34000 | BB43: =AY43 | BE43: =AY43+BB43 | BH43: =BE43 | BI43: =IF(AY43<=#REF!,#REF!,IF(AY43<=#REF!,#REF!,IF(AY43<=#REF!,#REF!,IF(AY43<=#REF!,#REF!,IF(AY43<=#REF!,#REF!,IF(AY43<=#REF!,#REF!,IF(AY43<=#REF!,#REF!,0.05))))))) | BJ43: =BI43*AY43 | BL43: =IF(BB43<=#REF!,#REF!,IF(BB43<=#REF!,#REF!,IF(BB43<=#REF!,#REF!,IF(BB43<=#REF!,#REF!,IF(BB43<=#REF!,#REF!,IF(BB43<=#REF!,#REF!,IF(BB43<=#REF!,#REF!,0.05))))))) | BM43: =BL43*BB43 | BO43: =IF(BE43<=#REF!,#REF!,IF(BE43<=#REF!,#REF!,IF(BE43<=#REF!,#REF!,IF(BE43<=#REF!,#REF!,IF(BE43<=#REF!,#REF!,IF(BE43<=#REF!,#REF!,IF(BE43<=#REF!,#REF!,0.05))))))) | BP43: =BO43*SUM(BM43,BJ43,BE43) | BR43: =IF(BH43<=#REF!,#REF!,IF(BH43<=#REF!,#REF!,IF(BH43<=#REF!,#REF!,IF(BH43<=#REF!,#REF!,IF(BH43<=#REF!,#REF!,IF(BH43<=#REF!,#REF!,IF(BH43<=#REF!,#REF!,0.05))))))) | BS43: =BR43*BH43 | BU43: =0.07*SUM(BE43,BJ43,BM43,BP43,BS43) | BW43: =SUM(BU43,BS43,BP43,BM43,BJ43,BE43) | BX43: =SUM(BS43,BP43,BM43,BJ43) | BY43: =BX43/BW43 | CO43: 34000 | CR43: =CO43 | CU43: =CO43+CR43 | CX43: =CU43 | CY43: =IF(CO43<=BQ$6,BP$6,IF(CO43<=BQ$7,BP$7,IF(CO43<=BQ$8,BP$8,IF(CO43<=BQ$9,BP$9,IF(CO43<=BQ$14,BP$14,IF(CO43<=BQ$15,BP$15,IF(CO43<=BQ$16,BP$16,0.05))))))) | CZ43: =CY43*CO43 | DB43: =IF(CR43<=BT$6,BS$6,IF(CR43<=BT$7,BS$7,IF(CR43<=BT$8,BS$8,IF(CR43<=BT$9,BS$9,IF(CR43<=BT$14,BS$14,IF(CR43<=BT$15,BS$15,IF(CR43<=BT$16,BS$16,0.05))))))) | DC43: =DB43*CR43 | DE43: =IF(CU43<=BW$6,BV$6,IF(CU43<=BW$7,BV$7,IF(CU43<=BW$8,BV$8,IF(CU43<=BW$9,BV$9,IF(CU43<=BW$14,BV$14,IF(CU43<=BW$15,BV$15,IF(CU43<=BW$16,BV$16,0.05))))))) | DF43: =DE43*SUM(DC43,CZ43,CU43) | DH43: =IF(CX43<=BZ$6,BY$6,IF(CX43<=BZ$7,BY$7,IF(CX43<=BZ$8,BY$8,IF(CX43<=BZ$9,BY$9,IF(CX43<=BZ$14,BY$14,IF(CX43<=BZ$15,BY$15,IF(CX43<=BZ$16,BY$16,0.05))))))) | DI43: =DH43*CX43 | DK43: =0.07*SUM(CU43,CZ43,DC43,DF43,DI43) | DM43: =SUM(DK43,DI43,DF43,DC43,CZ43,CU43) | DN43: =SUM(DI43,DF43,DC43,CZ43) | DO43: =DN43/DM43
A44: Labor: Guys | B44: Hours | C44: Rate (PW?) | E44: Totals | F44: Labor | N44: 3/8" | O44: SC 50 HP (3/8") | P44: =Q44*R44 | Q44: 120 | R44: =0.55+0.06 | AY44: 35000 | BB44: =AY44 | BE44: =AY44+BB44 | BH44: =BE44 | BI44: =IF(AY44<=#REF!,#REF!,IF(AY44<=#REF!,#REF!,IF(AY44<=#REF!,#REF!,IF(AY44<=#REF!,#REF!,IF(AY44<=#REF!,#REF!,IF(AY44<=#REF!,#REF!,IF(AY44<=#REF!,#REF!,0.05))))))) | BJ44: =BI44*AY44 | BL44: =IF(BB44<=#REF!,#REF!,IF(BB44<=#REF!,#REF!,IF(BB44<=#REF!,#REF!,IF(BB44<=#REF!,#REF!,IF(BB44<=#REF!,#REF!,IF(BB44<=#REF!,#REF!,IF(BB44<=#REF!,#REF!,0.05))))))) | BM44: =BL44*BB44 | BO44: =IF(BE44<=#REF!,#REF!,IF(BE44<=#REF!,#REF!,IF(BE44<=#REF!,#REF!,IF(BE44<=#REF!,#REF!,IF(BE44<=#REF!,#REF!,IF(BE44<=#REF!,#REF!,IF(BE44<=#REF!,#REF!,0.05))))))) | BP44: =BO44*SUM(BM44,BJ44,BE44) | BR44: =IF(BH44<=#REF!,#REF!,IF(BH44<=#REF!,#REF!,IF(BH44<=#REF!,#REF!,IF(BH44<=#REF!,#REF!,IF(BH44<=#REF!,#REF!,IF(BH44<=#REF!,#REF!,IF(BH44<=#REF!,#REF!,0.05))))))) | BS44: =BR44*BH44 | BU44: =0.07*SUM(BE44,BJ44,BM44,BP44,BS44) | BW44: =SUM(BU44,BS44,BP44,BM44,BJ44,BE44) | BX44: =SUM(BS44,BP44,BM44,BJ44) | BY44: =BX44/BW44 | CO44: 35000 | CR44: =CO44 | CU44: =CO44+CR44 | CX44: =CU44 | CY44: =IF(CO44<=BQ$6,BP$6,IF(CO44<=BQ$7,BP$7,IF(CO44<=BQ$8,BP$8,IF(CO44<=BQ$9,BP$9,IF(CO44<=BQ$14,BP$14,IF(CO44<=BQ$15,BP$15,IF(CO44<=BQ$16,BP$16,0.05))))))) | CZ44: =CY44*CO44 | DB44: =IF(CR44<=BT$6,BS$6,IF(CR44<=BT$7,BS$7,IF(CR44<=BT$8,BS$8,IF(CR44<=BT$9,BS$9,IF(CR44<=BT$14,BS$14,IF(CR44<=BT$15,BS$15,IF(CR44<=BT$16,BS$16,0.05))))))) | DC44: =DB44*CR44 | DE44: =IF(CU44<=BW$6,BV$6,IF(CU44<=BW$7,BV$7,IF(CU44<=BW$8,BV$8,IF(CU44<=BW$9,BV$9,IF(CU44<=BW$14,BV$14,IF(CU44<=BW$15,BV$15,IF(CU44<=BW$16,BV$16,0.05))))))) | DF44: =DE44*SUM(DC44,CZ44,CU44) | DH44: =IF(CX44<=BZ$6,BY$6,IF(CX44<=BZ$7,BY$7,IF(CX44<=BZ$8,BY$8,IF(CX44<=BZ$9,BY$9,IF(CX44<=BZ$14,BY$14,IF(CX44<=BZ$15,BY$15,IF(CX44<=BZ$16,BY$16,0.05))))))) | DI44: =DH44*CX44 | DK44: =0.07*SUM(CU44,CZ44,DC44,DF44,DI44) | DM44: =SUM(DK44,DI44,DF44,DC44,CZ44,CU44) | DN44: =SUM(DI44,DF44,DC44,CZ44) | DO44: =DN44/DM44
A45: 8 | B45: 0 | C45: 33.66 | E45: =A45*B45*C45 | F45: Pre-Pours Hours | G45: 8 | AY45: 36000 | BB45: =AY45 | BE45: =AY45+BB45 | BH45: =BE45 | BI45: =IF(AY45<=#REF!,#REF!,IF(AY45<=#REF!,#REF!,IF(AY45<=#REF!,#REF!,IF(AY45<=#REF!,#REF!,IF(AY45<=#REF!,#REF!,IF(AY45<=#REF!,#REF!,IF(AY45<=#REF!,#REF!,0.05))))))) | BJ45: =BI45*AY45 | BL45: =IF(BB45<=#REF!,#REF!,IF(BB45<=#REF!,#REF!,IF(BB45<=#REF!,#REF!,IF(BB45<=#REF!,#REF!,IF(BB45<=#REF!,#REF!,IF(BB45<=#REF!,#REF!,IF(BB45<=#REF!,#REF!,0.05))))))) | BM45: =BL45*BB45 | BO45: =IF(BE45<=#REF!,#REF!,IF(BE45<=#REF!,#REF!,IF(BE45<=#REF!,#REF!,IF(BE45<=#REF!,#REF!,IF(BE45<=#REF!,#REF!,IF(BE45<=#REF!,#REF!,IF(BE45<=#REF!,#REF!,0.05))))))) | BP45: =BO45*SUM(BM45,BJ45,BE45) | BR45: =IF(BH45<=#REF!,#REF!,IF(BH45<=#REF!,#REF!,IF(BH45<=#REF!,#REF!,IF(BH45<=#REF!,#REF!,IF(BH45<=#REF!,#REF!,IF(BH45<=#REF!,#REF!,IF(BH45<=#REF!,#REF!,0.05))))))) | BS45: =BR45*BH45 | BU45: =0.07*SUM(BE45,BJ45,BM45,BP45,BS45) | BW45: =SUM(BU45,BS45,BP45,BM45,BJ45,BE45) | BX45: =SUM(BS45,BP45,BM45,BJ45) | BY45: =BX45/BW45 | CO45: 36000 | CR45: =CO45 | CU45: =CO45+CR45 | CX45: =CU45 | CY45: =IF(CO45<=BQ$6,BP$6,IF(CO45<=BQ$7,BP$7,IF(CO45<=BQ$8,BP$8,IF(CO45<=BQ$9,BP$9,IF(CO45<=BQ$14,BP$14,IF(CO45<=BQ$15,BP$15,IF(CO45<=BQ$16,BP$16,0.05))))))) | CZ45: =CY45*CO45 | DB45: =IF(CR45<=BT$6,BS$6,IF(CR45<=BT$7,BS$7,IF(CR45<=BT$8,BS$8,IF(CR45<=BT$9,BS$9,IF(CR45<=BT$14,BS$14,IF(CR45<=BT$15,BS$15,IF(CR45<=BT$16,BS$16,0.05))))))) | DC45: =DB45*CR45 | DE45: =IF(CU45<=BW$6,BV$6,IF(CU45<=BW$7,BV$7,IF(CU45<=BW$8,BV$8,IF(CU45<=BW$9,BV$9,IF(CU45<=BW$14,BV$14,IF(CU45<=BW$15,BV$15,IF(CU45<=BW$16,BV$16,0.05))))))) | DF45: =DE45*SUM(DC45,CZ45,CU45) | DH45: =IF(CX45<=BZ$6,BY$6,IF(CX45<=BZ$7,BY$7,IF(CX45<=BZ$8,BY$8,IF(CX45<=BZ$9,BY$9,IF(CX45<=BZ$14,BY$14,IF(CX45<=BZ$15,BY$15,IF(CX45<=BZ$16,BY$16,0.05))))))) | DI45: =DH45*CX45 | DK45: =0.07*SUM(CU45,CZ45,DC45,DF45,DI45) | DM45: =SUM(DK45,DI45,DF45,DC45,CZ45,CU45) | DN45: =SUM(DI45,DF45,DC45,CZ45) | DO45: =DN45/DM45
A46: 8 | B46: =T28*G46 | C46: =C45 | E46: =A46*B46*C46 | F46: Prep/Prime/Seal Hours (hrs per mob) | G46: 4 | J46: =P31 | K46: % Soft Surf | O46: mat $ difference | P46: =P37-P42 | R46: =R37-R42 | AY46: 36000 | BB46: =AY46 | BE46: =AY46+BB46 | BH46: =BE46 | BI46: =IF(AY46<=#REF!,#REF!,IF(AY46<=#REF!,#REF!,IF(AY46<=#REF!,#REF!,IF(AY46<=#REF!,#REF!,IF(AY46<=#REF!,#REF!,IF(AY46<=#REF!,#REF!,IF(AY46<=#REF!,#REF!,0.05))))))) | BJ46: =BI46*AY46 | BL46: =IF(BB46<=#REF!,#REF!,IF(BB46<=#REF!,#REF!,IF(BB46<=#REF!,#REF!,IF(BB46<=#REF!,#REF!,IF(BB46<=#REF!,#REF!,IF(BB46<=#REF!,#REF!,IF(BB46<=#REF!,#REF!,0.05))))))) | BM46: =BL46*BB46 | BO46: =IF(BE46<=#REF!,#REF!,IF(BE46<=#REF!,#REF!,IF(BE46<=#REF!,#REF!,IF(BE46<=#REF!,#REF!,IF(BE46<=#REF!,#REF!,IF(BE46<=#REF!,#REF!,IF(BE46<=#REF!,#REF!,0.05))))))) | BP46: =BO46*SUM(BM46,BJ46,BE46) | BR46: =IF(BH46<=#REF!,#REF!,IF(BH46<=#REF!,#REF!,IF(BH46<=#REF!,#REF!,IF(BH46<=#REF!,#REF!,IF(BH46<=#REF!,#REF!,IF(BH46<=#REF!,#REF!,IF(BH46<=#REF!,#REF!,0.05))))))) | BS46: =BR46*BH46 | BU46: =0.07*SUM(BE46,BJ46,BM46,BP46,BS46) | BW46: =SUM(BU46,BS46,BP46,BM46,BJ46,BE46) | BX46: =SUM(BS46,BP46,BM46,BJ46) | BY46: =BX46/BW46 | CO46: 36000 | CR46: =CO46 | CU46: =CO46+CR46 | CX46: =CU46 | CY46: =IF(CO46<=BQ$6,BP$6,IF(CO46<=BQ$7,BP$7,IF(CO46<=BQ$8,BP$8,IF(CO46<=BQ$9,BP$9,IF(CO46<=BQ$14,BP$14,IF(CO46<=BQ$15,BP$15,IF(CO46<=BQ$16,BP$16,0.05))))))) | CZ46: =CY46*CO46 | DB46: =IF(CR46<=BT$6,BS$6,IF(CR46<=BT$7,BS$7,IF(CR46<=BT$8,BS$8,IF(CR46<=BT$9,BS$9,IF(CR46<=BT$14,BS$14,IF(CR46<=BT$15,BS$15,IF(CR46<=BT$16,BS$16,0.05))))))) | DC46: =DB46*CR46 | DE46: =IF(CU46<=BW$6,BV$6,IF(CU46<=BW$7,BV$7,IF(CU46<=BW$8,BV$8,IF(CU46<=BW$9,BV$9,IF(CU46<=BW$14,BV$14,IF(CU46<=BW$15,BV$15,IF(CU46<=BW$16,BV$16,0.05))))))) | DF46: =DE46*SUM(DC46,CZ46,CU46) | DH46: =IF(CX46<=BZ$6,BY$6,IF(CX46<=BZ$7,BY$7,IF(CX46<=BZ$8,BY$8,IF(CX46<=BZ$9,BY$9,IF(CX46<=BZ$14,BY$14,IF(CX46<=BZ$15,BY$15,IF(CX46<=BZ$16,BY$16,0.05))))))) | DI46: =DH46*CX46 | DK46: =0.07*SUM(CU46,CZ46,DC46,DF46,DI46) | DM46: =SUM(DK46,DI46,DF46,DC46,CZ46,CU46) | DN46: =SUM(DI46,DF46,DC46,CZ46) | DO46: =DN46/DM46
A47: 7 | B47: =F24/G47 | C47: =C45 | E47: =A47*B47*C47 | F47: Mat Time Hours (total HSA mat area/rate) | G47: =85*A47 | H47: INCLUDES HARD SURFACE AREAS ONLY | J47: =Q31 | K47: % Hard Surf / Mat | P47: =P38-P43 | R47: =R38-R43
A48: =A46 | B48: =H33/G48 | C48: =C45 | E48: =A48*B48*C48 | F48: Pour Hours (total bags/pump rate) | G48: 75 | J48: =R31 | K48: % Corridors | P48: =P39-P44 | R48: =R39-R44 | AY48: 37000 | BB48: =AY48 | BE48: =AY48+BB48 | BH48: =BE48 | BI48: =IF(AY48<=#REF!,#REF!,IF(AY48<=#REF!,#REF!,IF(AY48<=#REF!,#REF!,IF(AY48<=#REF!,#REF!,IF(AY48<=#REF!,#REF!,IF(AY48<=#REF!,#REF!,IF(AY48<=#REF!,#REF!,0.05))))))) | BJ48: =BI48*AY48 | BL48: =IF(BB48<=#REF!,#REF!,IF(BB48<=#REF!,#REF!,IF(BB48<=#REF!,#REF!,IF(BB48<=#REF!,#REF!,IF(BB48<=#REF!,#REF!,IF(BB48<=#REF!,#REF!,IF(BB48<=#REF!,#REF!,0.05))))))) | BM48: =BL48*BB48 | BO48: =IF(BE48<=#REF!,#REF!,IF(BE48<=#REF!,#REF!,IF(BE48<=#REF!,#REF!,IF(BE48<=#REF!,#REF!,IF(BE48<=#REF!,#REF!,IF(BE48<=#REF!,#REF!,IF(BE48<=#REF!,#REF!,0.05))))))) | BP48: =BO48*SUM(BM48,BJ48,BE48) | BR48: =IF(BH48<=#REF!,#REF!,IF(BH48<=#REF!,#REF!,IF(BH48<=#REF!,#REF!,IF(BH48<=#REF!,#REF!,IF(BH48<=#REF!,#REF!,IF(BH48<=#REF!,#REF!,IF(BH48<=#REF!,#REF!,0.05))))))) | BS48: =BR48*BH48 | BU48: =0.07*SUM(BE48,BJ48,BM48,BP48,BS48) | BW48: =SUM(BU48,BS48,BP48,BM48,BJ48,BE48) | BX48: =SUM(BS48,BP48,BM48,BJ48) | BY48: =BX48/BW48 | CO48: 37000 | CR48: =CO48 | CU48: =CO48+CR48 | CX48: =CU48 | CY48: =IF(CO48<=BQ$6,BP$6,IF(CO48<=BQ$7,BP$7,IF(CO48<=BQ$8,BP$8,IF(CO48<=BQ$9,BP$9,IF(CO48<=BQ$14,BP$14,IF(CO48<=BQ$15,BP$15,IF(CO48<=BQ$16,BP$16,0.05))))))) | CZ48: =CY48*CO48 | DB48: =IF(CR48<=BT$6,BS$6,IF(CR48<=BT$7,BS$7,IF(CR48<=BT$8,BS$8,IF(CR48<=BT$9,BS$9,IF(CR48<=BT$14,BS$14,IF(CR48<=BT$15,BS$15,IF(CR48<=BT$16,BS$16,0.05))))))) | DC48: =DB48*CR48 | DE48: =IF(CU48<=BW$6,BV$6,IF(CU48<=BW$7,BV$7,IF(CU48<=BW$8,BV$8,IF(CU48<=BW$9,BV$9,IF(CU48<=BW$14,BV$14,IF(CU48<=BW$15,BV$15,IF(CU48<=BW$16,BV$16,0.05))))))) | DF48: =DE48*SUM(DC48,CZ48,CU48) | DH48: =IF(CX48<=BZ$6,BY$6,IF(CX48<=BZ$7,BY$7,IF(CX48<=BZ$8,BY$8,IF(CX48<=BZ$9,BY$9,IF(CX48<=BZ$14,BY$14,IF(CX48<=BZ$15,BY$15,IF(CX48<=BZ$16,BY$16,0.05))))))) | DI48: =DH48*CX48 | DK48: =0.07*SUM(CU48,CZ48,DC48,DF48,DI48) | DM48: =SUM(DK48,DI48,DF48,DC48,CZ48,CU48) | DN48: =SUM(DI48,DF48,DC48,CZ48) | DO48: =DN48/DM48
A49: 2 | B49: =G49*H49 | C49: =C45 | D49: for mat ONLY | E49: =A49*B49*C49 | F49: Semi Delivery Unload Hours (Mobz X hr) | G49: 2 | H49: =G55 | I49: # of Mobs -or- | AY49: 37000 | BB49: =AY49 | BE49: =AY49+BB49 | BH49: =BE49 | BI49: =IF(AY49<=#REF!,#REF!,IF(AY49<=#REF!,#REF!,IF(AY49<=#REF!,#REF!,IF(AY49<=#REF!,#REF!,IF(AY49<=#REF!,#REF!,IF(AY49<=#REF!,#REF!,IF(AY49<=#REF!,#REF!,0.05))))))) | BJ49: =BI49*AY49 | BL49: =IF(BB49<=#REF!,#REF!,IF(BB49<=#REF!,#REF!,IF(BB49<=#REF!,#REF!,IF(BB49<=#REF!,#REF!,IF(BB49<=#REF!,#REF!,IF(BB49<=#REF!,#REF!,IF(BB49<=#REF!,#REF!,0.05))))))) | BM49: =BL49*BB49 | BO49: =IF(BE49<=#REF!,#REF!,IF(BE49<=#REF!,#REF!,IF(BE49<=#REF!,#REF!,IF(BE49<=#REF!,#REF!,IF(BE49<=#REF!,#REF!,IF(BE49<=#REF!,#REF!,IF(BE49<=#REF!,#REF!,0.05))))))) | BP49: =BO49*SUM(BM49,BJ49,BE49) | BR49: =IF(BH49<=#REF!,#REF!,IF(BH49<=#REF!,#REF!,IF(BH49<=#REF!,#REF!,IF(BH49<=#REF!,#REF!,IF(BH49<=#REF!,#REF!,IF(BH49<=#REF!,#REF!,IF(BH49<=#REF!,#REF!,0.05))))))) | BS49: =BR49*BH49 | BU49: =0.07*SUM(BE49,BJ49,BM49,BP49,BS49) | BW49: =SUM(BU49,BS49,BP49,BM49,BJ49,BE49) | BX49: =SUM(BS49,BP49,BM49,BJ49) | BY49: =BX49/BW49 | CO49: 37000 | CR49: =CO49 | CU49: =CO49+CR49 | CX49: =CU49 | CY49: =IF(CO49<=BQ$6,BP$6,IF(CO49<=BQ$7,BP$7,IF(CO49<=BQ$8,BP$8,IF(CO49<=BQ$9,BP$9,IF(CO49<=BQ$14,BP$14,IF(CO49<=BQ$15,BP$15,IF(CO49<=BQ$16,BP$16,0.05))))))) | CZ49: =CY49*CO49 | DB49: =IF(CR49<=BT$6,BS$6,IF(CR49<=BT$7,BS$7,IF(CR49<=BT$8,BS$8,IF(CR49<=BT$9,BS$9,IF(CR49<=BT$14,BS$14,IF(CR49<=BT$15,BS$15,IF(CR49<=BT$16,BS$16,0.05))))))) | DC49: =DB49*CR49 | DE49: =IF(CU49<=BW$6,BV$6,IF(CU49<=BW$7,BV$7,IF(CU49<=BW$8,BV$8,IF(CU49<=BW$9,BV$9,IF(CU49<=BW$14,BV$14,IF(CU49<=BW$15,BV$15,IF(CU49<=BW$16,BV$16,0.05))))))) | DF49: =DE49*SUM(DC49,CZ49,CU49) | DH49: =IF(CX49<=BZ$6,BY$6,IF(CX49<=BZ$7,BY$7,IF(CX49<=BZ$8,BY$8,IF(CX49<=BZ$9,BY$9,IF(CX49<=BZ$14,BY$14,IF(CX49<=BZ$15,BY$15,IF(CX49<=BZ$16,BY$16,0.05))))))) | DI49: =DH49*CX49 | DK49: =0.07*SUM(CU49,CZ49,DC49,DF49,DI49) | DM49: =SUM(DK49,DI49,DF49,DC49,CZ49,CU49) | DN49: =SUM(DI49,DF49,DC49,CZ49) | DO49: =DN49/DM49
